Workbook
Name cnhlist: '[1]CNH Prices'!$C$3:$E$47
Name OLE_LINK1: Template!#REF!
Name 首頁日期: Template!#REF!

Sheet Template
C1: 全球市場總覽 | P1: ="Fixed income market analysis "&TEXT(TODAY(),"dd-mmm-yyyy") -> Fixed income market analysis 07-Aug-2026 | S1: 重點發行人市場表現 | AJ1: 美國投資等級債券初級市場 | BB1: 美國投資等級債券初級市場 | BT1: Weely Bond Flow | CK1: 焦點新聞 | DB1: 焦點新聞 | DR1: 焦點新聞 | EG1: 焦點_稀土貿易戰 | EX1: 焦點_私募信貸的隱憂
A5: Fixed Income Markets Frontier | C5: 債市回顧及展望 | Q5: Fixed Income Markets Frontier | S5: 產業 | T5: 公司名稱 | U5: 中文名稱 | V5: 股價/匯價 | W5: 1W %△ | X5: CDS | Y5: 1W △ | Z5: YTD △ | AA5: S&P | AB5: Moody's | AC5: Fitch | AH5: Fixed Income Markets Frontier | AJ5: 11/11~11/17市場回顧 | AX5: =TODAY() -> 46241 | AZ5: Fixed Income Markets Frontier | BB5: Ticker | BC5: 發行人 | BD5: ISIN | BE5: 定價日 | BF5: 發行量(MM) | BH5: 天期 | BI5: 票息 | BJ5: 償債順位 | BK5: 殖利率 | BL5: S&P | BM5: Moody's | BN5: Fitch | BO5: 認購倍數 | BR5: Fixed Income Markets Frontier | BT5: 投資等級債券交易量 Top 20 | CI5: Fixed Income Markets Frontier | CK5: APA / REPSEP | CR5: 迪士尼 (DIS) | CZ5: Fixed Income Markets Frontier | DB5: 優步 (UBER) | DI5: AppLovin (APP) | DP5: Fixed Income Markets Frontier | EE5: Fixed Income Markets Frontier | EG5: 中國稀土出口管制措施 | EN5: 全球稀土出口與精煉比例 | EV5: Fixed Income Markets Frontier | EX5: 近期私募信貸事件
C7: 上週美債10y利率維持10bps之內震盪，全週利率微漲2bps，curve steepen。美國政府結束關門，投資者等待勞動力市場與通膨數據更新。上半週債券交易員大量買入壓注10y美債收益率跌破4%的期權，因為即將公布的一系列數據可能重塑市場對美國經濟前景的預期。上週以來加密貨幣大跌，比特幣抹去今年以來所有漲幅，標普500較全球股指溢價逾50%，上週以來股市的selloff顯示出投機情緒正在退場；目前市場對風險擔憂的情緒略有升溫，部分原因仍來自脆弱的信用相關數據以及偏緊的資金。根據惠譽評級的數據，美國10月份次級車貸違約率創新高，而緊接大空頭Michael Burry質疑科技巨頭通過延長計算設備折舊年限可能在帳面上虛增盈利增速後，新債王Gundlach將矛頭直指私人信貸市場，認為風險正源於對私營企業的危險貸款及對人工智能的過度期待，並可能將全球市場推向新一輪崩盤。資金部分，近幾週一系列短期利率居高不下，SOFR甚至出現自2020年3月疫情高峰以來非加息週期中的單日最大波動，造成市場緊縮的主因是國庫券發行增加，吸走了短期市場現金，令銀行體系流動性減少，以回購為基礎的基準利率進一步高於美聯儲支付給銀行準備金的利率(IORB)水平，而美聯儲的常設回購機制(SRF)近幾週亦被頻繁使用。在風險情緒降溫的上週，多位Fed官員釋出鷹派訊號，期貨市場目前預期美國12月降息1碼的機率僅剩42.9%。 其它市場部分，日圓兌美元匯率跌至155，創今年2月以來新低，預計將促使東京官員行使口頭干預以遏制匯率下滑；美國關稅打擊日本出口，拖累日本Q3 GDP季減年率1.8%，創下六季以來首次萎縮紀錄；澳州10月就業人數增加42200人，高於預估的20000人，顯示就業市場依舊有韌性。 展望本週，美國即將公布一系列數據，重要數據公布時間如下，11/20公布9月非農就業報告、21日為9月實際薪資數據、26日將發布Q3 GDP修正值，當天10月個人所得支出以及PCE指數也將出爐；12/4將公布10月國際貿易報告，5日公布11月就業報告，10日則預定公布11月CPI，緊接著就是今年最後一次的FOMC會議。Fund flow部分，美股連續第9週淨流入($6.4bn)、IG bonds連續29週淨流入($10.9bn)；技術分析部分，雖10y美債利率日線於上週打破向下格局，但週月線仍延續下行趨勢，30y利率目前則來到4.74~4.76%壓力區，向上力道應不至於持續。 | S7: 金融 | T7: =VLOOKUP($AD7,'市場監控 '!$E$7:$W$194,6,FALSE) -> #NAME? | U7: =VLOOKUP($AD7,'市場監控 '!$E$7:$W$194,7,FALSE) -> #NAME? | V7: =VLOOKUP($AD7,'市場監控 '!$E$7:$W$194,8,FALSE) -> - | W7: =VLOOKUP($AD7,'市場監控 '!$E$7:$W$194,10,FALSE) -> - | X7: =VLOOKUP($AD7,'市場監控 '!$E$7:$W$194,12,FALSE) -> - | Y7: =VLOOKUP($AD7,'市場監控 '!$E$7:$W$194,14,FALSE) -> - | Z7: =VLOOKUP($AD7,'市場監控 '!$E$7:$W$194,15,FALSE) -> - | AA7: =VLOOKUP($AD7,'市場監控 '!$E$7:$W$194,17,FALSE) -> #NAME? | AB7: =VLOOKUP($AD7,'市場監控 '!$E$7:$W$194,18,FALSE) -> #NAME? | AC7: =VLOOKUP($AD7,'市場監控 '!$E$7:$W$194,19,FALSE) -> #NAME? | AD7: ANZ AU Equity | AE7: 中國銀行股份有限公司 | AJ7: 上週IG信用利差整體走窄，全週+1~+5bps，US IG widen 2bp，US HY widen 17bps。 S&P將UPS展望調整為負面，UPS信用利差widen 2bps。Moody’s 將 AppLovin 的高級無擔保評級上調至 Baa3，展望為正向。 11/12：IG closed +1/2bps。TMT underperformed，不同發行人漲跌各異(PARA -8, VZ +1, GOOGL +2, META +3, ORCL +13)，ORCL而後有short covering flow 。 初級市場 11/12：4個發行人定價$4.4bn IG bonds，NIC 1bps，認購倍數4x。Host Hotel發行$400mio WNG 3y券，獲得10x的認購峰值。 11/13：6個發行人定價$3.6bn IG bonds，NIC 4bps，認購倍數2.5x。DXC Technology在4年後發行5y券，IPT提供了大約50bps的NIC，由於股市不佳，order book僅$650mio，guidance unchanged。 11/17：10個發行人定價$26.3bn IG bonds，NIC 2bps，認購倍數3.6x。Amazon為近期發行量最大的發行人，定價$15bn債券。由於股市selloff，order book attrition攀高至40%，幾乎是YTD平均21%的兩倍。 | BB7: =VLOOKUP($BD7,NI!$B$5:$AL$2030,6,FALSE) -> #NAME? | BC7: =VLOOKUP($BD7,NI!$B$37:$AL$2030,2,FALSE) -> #NAME? | BD7: =NI!$B65 -> #NAME? | BE7: =VLOOKUP($BD7,NI!$B$5:$AL$2030,11,FALSE) -> #NAME? | BF7: =VLOOKUP($BD7,NI!$B$5:$AL$2030,12,FALSE)/1000000 -> #NAME? | BH7: =IF(ISNUMBER(VLOOKUP($BD7,NI!$B$5:$AL$2030,13,FALSE)),VLOOKUP($BD7,NI!$B$5:$AL$2030,13,FALSE),"-") -> - | BI7: =VLOOKUP($BD7,NI!$B$5:$AL$2030,4,FALSE) -> #NAME? | BJ7: =VLOOKUP($BD7,NI!$B$5:$AL$2030,3,FALSE) -> #NAME? | BK7: =VLOOKUP($BD7,NI!$B$5:$AL$2030,4,FALSE) -> #NAME? | BL7: =IF(LEFT(VLOOKUP($BD7,NI!$B$5:$AL$2030,31,FALSE),1)="#","-",VLOOKUP($BD7,NI!$B$5:$AL$2030,31,FALSE)) -> #NAME? | BM7: =IF(LEFT(VLOOKUP($BD7,NI!$B$5:$AL$2030,32,FALSE),1)="#","-",VLOOKUP($BD7,NI!$B$5:$AL$2030,32,FALSE)) -> #NAME? | BN7: =IF(LEFT(VLOOKUP($BD7,NI!$B$5:$AL$2030,33,FALSE),1)="#","-",VLOOKUP($BD7,NI!$B$5:$AL$2030,33,FALSE)) -> #NAME? | BO7: =VLOOKUP($BD7,NI!$B$5:$AL$2030,22,FALSE) -> #NAME? | BT7: Ticker | BU7: 發行人 | BV7: ISIN | BW7: 票面利率 | BX7: 天期 (y) | BZ7: 償債順位 | CA7: 目前殖利率 | CB7: 筆數 | CC7: 總量 (M) | CD7: S&P | CE7: Moody's | CF7: Fitch | CK7: Repsol 正在考慮將其上游業務與 Apache（以及其他潛在合併夥伴）進行反向合併，這可能為其提供更快速的途徑成為上市公司。目前的細節對我們來說是信用正面的，因為這將意味著更大的規模和更高的多元化，且槓桿率不會有顯著變化。假設上述條件成立，該合併後的實體信用利差可能會tighten 15~20bps ，但需要注意的是，Repsol 仍處於「考慮選項」的階段。APA 應該表現優於市場，因為一些人可能將此視為向其他潛在買家的開放機會。 11/13消息公布後，APA信用利差tighten 7bps，REPSEP信用利差tighten 3bps。 | CR7: 迪士尼獲利優於分析師估計，不過旗下有線電視與傳統電視業務持續萎縮，抵銷串流與主題樂園的亮眼表現，使股價在美股盤前一度下跌逾 5%。回購金額從 $3.5bn提高到$7bn，根據他們提供的指引，這應該會需要發行債券。迪士尼目前有約 $7bn的短期債務，其中大部分可能會尋求再融資。 營收：$22.5bn（低於預期 $22.7bn~22.8bn） EPS：$1.11（優於預期 $1.05~$1.07） 營運利益：$352mio（年增 39%） 11/13財報公布後，DIS股價下跌7.8%。 | DB7: 營收與獲利皆大幅優於預期，受惠於稅務利益與平台用戶成長。Q3行程數創歷史新高，毛利率提升。儘管Q4指引略低於市場預期，管理層強調AI與多元商業模式為未來成長動能。 營收：$13.47bn（年增 20%，優於預期） EPS：$3.11（含 $4.9bn 稅務利益） 淨利：$6.6bn 營業利潤率：8.1%（Adjusted EBITDA $2.3bn，年增 33%） 行程數：3.5bn（年增 22%） 自由現金流：$2.2bn 平台用戶：189m（年增 17%） 11/4消息公布後，UBER股價下跌5.1%。 | DI7: 季度表現穩健，槓桿率現在低於1倍。過去12個月的EBITDA約為$4bn，相較於$3.5bn 的債務，槓桿率為0.9倍，淨槓桿率為0.5倍。第三季FCF達到$1.05bn，過去12個月的FCF為33.4億美元。 營收：$1.41bn（年增 68%，預期 $1.34bn） EPS：$2.45（年增 96%，預期 $2.38） 淨利：$836mio（年增 92%） Adjusted EBITDA：$1.16bn（年增 79%，EBITDA margin 82%） 自由現金流：$1.05bn（年增 92%） 現金與等值資產：$1.7bn 股數：339M（Q3末） 回購：Q3回購1.3M股，總額 $571M；授權擴大 $3.2B，剩餘 $3.3B 11/6消息公布後，APP股價持平。 | EG7: 中國商務部在10/9發布「2025 年第 61 號」公告，自2025年12月起，擴大稀土管制： - 新增五種稀土元素及多項提煉設備。 - 凡產品含有超過 0.1% 中國稀土成分，或使用中國稀土技術者，出口前須申請許可。 - 軍事用途稀土材料全面禁止出口，包括導彈、戰機、潛艦、雷射、測距儀等關鍵零件。 美國對稀土出口管制的回應： - 宣布自 11/1 起（或更早視情況）對中輸美商品加徵額外 100% 關稅，並祭出「關鍵軟體」出口管制。 - 美國與 G7國家（包括歐盟、日本、韓國等）展開協調行動，尋求建立替代稀土供應鏈。 產業影響： - 軍功產業受創：稀土磁鐵是精密導引、隱形技術與高功率馬達的核心元件。 - 半導體與AI產業供應鏈中斷：晶片電容器使用「超純鏑」製造，全球供應幾乎全來自中國無錫市一家精煉廠。 - 電動車與能源產業成本上升：電動車馬達與風力發電機使用大量稀土磁鐵，傳統燃油車也使用稀土磁鐵於座椅、方向盤、煞車系統等。 本次管制清單並未涵蓋全球用量最大的輕稀土「釹」和「鐠」，因為，若全面禁止，將讓全球電動車和風點產業瞬間停擺，也損害中國自身的下游客戶。選擇性的管制重稀土，則達到精準打擊並製造威攝的多重戰略目的。 | EN7: 國家/地區 | EO7: 開採比例 (%) | EP7: 精煉比例 (%) | EQ7: 出口比例 (%) | ER7: 補充說明 | EX7: 事件 | EZ7: 時間 | FA7: 內容 | FD7: 結果 | FH7: 影響
T8: =VLOOKUP($AD8,'市場監控 '!$E$7:$W$194,6,FALSE) -> #NAME? | U8: =VLOOKUP($AD8,'市場監控 '!$E$7:$W$194,7,FALSE) -> #NAME? | V8: =VLOOKUP($AD8,'市場監控 '!$E$7:$W$194,8,FALSE) -> - | W8: =VLOOKUP($AD8,'市場監控 '!$E$7:$W$194,10,FALSE) -> - | X8: =VLOOKUP($AD8,'市場監控 '!$E$7:$W$194,12,FALSE) -> - | Y8: =VLOOKUP($AD8,'市場監控 '!$E$7:$W$194,14,FALSE) -> - | Z8: =VLOOKUP($AD8,'市場監控 '!$E$7:$W$194,15,FALSE) -> - | AA8: =VLOOKUP($AD8,'市場監控 '!$E$7:$W$194,17,FALSE) -> #NAME? | AB8: =VLOOKUP($AD8,'市場監控 '!$E$7:$W$194,18,FALSE) -> #NAME? | AC8: =VLOOKUP($AD8,'市場監控 '!$E$7:$W$194,19,FALSE) -> #NAME? | AD8: CBA AU Equity | AE8: 中國工商銀行股份有限公司 | BB8: =VLOOKUP($BD8,NI!$B$5:$AL$2030,6,FALSE) -> #NAME? | BC8: =VLOOKUP($BD8,NI!$B$37:$AL$2030,2,FALSE) -> #NAME? | BD8: =NI!$B66 -> #NAME? | BE8: =VLOOKUP($BD8,NI!$B$5:$AL$2030,11,FALSE) -> #NAME? | BF8: =VLOOKUP($BD8,NI!$B$5:$AL$2030,12,FALSE)/1000000 -> #NAME? | BH8: =IF(ISNUMBER(VLOOKUP($BD8,NI!$B$5:$AL$2030,13,FALSE)),VLOOKUP($BD8,NI!$B$5:$AL$2030,13,FALSE),"-") -> - | BI8: =VLOOKUP($BD8,NI!$B$5:$AL$2030,4,FALSE) -> #NAME? | BJ8: =VLOOKUP($BD8,NI!$B$5:$AL$2030,3,FALSE) -> #NAME? | BK8: =VLOOKUP($BD8,NI!$B$5:$AL$2030,4,FALSE) -> #NAME? | BL8: =IF(LEFT(VLOOKUP($BD8,NI!$B$5:$AL$2030,31,FALSE),1)="#","-",VLOOKUP($BD8,NI!$B$5:$AL$2030,31,FALSE)) -> #NAME? | BM8: =IF(LEFT(VLOOKUP($BD8,NI!$B$5:$AL$2030,32,FALSE),1)="#","-",VLOOKUP($BD8,NI!$B$5:$AL$2030,32,FALSE)) -> #NAME? | BN8: =IF(LEFT(VLOOKUP($BD8,NI!$B$5:$AL$2030,33,FALSE),1)="#","-",VLOOKUP($BD8,NI!$B$5:$AL$2030,33,FALSE)) -> #NAME? | BO8: =VLOOKUP($BD8,NI!$B$5:$AL$2030,22,FALSE) -> #NAME? | BT8: =VLOOKUP($BV8,TACT!$A$3:$AH$100,2,FALSE) -> #NAME? | BU8: =VLOOKUP($BV8,TACT!$A$3:$AH$100,3,FALSE) -> #NAME? | BV8: =TACT!$A3 -> #NAME? | BW8: =VLOOKUP($BV8,TACT!$A$3:$AH$100,11,FALSE) -> #NAME? | BX8: =VLOOKUP($BV8,TACT!$A$3:$AH$100,5,FALSE) -> #NAME? | BZ8: =VLOOKUP($BV8,TACT!$A$3:$AH$100,4,FALSE) -> #NAME? | CA8: =VLOOKUP($BV8,TACT!$A$3:$AH$100,21,FALSE) -> #NAME? | CB8: =VLOOKUP($BV8,TACT!$A$3:$AH$100,32,FALSE) -> #NAME? | CC8: =VLOOKUP($BV8,TACT!$A$3:$AH$100,33,FALSE) -> #NAME? | CD8: =IF(LEFT(VLOOKUP($BV8,TACT!$A$3:$AH$100,6,FALSE),1)="#","-",VLOOKUP($BV8,TACT!$A$3:$AH$100,6,FALSE)) -> #NAME? | CE8: =IF(LEFT(VLOOKUP($BV8,TACT!$A$3:$AH$100,7,FALSE),1)="#","-",VLOOKUP($BV8,TACT!$A$3:$AH$100,7,FALSE)) -> #NAME? | CF8: =IF(LEFT(VLOOKUP($BV8,TACT!$A$3:$AH$100,8,FALSE),1)="#","-",VLOOKUP($BV8,TACT!$A$3:$AH$100,8,FALSE)) -> #NAME?
T9: =VLOOKUP($AD9,'市場監控 '!$E$7:$W$194,6,FALSE) -> #NAME? | U9: =VLOOKUP($AD9,'市場監控 '!$E$7:$W$194,7,FALSE) -> #NAME? | V9: =VLOOKUP($AD9,'市場監控 '!$E$7:$W$194,8,FALSE) -> - | W9: =VLOOKUP($AD9,'市場監控 '!$E$7:$W$194,10,FALSE) -> - | X9: =VLOOKUP($AD9,'市場監控 '!$E$7:$W$194,12,FALSE) -> - | Y9: =VLOOKUP($AD9,'市場監控 '!$E$7:$W$194,14,FALSE) -> - | Z9: =VLOOKUP($AD9,'市場監控 '!$E$7:$W$194,15,FALSE) -> - | AA9: =VLOOKUP($AD9,'市場監控 '!$E$7:$W$194,17,FALSE) -> #NAME? | AB9: =VLOOKUP($AD9,'市場監控 '!$E$7:$W$194,18,FALSE) -> #NAME? | AC9: =VLOOKUP($AD9,'市場監控 '!$E$7:$W$194,19,FALSE) -> #NAME? | AD9: NAB AU Equity | AE9: 中國建設銀行股份有限公司 | BB9: =VLOOKUP($BD9,NI!$B$5:$AL$2030,6,FALSE) -> #NAME? | BC9: =VLOOKUP($BD9,NI!$B$37:$AL$2030,2,FALSE) -> #NAME? | BD9: =NI!$B67 -> #NAME? | BE9: =VLOOKUP($BD9,NI!$B$5:$AL$2030,11,FALSE) -> #NAME? | BF9: =VLOOKUP($BD9,NI!$B$5:$AL$2030,12,FALSE)/1000000 -> #NAME? | BH9: =IF(ISNUMBER(VLOOKUP($BD9,NI!$B$5:$AL$2030,13,FALSE)),VLOOKUP($BD9,NI!$B$5:$AL$2030,13,FALSE),"-") -> - | BI9: =VLOOKUP($BD9,NI!$B$5:$AL$2030,4,FALSE) -> #NAME? | BJ9: =VLOOKUP($BD9,NI!$B$5:$AL$2030,3,FALSE) -> #NAME? | BK9: =VLOOKUP($BD9,NI!$B$5:$AL$2030,4,FALSE) -> #NAME? | BL9: =IF(LEFT(VLOOKUP($BD9,NI!$B$5:$AL$2030,31,FALSE),1)="#","-",VLOOKUP($BD9,NI!$B$5:$AL$2030,31,FALSE)) -> #NAME? | BM9: =IF(LEFT(VLOOKUP($BD9,NI!$B$5:$AL$2030,32,FALSE),1)="#","-",VLOOKUP($BD9,NI!$B$5:$AL$2030,32,FALSE)) -> #NAME? | BN9: =IF(LEFT(VLOOKUP($BD9,NI!$B$5:$AL$2030,33,FALSE),1)="#","-",VLOOKUP($BD9,NI!$B$5:$AL$2030,33,FALSE)) -> #NAME? | BO9: =VLOOKUP($BD9,NI!$B$5:$AL$2030,22,FALSE) -> #NAME? | BT9: =VLOOKUP($BV9,TACT!$A$3:$AH$100,2,FALSE) -> #NAME? | BU9: =VLOOKUP($BV9,TACT!$A$3:$AH$100,3,FALSE) -> #NAME? | BV9: =TACT!$A4 -> #NAME? | BW9: =VLOOKUP($BV9,TACT!$A$3:$AH$100,11,FALSE) -> #NAME? | BX9: =VLOOKUP($BV9,TACT!$A$3:$AH$100,5,FALSE) -> #NAME? | BZ9: =VLOOKUP($BV9,TACT!$A$3:$AH$100,4,FALSE) -> #NAME? | CA9: =VLOOKUP($BV9,TACT!$A$3:$AH$100,21,FALSE) -> #NAME? | CB9: =VLOOKUP($BV9,TACT!$A$3:$AH$100,32,FALSE) -> #NAME? | CC9: =VLOOKUP($BV9,TACT!$A$3:$AH$100,33,FALSE) -> #NAME? | CD9: =IF(LEFT(VLOOKUP($BV9,TACT!$A$3:$AH$100,6,FALSE),1)="#","-",VLOOKUP($BV9,TACT!$A$3:$AH$100,6,FALSE)) -> #NAME? | CE9: =IF(LEFT(VLOOKUP($BV9,TACT!$A$3:$AH$100,7,FALSE),1)="#","-",VLOOKUP($BV9,TACT!$A$3:$AH$100,7,FALSE)) -> #NAME? | CF9: =IF(LEFT(VLOOKUP($BV9,TACT!$A$3:$AH$100,8,FALSE),1)="#","-",VLOOKUP($BV9,TACT!$A$3:$AH$100,8,FALSE)) -> #NAME? | EN9: 中國 | EO9: 60 | EP9: 90 | EQ9: 60 | ER9: 全球唯一能提供全部17種稀土金屬的國家 | EX9: Tricolor Holdings 與 First Brands Group 破產 | EZ9: 2025年9月 | FA9: 1. Tricolor：二手車貸款機構，疑涉欺詐，導致摩根大通損失1.7億美元。 2. First Brands：汽車零件供應商，依賴私募與對沖基金融資，部分資產重複抵押。約有100~500億美元債務。 | FD9: 1. 多家銀行（如摩根大通、Fifth Third Bancorp）曝險。 2. 私募信貸市場震盪，Blue Owl Capital股價重挫。 | FH9: 1. 引發「蟑螂理論」擔憂：一宗壞帳可能代表更多潛在風險。 2. 信貸品質與放貸審查標準遭質疑。 3. 私募信貸與高收益債市場利差擴大，投資人風險意識升高。
T10: =VLOOKUP($AD10,'市場監控 '!$E$7:$W$194,6,FALSE) -> #NAME? | U10: =VLOOKUP($AD10,'市場監控 '!$E$7:$W$194,7,FALSE) -> #NAME? | V10: =VLOOKUP($AD10,'市場監控 '!$E$7:$W$194,8,FALSE) -> - | W10: =VLOOKUP($AD10,'市場監控 '!$E$7:$W$194,10,FALSE) -> - | X10: =VLOOKUP($AD10,'市場監控 '!$E$7:$W$194,12,FALSE) -> - | Y10: =VLOOKUP($AD10,'市場監控 '!$E$7:$W$194,14,FALSE) -> - | Z10: =VLOOKUP($AD10,'市場監控 '!$E$7:$W$194,15,FALSE) -> - | AA10: =VLOOKUP($AD10,'市場監控 '!$E$7:$W$194,17,FALSE) -> #NAME? | AB10: =VLOOKUP($AD10,'市場監控 '!$E$7:$W$194,18,FALSE) -> #NAME? | AC10: =VLOOKUP($AD10,'市場監控 '!$E$7:$W$194,19,FALSE) -> #NAME? | AD10: WBC AU Equity | AE10: 交通銀行股份有限公司 | BB10: =VLOOKUP($BD10,NI!$B$5:$AL$2030,6,FALSE) -> #NAME? | BC10: =VLOOKUP($BD10,NI!$B$37:$AL$2030,2,FALSE) -> #NAME? | BD10: =NI!$B68 -> #NAME? | BE10: =VLOOKUP($BD10,NI!$B$5:$AL$2030,11,FALSE) -> #NAME? | BF10: =VLOOKUP($BD10,NI!$B$5:$AL$2030,12,FALSE)/1000000 -> #NAME? | BH10: =IF(ISNUMBER(VLOOKUP($BD10,NI!$B$5:$AL$2030,13,FALSE)),VLOOKUP($BD10,NI!$B$5:$AL$2030,13,FALSE),"-") -> - | BI10: =VLOOKUP($BD10,NI!$B$5:$AL$2030,4,FALSE) -> #NAME? | BJ10: =VLOOKUP($BD10,NI!$B$5:$AL$2030,3,FALSE) -> #NAME? | BK10: =VLOOKUP($BD10,NI!$B$5:$AL$2030,4,FALSE) -> #NAME? | BL10: =IF(LEFT(VLOOKUP($BD10,NI!$B$5:$AL$2030,31,FALSE),1)="#","-",VLOOKUP($BD10,NI!$B$5:$AL$2030,31,FALSE)) -> #NAME? | BM10: =IF(LEFT(VLOOKUP($BD10,NI!$B$5:$AL$2030,32,FALSE),1)="#","-",VLOOKUP($BD10,NI!$B$5:$AL$2030,32,FALSE)) -> #NAME? | BN10: =IF(LEFT(VLOOKUP($BD10,NI!$B$5:$AL$2030,33,FALSE),1)="#","-",VLOOKUP($BD10,NI!$B$5:$AL$2030,33,FALSE)) -> #NAME? | BO10: =VLOOKUP($BD10,NI!$B$5:$AL$2030,22,FALSE) -> #NAME? | BT10: =VLOOKUP($BV10,TACT!$A$3:$AH$100,2,FALSE) -> #NAME? | BU10: =VLOOKUP($BV10,TACT!$A$3:$AH$100,3,FALSE) -> #NAME? | BV10: =TACT!$A5 -> #NAME? | BW10: =VLOOKUP($BV10,TACT!$A$3:$AH$100,11,FALSE) -> #NAME? | BX10: =VLOOKUP($BV10,TACT!$A$3:$AH$100,5,FALSE) -> #NAME? | BZ10: =VLOOKUP($BV10,TACT!$A$3:$AH$100,4,FALSE) -> #NAME? | CA10: =VLOOKUP($BV10,TACT!$A$3:$AH$100,21,FALSE) -> #NAME? | CB10: =VLOOKUP($BV10,TACT!$A$3:$AH$100,32,FALSE) -> #NAME? | CC10: =VLOOKUP($BV10,TACT!$A$3:$AH$100,33,FALSE) -> #NAME? | CD10: =IF(LEFT(VLOOKUP($BV10,TACT!$A$3:$AH$100,6,FALSE),1)="#","-",VLOOKUP($BV10,TACT!$A$3:$AH$100,6,FALSE)) -> #NAME? | CE10: =IF(LEFT(VLOOKUP($BV10,TACT!$A$3:$AH$100,7,FALSE),1)="#","-",VLOOKUP($BV10,TACT!$A$3:$AH$100,7,FALSE)) -> #NAME? | CF10: =IF(LEFT(VLOOKUP($BV10,TACT!$A$3:$AH$100,8,FALSE),1)="#","-",VLOOKUP($BV10,TACT!$A$3:$AH$100,8,FALSE)) -> #NAME?
T11: =VLOOKUP($AD11,'市場監控 '!$E$7:$W$194,6,FALSE) -> #NAME? | U11: =VLOOKUP($AD11,'市場監控 '!$E$7:$W$194,7,FALSE) -> #NAME? | V11: =VLOOKUP($AD11,'市場監控 '!$E$7:$W$194,8,FALSE) -> - | W11: =VLOOKUP($AD11,'市場監控 '!$E$7:$W$194,10,FALSE) -> - | X11: =VLOOKUP($AD11,'市場監控 '!$E$7:$W$194,12,FALSE) -> - | Y11: =VLOOKUP($AD11,'市場監控 '!$E$7:$W$194,14,FALSE) -> - | Z11: =VLOOKUP($AD11,'市場監控 '!$E$7:$W$194,15,FALSE) -> - | AA11: =VLOOKUP($AD11,'市場監控 '!$E$7:$W$194,17,FALSE) -> #NAME? | AB11: =VLOOKUP($AD11,'市場監控 '!$E$7:$W$194,18,FALSE) -> #NAME? | AC11: =VLOOKUP($AD11,'市場監控 '!$E$7:$W$194,19,FALSE) -> #NAME? | AD11: BNP FP Equity | AE11: 中國農業銀行股份有限公司 | BB11: =VLOOKUP($BD11,NI!$B$5:$AL$2030,6,FALSE) -> #NAME? | BC11: =VLOOKUP($BD11,NI!$B$37:$AL$2030,2,FALSE) -> #NAME? | BD11: =NI!$B69 -> #NAME? | BE11: =VLOOKUP($BD11,NI!$B$5:$AL$2030,11,FALSE) -> #NAME? | BF11: =VLOOKUP($BD11,NI!$B$5:$AL$2030,12,FALSE)/1000000 -> #NAME? | BH11: =IF(ISNUMBER(VLOOKUP($BD11,NI!$B$5:$AL$2030,13,FALSE)),VLOOKUP($BD11,NI!$B$5:$AL$2030,13,FALSE),"-") -> - | BI11: =VLOOKUP($BD11,NI!$B$5:$AL$2030,4,FALSE) -> #NAME? | BJ11: =VLOOKUP($BD11,NI!$B$5:$AL$2030,3,FALSE) -> #NAME? | BK11: =VLOOKUP($BD11,NI!$B$5:$AL$2030,4,FALSE) -> #NAME? | BL11: =IF(LEFT(VLOOKUP($BD11,NI!$B$5:$AL$2030,31,FALSE),1)="#","-",VLOOKUP($BD11,NI!$B$5:$AL$2030,31,FALSE)) -> #NAME? | BM11: =IF(LEFT(VLOOKUP($BD11,NI!$B$5:$AL$2030,32,FALSE),1)="#","-",VLOOKUP($BD11,NI!$B$5:$AL$2030,32,FALSE)) -> #NAME? | BN11: =IF(LEFT(VLOOKUP($BD11,NI!$B$5:$AL$2030,33,FALSE),1)="#","-",VLOOKUP($BD11,NI!$B$5:$AL$2030,33,FALSE)) -> #NAME? | BO11: =VLOOKUP($BD11,NI!$B$5:$AL$2030,22,FALSE) -> #NAME? | BT11: =VLOOKUP($BV11,TACT!$A$3:$AH$100,2,FALSE) -> #NAME? | BU11: =VLOOKUP($BV11,TACT!$A$3:$AH$100,3,FALSE) -> #NAME? | BV11: =TACT!$A6 -> #NAME? | BW11: =VLOOKUP($BV11,TACT!$A$3:$AH$100,11,FALSE) -> #NAME? | BX11: =VLOOKUP($BV11,TACT!$A$3:$AH$100,5,FALSE) -> #NAME? | BZ11: =VLOOKUP($BV11,TACT!$A$3:$AH$100,4,FALSE) -> #NAME? | CA11: =VLOOKUP($BV11,TACT!$A$3:$AH$100,21,FALSE) -> #NAME? | CB11: =VLOOKUP($BV11,TACT!$A$3:$AH$100,32,FALSE) -> #NAME? | CC11: =VLOOKUP($BV11,TACT!$A$3:$AH$100,33,FALSE) -> #NAME? | CD11: =IF(LEFT(VLOOKUP($BV11,TACT!$A$3:$AH$100,6,FALSE),1)="#","-",VLOOKUP($BV11,TACT!$A$3:$AH$100,6,FALSE)) -> #NAME? | CE11: =IF(LEFT(VLOOKUP($BV11,TACT!$A$3:$AH$100,7,FALSE),1)="#","-",VLOOKUP($BV11,TACT!$A$3:$AH$100,7,FALSE)) -> #NAME? | CF11: =IF(LEFT(VLOOKUP($BV11,TACT!$A$3:$AH$100,8,FALSE),1)="#","-",VLOOKUP($BV11,TACT!$A$3:$AH$100,8,FALSE)) -> #NAME?
T12: =VLOOKUP($AD12,'市場監控 '!$E$7:$W$194,6,FALSE) -> #NAME? | U12: =VLOOKUP($AD12,'市場監控 '!$E$7:$W$194,7,FALSE) -> #NAME? | V12: =VLOOKUP($AD12,'市場監控 '!$E$7:$W$194,8,FALSE) -> - | W12: =VLOOKUP($AD12,'市場監控 '!$E$7:$W$194,10,FALSE) -> - | X12: =VLOOKUP($AD12,'市場監控 '!$E$7:$W$194,12,FALSE) -> - | Y12: =VLOOKUP($AD12,'市場監控 '!$E$7:$W$194,14,FALSE) -> - | Z12: =VLOOKUP($AD12,'市場監控 '!$E$7:$W$194,15,FALSE) -> - | AA12: =VLOOKUP($AD12,'市場監控 '!$E$7:$W$194,17,FALSE) -> #NAME? | AB12: =VLOOKUP($AD12,'市場監控 '!$E$7:$W$194,18,FALSE) -> #NAME? | AC12: =VLOOKUP($AD12,'市場監控 '!$E$7:$W$194,19,FALSE) -> #NAME? | AD12: ACA FP Equity | AE12: 花旗集團 | BB12: =VLOOKUP($BD12,NI!$B$5:$AL$2030,6,FALSE) -> #NAME? | BC12: =VLOOKUP($BD12,NI!$B$37:$AL$2030,2,FALSE) -> #NAME? | BD12: =NI!$B70 -> #NAME? | BE12: =VLOOKUP($BD12,NI!$B$5:$AL$2030,11,FALSE) -> #NAME? | BF12: =VLOOKUP($BD12,NI!$B$5:$AL$2030,12,FALSE)/1000000 -> #NAME? | BH12: =IF(ISNUMBER(VLOOKUP($BD12,NI!$B$5:$AL$2030,13,FALSE)),VLOOKUP($BD12,NI!$B$5:$AL$2030,13,FALSE),"-") -> - | BI12: =VLOOKUP($BD12,NI!$B$5:$AL$2030,4,FALSE) -> #NAME? | BJ12: =VLOOKUP($BD12,NI!$B$5:$AL$2030,3,FALSE) -> #NAME? | BK12: =VLOOKUP($BD12,NI!$B$5:$AL$2030,4,FALSE) -> #NAME? | BL12: =IF(LEFT(VLOOKUP($BD12,NI!$B$5:$AL$2030,31,FALSE),1)="#","-",VLOOKUP($BD12,NI!$B$5:$AL$2030,31,FALSE)) -> #NAME? | BM12: =IF(LEFT(VLOOKUP($BD12,NI!$B$5:$AL$2030,32,FALSE),1)="#","-",VLOOKUP($BD12,NI!$B$5:$AL$2030,32,FALSE)) -> #NAME? | BN12: =IF(LEFT(VLOOKUP($BD12,NI!$B$5:$AL$2030,33,FALSE),1)="#","-",VLOOKUP($BD12,NI!$B$5:$AL$2030,33,FALSE)) -> #NAME? | BO12: =VLOOKUP($BD12,NI!$B$5:$AL$2030,22,FALSE) -> #NAME? | BT12: =VLOOKUP($BV12,TACT!$A$3:$AH$100,2,FALSE) -> #NAME? | BU12: =VLOOKUP($BV12,TACT!$A$3:$AH$100,3,FALSE) -> #NAME? | BV12: =TACT!$A7 -> #NAME? | BW12: =VLOOKUP($BV12,TACT!$A$3:$AH$100,11,FALSE) -> #NAME? | BX12: =VLOOKUP($BV12,TACT!$A$3:$AH$100,5,FALSE) -> #NAME? | BZ12: =VLOOKUP($BV12,TACT!$A$3:$AH$100,4,FALSE) -> #NAME? | CA12: =VLOOKUP($BV12,TACT!$A$3:$AH$100,21,FALSE) -> #NAME? | CB12: =VLOOKUP($BV12,TACT!$A$3:$AH$100,32,FALSE) -> #NAME? | CC12: =VLOOKUP($BV12,TACT!$A$3:$AH$100,33,FALSE) -> #NAME? | CD12: =IF(LEFT(VLOOKUP($BV12,TACT!$A$3:$AH$100,6,FALSE),1)="#","-",VLOOKUP($BV12,TACT!$A$3:$AH$100,6,FALSE)) -> #NAME? | CE12: =IF(LEFT(VLOOKUP($BV12,TACT!$A$3:$AH$100,7,FALSE),1)="#","-",VLOOKUP($BV12,TACT!$A$3:$AH$100,7,FALSE)) -> #NAME? | CF12: =IF(LEFT(VLOOKUP($BV12,TACT!$A$3:$AH$100,8,FALSE),1)="#","-",VLOOKUP($BV12,TACT!$A$3:$AH$100,8,FALSE)) -> #NAME? | EN12: 美國 | EO12: 11 | EP12: 2 | EQ12: 5 | ER12: 主要礦場為加州 Mountain Pass，仍依賴中國精煉
T13: =VLOOKUP($AD13,'市場監控 '!$E$7:$W$194,6,FALSE) -> #NAME? | U13: =VLOOKUP($AD13,'市場監控 '!$E$7:$W$194,7,FALSE) -> #NAME? | V13: =VLOOKUP($AD13,'市場監控 '!$E$7:$W$194,8,FALSE) -> - | W13: =VLOOKUP($AD13,'市場監控 '!$E$7:$W$194,10,FALSE) -> - | X13: =VLOOKUP($AD13,'市場監控 '!$E$7:$W$194,12,FALSE) -> - | Y13: =VLOOKUP($AD13,'市場監控 '!$E$7:$W$194,14,FALSE) -> - | Z13: =VLOOKUP($AD13,'市場監控 '!$E$7:$W$194,15,FALSE) -> - | AA13: =VLOOKUP($AD13,'市場監控 '!$E$7:$W$194,17,FALSE) -> #NAME? | AB13: =VLOOKUP($AD13,'市場監控 '!$E$7:$W$194,18,FALSE) -> #NAME? | AC13: =VLOOKUP($AD13,'市場監控 '!$E$7:$W$194,19,FALSE) -> #NAME? | AD13: KN FP Equity | AE13: 美國銀行 | BB13: =VLOOKUP($BD13,NI!$B$5:$AL$2030,6,FALSE) -> #NAME? | BC13: =VLOOKUP($BD13,NI!$B$37:$AL$2030,2,FALSE) -> #NAME? | BD13: =NI!$B71 -> #NAME? | BE13: =VLOOKUP($BD13,NI!$B$5:$AL$2030,11,FALSE) -> #NAME? | BF13: =VLOOKUP($BD13,NI!$B$5:$AL$2030,12,FALSE)/1000000 -> #NAME? | BH13: =IF(ISNUMBER(VLOOKUP($BD13,NI!$B$5:$AL$2030,13,FALSE)),VLOOKUP($BD13,NI!$B$5:$AL$2030,13,FALSE),"-") -> - | BI13: =VLOOKUP($BD13,NI!$B$5:$AL$2030,4,FALSE) -> #NAME? | BJ13: =VLOOKUP($BD13,NI!$B$5:$AL$2030,3,FALSE) -> #NAME? | BK13: =VLOOKUP($BD13,NI!$B$5:$AL$2030,4,FALSE) -> #NAME? | BL13: =IF(LEFT(VLOOKUP($BD13,NI!$B$5:$AL$2030,31,FALSE),1)="#","-",VLOOKUP($BD13,NI!$B$5:$AL$2030,31,FALSE)) -> #NAME? | BM13: =IF(LEFT(VLOOKUP($BD13,NI!$B$5:$AL$2030,32,FALSE),1)="#","-",VLOOKUP($BD13,NI!$B$5:$AL$2030,32,FALSE)) -> #NAME? | BN13: =IF(LEFT(VLOOKUP($BD13,NI!$B$5:$AL$2030,33,FALSE),1)="#","-",VLOOKUP($BD13,NI!$B$5:$AL$2030,33,FALSE)) -> #NAME? | BO13: =VLOOKUP($BD13,NI!$B$5:$AL$2030,22,FALSE) -> #NAME? | BT13: =VLOOKUP($BV13,TACT!$A$3:$AH$100,2,FALSE) -> #NAME? | BU13: =VLOOKUP($BV13,TACT!$A$3:$AH$100,3,FALSE) -> #NAME? | BV13: =TACT!$A8 -> #NAME? | BW13: =VLOOKUP($BV13,TACT!$A$3:$AH$100,11,FALSE) -> #NAME? | BX13: =VLOOKUP($BV13,TACT!$A$3:$AH$100,5,FALSE) -> #NAME? | BZ13: =VLOOKUP($BV13,TACT!$A$3:$AH$100,4,FALSE) -> #NAME? | CA13: =VLOOKUP($BV13,TACT!$A$3:$AH$100,21,FALSE) -> #NAME? | CB13: =VLOOKUP($BV13,TACT!$A$3:$AH$100,32,FALSE) -> #NAME? | CC13: =VLOOKUP($BV13,TACT!$A$3:$AH$100,33,FALSE) -> #NAME? | CD13: =IF(LEFT(VLOOKUP($BV13,TACT!$A$3:$AH$100,6,FALSE),1)="#","-",VLOOKUP($BV13,TACT!$A$3:$AH$100,6,FALSE)) -> #NAME? | CE13: =IF(LEFT(VLOOKUP($BV13,TACT!$A$3:$AH$100,7,FALSE),1)="#","-",VLOOKUP($BV13,TACT!$A$3:$AH$100,7,FALSE)) -> #NAME? | CF13: =IF(LEFT(VLOOKUP($BV13,TACT!$A$3:$AH$100,8,FALSE),1)="#","-",VLOOKUP($BV13,TACT!$A$3:$AH$100,8,FALSE)) -> #NAME?
T14: =VLOOKUP($AD14,'市場監控 '!$E$7:$W$194,6,FALSE) -> #NAME? | U14: =VLOOKUP($AD14,'市場監控 '!$E$7:$W$194,7,FALSE) -> #NAME? | V14: =VLOOKUP($AD14,'市場監控 '!$E$7:$W$194,8,FALSE) -> - | W14: =VLOOKUP($AD14,'市場監控 '!$E$7:$W$194,10,FALSE) -> - | X14: =VLOOKUP($AD14,'市場監控 '!$E$7:$W$194,12,FALSE) -> - | Y14: =VLOOKUP($AD14,'市場監控 '!$E$7:$W$194,14,FALSE) -> - | Z14: =VLOOKUP($AD14,'市場監控 '!$E$7:$W$194,15,FALSE) -> - | AA14: =VLOOKUP($AD14,'市場監控 '!$E$7:$W$194,17,FALSE) -> #NAME? | AB14: =VLOOKUP($AD14,'市場監控 '!$E$7:$W$194,18,FALSE) -> #NAME? | AC14: =VLOOKUP($AD14,'市場監控 '!$E$7:$W$194,19,FALSE) -> #NAME? | AD14: 3358410Z FP EQUITY | AE14: 摩根大通銀行 | BB14: =VLOOKUP($BD14,NI!$B$5:$AL$2030,6,FALSE) -> #NAME? | BC14: =VLOOKUP($BD14,NI!$B$37:$AL$2030,2,FALSE) -> #NAME? | BD14: =NI!$B72 -> #NAME? | BE14: =VLOOKUP($BD14,NI!$B$5:$AL$2030,11,FALSE) -> #NAME? | BF14: =VLOOKUP($BD14,NI!$B$5:$AL$2030,12,FALSE)/1000000 -> #NAME? | BH14: =IF(ISNUMBER(VLOOKUP($BD14,NI!$B$5:$AL$2030,13,FALSE)),VLOOKUP($BD14,NI!$B$5:$AL$2030,13,FALSE),"-") -> - | BI14: =VLOOKUP($BD14,NI!$B$5:$AL$2030,4,FALSE) -> #NAME? | BJ14: =VLOOKUP($BD14,NI!$B$5:$AL$2030,3,FALSE) -> #NAME? | BK14: =VLOOKUP($BD14,NI!$B$5:$AL$2030,4,FALSE) -> #NAME? | BL14: =IF(LEFT(VLOOKUP($BD14,NI!$B$5:$AL$2030,31,FALSE),1)="#","-",VLOOKUP($BD14,NI!$B$5:$AL$2030,31,FALSE)) -> #NAME? | BM14: =IF(LEFT(VLOOKUP($BD14,NI!$B$5:$AL$2030,32,FALSE),1)="#","-",VLOOKUP($BD14,NI!$B$5:$AL$2030,32,FALSE)) -> #NAME? | BN14: =IF(LEFT(VLOOKUP($BD14,NI!$B$5:$AL$2030,33,FALSE),1)="#","-",VLOOKUP($BD14,NI!$B$5:$AL$2030,33,FALSE)) -> #NAME? | BO14: =VLOOKUP($BD14,NI!$B$5:$AL$2030,22,FALSE) -> #NAME? | BT14: =VLOOKUP($BV14,TACT!$A$3:$AH$100,2,FALSE) -> #NAME? | BU14: =VLOOKUP($BV14,TACT!$A$3:$AH$100,3,FALSE) -> #NAME? | BV14: =TACT!$A9 -> #NAME? | BW14: =VLOOKUP($BV14,TACT!$A$3:$AH$100,11,FALSE) -> #NAME? | BX14: =VLOOKUP($BV14,TACT!$A$3:$AH$100,5,FALSE) -> #NAME? | BZ14: =VLOOKUP($BV14,TACT!$A$3:$AH$100,4,FALSE) -> #NAME? | CA14: =VLOOKUP($BV14,TACT!$A$3:$AH$100,21,FALSE) -> #NAME? | CB14: =VLOOKUP($BV14,TACT!$A$3:$AH$100,32,FALSE) -> #NAME? | CC14: =VLOOKUP($BV14,TACT!$A$3:$AH$100,33,FALSE) -> #NAME? | CD14: =IF(LEFT(VLOOKUP($BV14,TACT!$A$3:$AH$100,6,FALSE),1)="#","-",VLOOKUP($BV14,TACT!$A$3:$AH$100,6,FALSE)) -> #NAME? | CE14: =IF(LEFT(VLOOKUP($BV14,TACT!$A$3:$AH$100,7,FALSE),1)="#","-",VLOOKUP($BV14,TACT!$A$3:$AH$100,7,FALSE)) -> #NAME? | CF14: =IF(LEFT(VLOOKUP($BV14,TACT!$A$3:$AH$100,8,FALSE),1)="#","-",VLOOKUP($BV14,TACT!$A$3:$AH$100,8,FALSE)) -> #NAME?
T15: =VLOOKUP($AD15,'市場監控 '!$E$7:$W$194,6,FALSE) -> #NAME? | U15: =VLOOKUP($AD15,'市場監控 '!$E$7:$W$194,7,FALSE) -> #NAME? | V15: =VLOOKUP($AD15,'市場監控 '!$E$7:$W$194,8,FALSE) -> - | W15: =VLOOKUP($AD15,'市場監控 '!$E$7:$W$194,10,FALSE) -> - | X15: =VLOOKUP($AD15,'市場監控 '!$E$7:$W$194,12,FALSE) -> - | Y15: =VLOOKUP($AD15,'市場監控 '!$E$7:$W$194,14,FALSE) -> - | Z15: =VLOOKUP($AD15,'市場監控 '!$E$7:$W$194,15,FALSE) -> - | AA15: =VLOOKUP($AD15,'市場監控 '!$E$7:$W$194,17,FALSE) -> #NAME? | AB15: =VLOOKUP($AD15,'市場監控 '!$E$7:$W$194,18,FALSE) -> #NAME? | AC15: =VLOOKUP($AD15,'市場監控 '!$E$7:$W$194,19,FALSE) -> #NAME? | AD15: SAN SM Equity | AE15: 富國銀行 | BB15: =VLOOKUP($BD15,NI!$B$5:$AL$2030,6,FALSE) -> #NAME? | BC15: =VLOOKUP($BD15,NI!$B$37:$AL$2030,2,FALSE) -> #NAME? | BD15: =NI!$B73 -> #NAME? | BE15: =VLOOKUP($BD15,NI!$B$5:$AL$2030,11,FALSE) -> #NAME? | BF15: =VLOOKUP($BD15,NI!$B$5:$AL$2030,12,FALSE)/1000000 -> #NAME? | BH15: =IF(ISNUMBER(VLOOKUP($BD15,NI!$B$5:$AL$2030,13,FALSE)),VLOOKUP($BD15,NI!$B$5:$AL$2030,13,FALSE),"-") -> - | BI15: =VLOOKUP($BD15,NI!$B$5:$AL$2030,4,FALSE) -> #NAME? | BJ15: =VLOOKUP($BD15,NI!$B$5:$AL$2030,3,FALSE) -> #NAME? | BK15: =VLOOKUP($BD15,NI!$B$5:$AL$2030,4,FALSE) -> #NAME? | BL15: =IF(LEFT(VLOOKUP($BD15,NI!$B$5:$AL$2030,31,FALSE),1)="#","-",VLOOKUP($BD15,NI!$B$5:$AL$2030,31,FALSE)) -> #NAME? | BM15: =IF(LEFT(VLOOKUP($BD15,NI!$B$5:$AL$2030,32,FALSE),1)="#","-",VLOOKUP($BD15,NI!$B$5:$AL$2030,32,FALSE)) -> #NAME? | BN15: =IF(LEFT(VLOOKUP($BD15,NI!$B$5:$AL$2030,33,FALSE),1)="#","-",VLOOKUP($BD15,NI!$B$5:$AL$2030,33,FALSE)) -> #NAME? | BO15: =VLOOKUP($BD15,NI!$B$5:$AL$2030,22,FALSE) -> #NAME? | BT15: =VLOOKUP($BV15,TACT!$A$3:$AH$100,2,FALSE) -> #NAME? | BU15: =VLOOKUP($BV15,TACT!$A$3:$AH$100,3,FALSE) -> #NAME? | BV15: =TACT!$A10 -> #NAME? | BW15: =VLOOKUP($BV15,TACT!$A$3:$AH$100,11,FALSE) -> #NAME? | BX15: =VLOOKUP($BV15,TACT!$A$3:$AH$100,5,FALSE) -> #NAME? | BZ15: =VLOOKUP($BV15,TACT!$A$3:$AH$100,4,FALSE) -> #NAME? | CA15: =VLOOKUP($BV15,TACT!$A$3:$AH$100,21,FALSE) -> #NAME? | CB15: =VLOOKUP($BV15,TACT!$A$3:$AH$100,32,FALSE) -> #NAME? | CC15: =VLOOKUP($BV15,TACT!$A$3:$AH$100,33,FALSE) -> #NAME? | CD15: =IF(LEFT(VLOOKUP($BV15,TACT!$A$3:$AH$100,6,FALSE),1)="#","-",VLOOKUP($BV15,TACT!$A$3:$AH$100,6,FALSE)) -> #NAME? | CE15: =IF(LEFT(VLOOKUP($BV15,TACT!$A$3:$AH$100,7,FALSE),1)="#","-",VLOOKUP($BV15,TACT!$A$3:$AH$100,7,FALSE)) -> #NAME? | CF15: =IF(LEFT(VLOOKUP($BV15,TACT!$A$3:$AH$100,8,FALSE),1)="#","-",VLOOKUP($BV15,TACT!$A$3:$AH$100,8,FALSE)) -> #NAME? | EN15: 澳洲 | EO15: 5 | EP15: 3 | EQ15: 4 | ER15: 擁有全球第4大蘊藏量，積極擴產與建精煉廠
T16: =VLOOKUP($AD16,'市場監控 '!$E$7:$W$194,6,FALSE) -> #NAME? | U16: =VLOOKUP($AD16,'市場監控 '!$E$7:$W$194,7,FALSE) -> #NAME? | V16: =VLOOKUP($AD16,'市場監控 '!$E$7:$W$194,8,FALSE) -> - | W16: =VLOOKUP($AD16,'市場監控 '!$E$7:$W$194,10,FALSE) -> - | X16: =VLOOKUP($AD16,'市場監控 '!$E$7:$W$194,12,FALSE) -> - | Y16: =VLOOKUP($AD16,'市場監控 '!$E$7:$W$194,14,FALSE) -> - | Z16: =VLOOKUP($AD16,'市場監控 '!$E$7:$W$194,15,FALSE) -> - | AA16: =VLOOKUP($AD16,'市場監控 '!$E$7:$W$194,17,FALSE) -> #NAME? | AB16: =VLOOKUP($AD16,'市場監控 '!$E$7:$W$194,18,FALSE) -> #NAME? | AC16: =VLOOKUP($AD16,'市場監控 '!$E$7:$W$194,19,FALSE) -> #NAME? | AD16: 3988 HK Equity | AE16: 高盛集團 | BB16: =VLOOKUP($BD16,NI!$B$5:$AL$2030,6,FALSE) -> #NAME? | BC16: =VLOOKUP($BD16,NI!$B$37:$AL$2030,2,FALSE) -> #NAME? | BD16: =NI!$B74 -> #NAME? | BE16: =VLOOKUP($BD16,NI!$B$5:$AL$2030,11,FALSE) -> #NAME? | BF16: =VLOOKUP($BD16,NI!$B$5:$AL$2030,12,FALSE)/1000000 -> #NAME? | BH16: =IF(ISNUMBER(VLOOKUP($BD16,NI!$B$5:$AL$2030,13,FALSE)),VLOOKUP($BD16,NI!$B$5:$AL$2030,13,FALSE),"-") -> - | BI16: =VLOOKUP($BD16,NI!$B$5:$AL$2030,4,FALSE) -> #NAME? | BJ16: =VLOOKUP($BD16,NI!$B$5:$AL$2030,3,FALSE) -> #NAME? | BK16: =VLOOKUP($BD16,NI!$B$5:$AL$2030,4,FALSE) -> #NAME? | BL16: =IF(LEFT(VLOOKUP($BD16,NI!$B$5:$AL$2030,31,FALSE),1)="#","-",VLOOKUP($BD16,NI!$B$5:$AL$2030,31,FALSE)) -> #NAME? | BM16: =IF(LEFT(VLOOKUP($BD16,NI!$B$5:$AL$2030,32,FALSE),1)="#","-",VLOOKUP($BD16,NI!$B$5:$AL$2030,32,FALSE)) -> #NAME? | BN16: =IF(LEFT(VLOOKUP($BD16,NI!$B$5:$AL$2030,33,FALSE),1)="#","-",VLOOKUP($BD16,NI!$B$5:$AL$2030,33,FALSE)) -> #NAME? | BO16: =VLOOKUP($BD16,NI!$B$5:$AL$2030,22,FALSE) -> #NAME? | BT16: =VLOOKUP($BV16,TACT!$A$3:$AH$100,2,FALSE) -> #NAME? | BU16: =VLOOKUP($BV16,TACT!$A$3:$AH$100,3,FALSE) -> #NAME? | BV16: =TACT!$A11 -> #NAME? | BW16: =VLOOKUP($BV16,TACT!$A$3:$AH$100,11,FALSE) -> #NAME? | BX16: =VLOOKUP($BV16,TACT!$A$3:$AH$100,5,FALSE) -> #NAME? | BZ16: =VLOOKUP($BV16,TACT!$A$3:$AH$100,4,FALSE) -> #NAME? | CA16: =VLOOKUP($BV16,TACT!$A$3:$AH$100,21,FALSE) -> #NAME? | CB16: =VLOOKUP($BV16,TACT!$A$3:$AH$100,32,FALSE) -> #NAME? | CC16: =VLOOKUP($BV16,TACT!$A$3:$AH$100,33,FALSE) -> #NAME? | CD16: =IF(LEFT(VLOOKUP($BV16,TACT!$A$3:$AH$100,6,FALSE),1)="#","-",VLOOKUP($BV16,TACT!$A$3:$AH$100,6,FALSE)) -> #NAME? | CE16: =IF(LEFT(VLOOKUP($BV16,TACT!$A$3:$AH$100,7,FALSE),1)="#","-",VLOOKUP($BV16,TACT!$A$3:$AH$100,7,FALSE)) -> #NAME? | CF16: =IF(LEFT(VLOOKUP($BV16,TACT!$A$3:$AH$100,8,FALSE),1)="#","-",VLOOKUP($BV16,TACT!$A$3:$AH$100,8,FALSE)) -> #NAME?
T17: =VLOOKUP($AD17,'市場監控 '!$E$7:$W$194,6,FALSE) -> #NAME? | U17: =VLOOKUP($AD17,'市場監控 '!$E$7:$W$194,7,FALSE) -> #NAME? | V17: =VLOOKUP($AD17,'市場監控 '!$E$7:$W$194,8,FALSE) -> - | W17: =VLOOKUP($AD17,'市場監控 '!$E$7:$W$194,10,FALSE) -> - | X17: =VLOOKUP($AD17,'市場監控 '!$E$7:$W$194,12,FALSE) -> - | Y17: =VLOOKUP($AD17,'市場監控 '!$E$7:$W$194,14,FALSE) -> - | Z17: =VLOOKUP($AD17,'市場監控 '!$E$7:$W$194,15,FALSE) -> - | AA17: =VLOOKUP($AD17,'市場監控 '!$E$7:$W$194,17,FALSE) -> #NAME? | AB17: =VLOOKUP($AD17,'市場監控 '!$E$7:$W$194,18,FALSE) -> #NAME? | AC17: =VLOOKUP($AD17,'市場監控 '!$E$7:$W$194,19,FALSE) -> #NAME? | AD17: 1398 HK Equity | AE17: 摩根士丹利 | BB17: =VLOOKUP($BD17,NI!$B$5:$AL$2030,6,FALSE) -> #NAME? | BC17: =VLOOKUP($BD17,NI!$B$37:$AL$2030,2,FALSE) -> #NAME? | BD17: =NI!$B75 -> #NAME? | BE17: =VLOOKUP($BD17,NI!$B$5:$AL$2030,11,FALSE) -> #NAME? | BF17: =VLOOKUP($BD17,NI!$B$5:$AL$2030,12,FALSE)/1000000 -> #NAME? | BH17: =IF(ISNUMBER(VLOOKUP($BD17,NI!$B$5:$AL$2030,13,FALSE)),VLOOKUP($BD17,NI!$B$5:$AL$2030,13,FALSE),"-") -> - | BI17: =VLOOKUP($BD17,NI!$B$5:$AL$2030,4,FALSE) -> #NAME? | BJ17: =VLOOKUP($BD17,NI!$B$5:$AL$2030,3,FALSE) -> #NAME? | BK17: =VLOOKUP($BD17,NI!$B$5:$AL$2030,4,FALSE) -> #NAME? | BL17: =IF(LEFT(VLOOKUP($BD17,NI!$B$5:$AL$2030,31,FALSE),1)="#","-",VLOOKUP($BD17,NI!$B$5:$AL$2030,31,FALSE)) -> #NAME? | BM17: =IF(LEFT(VLOOKUP($BD17,NI!$B$5:$AL$2030,32,FALSE),1)="#","-",VLOOKUP($BD17,NI!$B$5:$AL$2030,32,FALSE)) -> #NAME? | BN17: =IF(LEFT(VLOOKUP($BD17,NI!$B$5:$AL$2030,33,FALSE),1)="#","-",VLOOKUP($BD17,NI!$B$5:$AL$2030,33,FALSE)) -> #NAME? | BO17: =VLOOKUP($BD17,NI!$B$5:$AL$2030,22,FALSE) -> #NAME? | BT17: =VLOOKUP($BV17,TACT!$A$3:$AH$100,2,FALSE) -> #NAME? | BU17: =VLOOKUP($BV17,TACT!$A$3:$AH$100,3,FALSE) -> #NAME? | BV17: =TACT!$A12 -> #NAME? | BW17: =VLOOKUP($BV17,TACT!$A$3:$AH$100,11,FALSE) -> #NAME? | BX17: =VLOOKUP($BV17,TACT!$A$3:$AH$100,5,FALSE) -> #NAME? | BZ17: =VLOOKUP($BV17,TACT!$A$3:$AH$100,4,FALSE) -> #NAME? | CA17: =VLOOKUP($BV17,TACT!$A$3:$AH$100,21,FALSE) -> #NAME? | CB17: =VLOOKUP($BV17,TACT!$A$3:$AH$100,32,FALSE) -> #NAME? | CC17: =VLOOKUP($BV17,TACT!$A$3:$AH$100,33,FALSE) -> #NAME? | CD17: =IF(LEFT(VLOOKUP($BV17,TACT!$A$3:$AH$100,6,FALSE),1)="#","-",VLOOKUP($BV17,TACT!$A$3:$AH$100,6,FALSE)) -> #NAME? | CE17: =IF(LEFT(VLOOKUP($BV17,TACT!$A$3:$AH$100,7,FALSE),1)="#","-",VLOOKUP($BV17,TACT!$A$3:$AH$100,7,FALSE)) -> #NAME? | CF17: =IF(LEFT(VLOOKUP($BV17,TACT!$A$3:$AH$100,8,FALSE),1)="#","-",VLOOKUP($BV17,TACT!$A$3:$AH$100,8,FALSE)) -> #NAME? | EX17: 區域性銀行信貸踩雷 | EZ17: 2025年10月 | FA17: 1. Zions Bancorp與Western Alliance Bancorp爆出貸款損失，部分與Tricolor、First Brands有關。 2. 涉及非存款類金融機構（NDFI）貸款，與私募信貸密切相關。 | FD17: 1. Zions股價暴跌13%，WAL跌逾10%，區域銀行ETF（KRE）單日跌幅達6.2% 2. KBW區域銀行指數創半年最大跌幅。 3. 市場避險情緒升溫，VIX指數飆升。 | FH17: 投資人擔憂私募信貸風險擴散至銀行體系。
T18: =VLOOKUP($AD18,'市場監控 '!$E$7:$W$194,6,FALSE) -> #NAME? | U18: =VLOOKUP($AD18,'市場監控 '!$E$7:$W$194,7,FALSE) -> #NAME? | V18: =VLOOKUP($AD18,'市場監控 '!$E$7:$W$194,8,FALSE) -> - | W18: =VLOOKUP($AD18,'市場監控 '!$E$7:$W$194,10,FALSE) -> - | X18: =VLOOKUP($AD18,'市場監控 '!$E$7:$W$194,12,FALSE) -> - | Y18: =VLOOKUP($AD18,'市場監控 '!$E$7:$W$194,14,FALSE) -> - | Z18: =VLOOKUP($AD18,'市場監控 '!$E$7:$W$194,15,FALSE) -> - | AA18: =VLOOKUP($AD18,'市場監控 '!$E$7:$W$194,17,FALSE) -> #NAME? | AB18: =VLOOKUP($AD18,'市場監控 '!$E$7:$W$194,18,FALSE) -> #NAME? | AC18: =VLOOKUP($AD18,'市場監控 '!$E$7:$W$194,19,FALSE) -> #NAME? | AD18: 939 HK Equity | AE18: 法國巴黎銀行 | BB18: =VLOOKUP($BD18,NI!$B$5:$AL$2030,6,FALSE) -> #NAME? | BC18: =VLOOKUP($BD18,NI!$B$37:$AL$2030,2,FALSE) -> #NAME? | BD18: =NI!$B76 -> #NAME? | BE18: =VLOOKUP($BD18,NI!$B$5:$AL$2030,11,FALSE) -> #NAME? | BF18: =VLOOKUP($BD18,NI!$B$5:$AL$2030,12,FALSE)/1000000 -> #NAME? | BH18: =IF(ISNUMBER(VLOOKUP($BD18,NI!$B$5:$AL$2030,13,FALSE)),VLOOKUP($BD18,NI!$B$5:$AL$2030,13,FALSE),"-") -> - | BI18: =VLOOKUP($BD18,NI!$B$5:$AL$2030,4,FALSE) -> #NAME? | BJ18: =VLOOKUP($BD18,NI!$B$5:$AL$2030,3,FALSE) -> #NAME? | BK18: =VLOOKUP($BD18,NI!$B$5:$AL$2030,4,FALSE) -> #NAME? | BL18: =IF(LEFT(VLOOKUP($BD18,NI!$B$5:$AL$2030,31,FALSE),1)="#","-",VLOOKUP($BD18,NI!$B$5:$AL$2030,31,FALSE)) -> #NAME? | BM18: =IF(LEFT(VLOOKUP($BD18,NI!$B$5:$AL$2030,32,FALSE),1)="#","-",VLOOKUP($BD18,NI!$B$5:$AL$2030,32,FALSE)) -> #NAME? | BN18: =IF(LEFT(VLOOKUP($BD18,NI!$B$5:$AL$2030,33,FALSE),1)="#","-",VLOOKUP($BD18,NI!$B$5:$AL$2030,33,FALSE)) -> #NAME? | BO18: =VLOOKUP($BD18,NI!$B$5:$AL$2030,22,FALSE) -> #NAME? | BT18: =VLOOKUP($BV18,TACT!$A$3:$AH$100,2,FALSE) -> #NAME? | BU18: =VLOOKUP($BV18,TACT!$A$3:$AH$100,3,FALSE) -> #NAME? | BV18: =TACT!$A13 -> #NAME? | BW18: =VLOOKUP($BV18,TACT!$A$3:$AH$100,11,FALSE) -> #NAME? | BX18: =VLOOKUP($BV18,TACT!$A$3:$AH$100,5,FALSE) -> #NAME? | BZ18: =VLOOKUP($BV18,TACT!$A$3:$AH$100,4,FALSE) -> #NAME? | CA18: =VLOOKUP($BV18,TACT!$A$3:$AH$100,21,FALSE) -> #NAME? | CB18: =VLOOKUP($BV18,TACT!$A$3:$AH$100,32,FALSE) -> #NAME? | CC18: =VLOOKUP($BV18,TACT!$A$3:$AH$100,33,FALSE) -> #NAME? | CD18: =IF(LEFT(VLOOKUP($BV18,TACT!$A$3:$AH$100,6,FALSE),1)="#","-",VLOOKUP($BV18,TACT!$A$3:$AH$100,6,FALSE)) -> #NAME? | CE18: =IF(LEFT(VLOOKUP($BV18,TACT!$A$3:$AH$100,7,FALSE),1)="#","-",VLOOKUP($BV18,TACT!$A$3:$AH$100,7,FALSE)) -> #NAME? | CF18: =IF(LEFT(VLOOKUP($BV18,TACT!$A$3:$AH$100,8,FALSE),1)="#","-",VLOOKUP($BV18,TACT!$A$3:$AH$100,8,FALSE)) -> #NAME? | EN18: 緬甸與東南亞 | EO18: 10 | EP18: 2 | EQ18: 10 | ER18: 向中國出口氧化物或原礦，部分具初步分離能力
T19: =VLOOKUP($AD19,'市場監控 '!$E$7:$W$194,6,FALSE) -> #NAME? | U19: =VLOOKUP($AD19,'市場監控 '!$E$7:$W$194,7,FALSE) -> #NAME? | V19: =VLOOKUP($AD19,'市場監控 '!$E$7:$W$194,8,FALSE) -> - | W19: =VLOOKUP($AD19,'市場監控 '!$E$7:$W$194,10,FALSE) -> - | X19: =VLOOKUP($AD19,'市場監控 '!$E$7:$W$194,12,FALSE) -> - | Y19: =VLOOKUP($AD19,'市場監控 '!$E$7:$W$194,14,FALSE) -> - | Z19: =VLOOKUP($AD19,'市場監控 '!$E$7:$W$194,15,FALSE) -> - | AA19: =VLOOKUP($AD19,'市場監控 '!$E$7:$W$194,17,FALSE) -> #NAME? | AB19: =VLOOKUP($AD19,'市場監控 '!$E$7:$W$194,18,FALSE) -> #NAME? | AC19: =VLOOKUP($AD19,'市場監控 '!$E$7:$W$194,19,FALSE) -> #NAME? | AD19: 601288 CH Equity | AE19: 法國興業銀行 | BB19: =VLOOKUP($BD19,NI!$B$5:$AL$2030,6,FALSE) -> #NAME? | BC19: =VLOOKUP($BD19,NI!$B$37:$AL$2030,2,FALSE) -> #NAME? | BD19: =NI!$B77 -> #NAME? | BE19: =VLOOKUP($BD19,NI!$B$5:$AL$2030,11,FALSE) -> #NAME? | BF19: =VLOOKUP($BD19,NI!$B$5:$AL$2030,12,FALSE)/1000000 -> #NAME? | BH19: =IF(ISNUMBER(VLOOKUP($BD19,NI!$B$5:$AL$2030,13,FALSE)),VLOOKUP($BD19,NI!$B$5:$AL$2030,13,FALSE),"-") -> - | BI19: =VLOOKUP($BD19,NI!$B$5:$AL$2030,4,FALSE) -> #NAME? | BJ19: =VLOOKUP($BD19,NI!$B$5:$AL$2030,3,FALSE) -> #NAME? | BK19: =VLOOKUP($BD19,NI!$B$5:$AL$2030,4,FALSE) -> #NAME? | BL19: =IF(LEFT(VLOOKUP($BD19,NI!$B$5:$AL$2030,31,FALSE),1)="#","-",VLOOKUP($BD19,NI!$B$5:$AL$2030,31,FALSE)) -> #NAME? | BM19: =IF(LEFT(VLOOKUP($BD19,NI!$B$5:$AL$2030,32,FALSE),1)="#","-",VLOOKUP($BD19,NI!$B$5:$AL$2030,32,FALSE)) -> #NAME? | BN19: =IF(LEFT(VLOOKUP($BD19,NI!$B$5:$AL$2030,33,FALSE),1)="#","-",VLOOKUP($BD19,NI!$B$5:$AL$2030,33,FALSE)) -> #NAME? | BO19: =VLOOKUP($BD19,NI!$B$5:$AL$2030,22,FALSE) -> #NAME? | BT19: =VLOOKUP($BV19,TACT!$A$3:$AH$100,2,FALSE) -> #NAME? | BU19: =VLOOKUP($BV19,TACT!$A$3:$AH$100,3,FALSE) -> #NAME? | BV19: =TACT!$A14 -> #NAME? | BW19: =VLOOKUP($BV19,TACT!$A$3:$AH$100,11,FALSE) -> #NAME? | BX19: =VLOOKUP($BV19,TACT!$A$3:$AH$100,5,FALSE) -> #NAME? | BZ19: =VLOOKUP($BV19,TACT!$A$3:$AH$100,4,FALSE) -> #NAME? | CA19: =VLOOKUP($BV19,TACT!$A$3:$AH$100,21,FALSE) -> #NAME? | CB19: =VLOOKUP($BV19,TACT!$A$3:$AH$100,32,FALSE) -> #NAME? | CC19: =VLOOKUP($BV19,TACT!$A$3:$AH$100,33,FALSE) -> #NAME? | CD19: =IF(LEFT(VLOOKUP($BV19,TACT!$A$3:$AH$100,6,FALSE),1)="#","-",VLOOKUP($BV19,TACT!$A$3:$AH$100,6,FALSE)) -> #NAME? | CE19: =IF(LEFT(VLOOKUP($BV19,TACT!$A$3:$AH$100,7,FALSE),1)="#","-",VLOOKUP($BV19,TACT!$A$3:$AH$100,7,FALSE)) -> #NAME? | CF19: =IF(LEFT(VLOOKUP($BV19,TACT!$A$3:$AH$100,8,FALSE),1)="#","-",VLOOKUP($BV19,TACT!$A$3:$AH$100,8,FALSE)) -> #NAME?
T20: =VLOOKUP($AD20,'市場監控 '!$E$7:$W$194,6,FALSE) -> #NAME? | U20: =VLOOKUP($AD20,'市場監控 '!$E$7:$W$194,7,FALSE) -> #NAME? | V20: =VLOOKUP($AD20,'市場監控 '!$E$7:$W$194,8,FALSE) -> - | W20: =VLOOKUP($AD20,'市場監控 '!$E$7:$W$194,10,FALSE) -> - | X20: =VLOOKUP($AD20,'市場監控 '!$E$7:$W$194,12,FALSE) -> - | Y20: =VLOOKUP($AD20,'市場監控 '!$E$7:$W$194,14,FALSE) -> - | Z20: =VLOOKUP($AD20,'市場監控 '!$E$7:$W$194,15,FALSE) -> - | AA20: =VLOOKUP($AD20,'市場監控 '!$E$7:$W$194,17,FALSE) -> #NAME? | AB20: =VLOOKUP($AD20,'市場監控 '!$E$7:$W$194,18,FALSE) -> #NAME? | AC20: =VLOOKUP($AD20,'市場監控 '!$E$7:$W$194,19,FALSE) -> #NAME? | AD20: JPM US Equity | AE20: 法國農業信貸銀行 | BB20: =VLOOKUP($BD20,NI!$B$5:$AL$2030,6,FALSE) -> #NAME? | BC20: =VLOOKUP($BD20,NI!$B$37:$AL$2030,2,FALSE) -> #NAME? | BD20: =NI!$B78 -> #NAME? | BE20: =VLOOKUP($BD20,NI!$B$5:$AL$2030,11,FALSE) -> #NAME? | BF20: =VLOOKUP($BD20,NI!$B$5:$AL$2030,12,FALSE)/1000000 -> #NAME? | BH20: =IF(ISNUMBER(VLOOKUP($BD20,NI!$B$5:$AL$2030,13,FALSE)),VLOOKUP($BD20,NI!$B$5:$AL$2030,13,FALSE),"-") -> - | BI20: =VLOOKUP($BD20,NI!$B$5:$AL$2030,4,FALSE) -> #NAME? | BJ20: =VLOOKUP($BD20,NI!$B$5:$AL$2030,3,FALSE) -> #NAME? | BK20: =VLOOKUP($BD20,NI!$B$5:$AL$2030,4,FALSE) -> #NAME? | BL20: =IF(LEFT(VLOOKUP($BD20,NI!$B$5:$AL$2030,31,FALSE),1)="#","-",VLOOKUP($BD20,NI!$B$5:$AL$2030,31,FALSE)) -> #NAME? | BM20: =IF(LEFT(VLOOKUP($BD20,NI!$B$5:$AL$2030,32,FALSE),1)="#","-",VLOOKUP($BD20,NI!$B$5:$AL$2030,32,FALSE)) -> #NAME? | BN20: =IF(LEFT(VLOOKUP($BD20,NI!$B$5:$AL$2030,33,FALSE),1)="#","-",VLOOKUP($BD20,NI!$B$5:$AL$2030,33,FALSE)) -> #NAME? | BO20: =VLOOKUP($BD20,NI!$B$5:$AL$2030,22,FALSE) -> #NAME? | BT20: =VLOOKUP($BV20,TACT!$A$3:$AH$100,2,FALSE) -> #NAME? | BU20: =VLOOKUP($BV20,TACT!$A$3:$AH$100,3,FALSE) -> #NAME? | BV20: =TACT!$A15 -> #NAME? | BW20: =VLOOKUP($BV20,TACT!$A$3:$AH$100,11,FALSE) -> #NAME? | BX20: =VLOOKUP($BV20,TACT!$A$3:$AH$100,5,FALSE) -> #NAME? | BZ20: =VLOOKUP($BV20,TACT!$A$3:$AH$100,4,FALSE) -> #NAME? | CA20: =VLOOKUP($BV20,TACT!$A$3:$AH$100,21,FALSE) -> #NAME? | CB20: =VLOOKUP($BV20,TACT!$A$3:$AH$100,32,FALSE) -> #NAME? | CC20: =VLOOKUP($BV20,TACT!$A$3:$AH$100,33,FALSE) -> #NAME? | CD20: =IF(LEFT(VLOOKUP($BV20,TACT!$A$3:$AH$100,6,FALSE),1)="#","-",VLOOKUP($BV20,TACT!$A$3:$AH$100,6,FALSE)) -> #NAME? | CE20: =IF(LEFT(VLOOKUP($BV20,TACT!$A$3:$AH$100,7,FALSE),1)="#","-",VLOOKUP($BV20,TACT!$A$3:$AH$100,7,FALSE)) -> #NAME? | CF20: =IF(LEFT(VLOOKUP($BV20,TACT!$A$3:$AH$100,8,FALSE),1)="#","-",VLOOKUP($BV20,TACT!$A$3:$AH$100,8,FALSE)) -> #NAME?
T21: =VLOOKUP($AD21,'市場監控 '!$E$7:$W$194,6,FALSE) -> #NAME? | U21: =VLOOKUP($AD21,'市場監控 '!$E$7:$W$194,7,FALSE) -> #NAME? | V21: =VLOOKUP($AD21,'市場監控 '!$E$7:$W$194,8,FALSE) -> - | W21: =VLOOKUP($AD21,'市場監控 '!$E$7:$W$194,10,FALSE) -> - | X21: =VLOOKUP($AD21,'市場監控 '!$E$7:$W$194,12,FALSE) -> - | Y21: =VLOOKUP($AD21,'市場監控 '!$E$7:$W$194,14,FALSE) -> - | Z21: =VLOOKUP($AD21,'市場監控 '!$E$7:$W$194,15,FALSE) -> - | AA21: =VLOOKUP($AD21,'市場監控 '!$E$7:$W$194,17,FALSE) -> #NAME? | AB21: =VLOOKUP($AD21,'市場監控 '!$E$7:$W$194,18,FALSE) -> #NAME? | AC21: =VLOOKUP($AD21,'市場監控 '!$E$7:$W$194,19,FALSE) -> #NAME? | AD21: GLE FP Equity | AE21: 法國外貿銀行股份有限公司 | BB21: =VLOOKUP($BD21,NI!$B$5:$AL$2030,6,FALSE) -> #NAME? | BC21: =VLOOKUP($BD21,NI!$B$37:$AL$2030,2,FALSE) -> #NAME? | BD21: =NI!$B79 -> #NAME? | BE21: =VLOOKUP($BD21,NI!$B$5:$AL$2030,11,FALSE) -> #NAME? | BF21: =VLOOKUP($BD21,NI!$B$5:$AL$2030,12,FALSE)/1000000 -> #NAME? | BH21: =IF(ISNUMBER(VLOOKUP($BD21,NI!$B$5:$AL$2030,13,FALSE)),VLOOKUP($BD21,NI!$B$5:$AL$2030,13,FALSE),"-") -> - | BI21: =VLOOKUP($BD21,NI!$B$5:$AL$2030,4,FALSE) -> #NAME? | BJ21: =VLOOKUP($BD21,NI!$B$5:$AL$2030,3,FALSE) -> #NAME? | BK21: =VLOOKUP($BD21,NI!$B$5:$AL$2030,4,FALSE) -> #NAME? | BL21: =IF(LEFT(VLOOKUP($BD21,NI!$B$5:$AL$2030,31,FALSE),1)="#","-",VLOOKUP($BD21,NI!$B$5:$AL$2030,31,FALSE)) -> #NAME? | BM21: =IF(LEFT(VLOOKUP($BD21,NI!$B$5:$AL$2030,32,FALSE),1)="#","-",VLOOKUP($BD21,NI!$B$5:$AL$2030,32,FALSE)) -> #NAME? | BN21: =IF(LEFT(VLOOKUP($BD21,NI!$B$5:$AL$2030,33,FALSE),1)="#","-",VLOOKUP($BD21,NI!$B$5:$AL$2030,33,FALSE)) -> #NAME? | BO21: =VLOOKUP($BD21,NI!$B$5:$AL$2030,22,FALSE) -> #NAME? | BT21: =VLOOKUP($BV21,TACT!$A$3:$AH$100,2,FALSE) -> #NAME? | BU21: =VLOOKUP($BV21,TACT!$A$3:$AH$100,3,FALSE) -> #NAME? | BV21: =TACT!$A16 -> #NAME? | BW21: =VLOOKUP($BV21,TACT!$A$3:$AH$100,11,FALSE) -> #NAME? | BX21: =VLOOKUP($BV21,TACT!$A$3:$AH$100,5,FALSE) -> #NAME? | BZ21: =VLOOKUP($BV21,TACT!$A$3:$AH$100,4,FALSE) -> #NAME? | CA21: =VLOOKUP($BV21,TACT!$A$3:$AH$100,21,FALSE) -> #NAME? | CB21: =VLOOKUP($BV21,TACT!$A$3:$AH$100,32,FALSE) -> #NAME? | CC21: =VLOOKUP($BV21,TACT!$A$3:$AH$100,33,FALSE) -> #NAME? | CD21: =IF(LEFT(VLOOKUP($BV21,TACT!$A$3:$AH$100,6,FALSE),1)="#","-",VLOOKUP($BV21,TACT!$A$3:$AH$100,6,FALSE)) -> #NAME? | CE21: =IF(LEFT(VLOOKUP($BV21,TACT!$A$3:$AH$100,7,FALSE),1)="#","-",VLOOKUP($BV21,TACT!$A$3:$AH$100,7,FALSE)) -> #NAME? | CF21: =IF(LEFT(VLOOKUP($BV21,TACT!$A$3:$AH$100,8,FALSE),1)="#","-",VLOOKUP($BV21,TACT!$A$3:$AH$100,8,FALSE)) -> #NAME? | EN21: 加拿大 | EO21: 7 | EP21: 2 | EQ21: 3 | ER21: 擁有全球最大稀土氧化物蘊藏量之一，尚在開發階段
T22: =VLOOKUP($AD22,'市場監控 '!$E$7:$W$194,6,FALSE) -> #NAME? | U22: =VLOOKUP($AD22,'市場監控 '!$E$7:$W$194,7,FALSE) -> #NAME? | V22: =VLOOKUP($AD22,'市場監控 '!$E$7:$W$194,8,FALSE) -> - | W22: =VLOOKUP($AD22,'市場監控 '!$E$7:$W$194,10,FALSE) -> - | X22: =VLOOKUP($AD22,'市場監控 '!$E$7:$W$194,12,FALSE) -> - | Y22: =VLOOKUP($AD22,'市場監控 '!$E$7:$W$194,14,FALSE) -> - | Z22: =VLOOKUP($AD22,'市場監控 '!$E$7:$W$194,15,FALSE) -> - | AA22: =VLOOKUP($AD22,'市場監控 '!$E$7:$W$194,17,FALSE) -> #NAME? | AB22: =VLOOKUP($AD22,'市場監控 '!$E$7:$W$194,18,FALSE) -> #NAME? | AC22: =VLOOKUP($AD22,'市場監控 '!$E$7:$W$194,19,FALSE) -> #NAME? | AD22: DBK GR Equity | AE22: BPCE有限責任公司 | BB22: =VLOOKUP($BD22,NI!$B$5:$AL$2030,6,FALSE) -> #NAME? | BC22: =VLOOKUP($BD22,NI!$B$37:$AL$2030,2,FALSE) -> #NAME? | BD22: =NI!$B80 -> #NAME? | BE22: =VLOOKUP($BD22,NI!$B$5:$AL$2030,11,FALSE) -> #NAME? | BF22: =VLOOKUP($BD22,NI!$B$5:$AL$2030,12,FALSE)/1000000 -> #NAME? | BH22: =IF(ISNUMBER(VLOOKUP($BD22,NI!$B$5:$AL$2030,13,FALSE)),VLOOKUP($BD22,NI!$B$5:$AL$2030,13,FALSE),"-") -> - | BI22: =VLOOKUP($BD22,NI!$B$5:$AL$2030,4,FALSE) -> #NAME? | BJ22: =VLOOKUP($BD22,NI!$B$5:$AL$2030,3,FALSE) -> #NAME? | BK22: =VLOOKUP($BD22,NI!$B$5:$AL$2030,4,FALSE) -> #NAME? | BL22: =IF(LEFT(VLOOKUP($BD22,NI!$B$5:$AL$2030,31,FALSE),1)="#","-",VLOOKUP($BD22,NI!$B$5:$AL$2030,31,FALSE)) -> #NAME? | BM22: =IF(LEFT(VLOOKUP($BD22,NI!$B$5:$AL$2030,32,FALSE),1)="#","-",VLOOKUP($BD22,NI!$B$5:$AL$2030,32,FALSE)) -> #NAME? | BN22: =IF(LEFT(VLOOKUP($BD22,NI!$B$5:$AL$2030,33,FALSE),1)="#","-",VLOOKUP($BD22,NI!$B$5:$AL$2030,33,FALSE)) -> #NAME? | BO22: =VLOOKUP($BD22,NI!$B$5:$AL$2030,22,FALSE) -> #NAME? | BT22: =VLOOKUP($BV22,TACT!$A$3:$AH$100,2,FALSE) -> #NAME? | BU22: =VLOOKUP($BV22,TACT!$A$3:$AH$100,3,FALSE) -> #NAME? | BV22: =TACT!$A17 -> #NAME? | BW22: =VLOOKUP($BV22,TACT!$A$3:$AH$100,11,FALSE) -> #NAME? | BX22: =VLOOKUP($BV22,TACT!$A$3:$AH$100,5,FALSE) -> #NAME? | BZ22: =VLOOKUP($BV22,TACT!$A$3:$AH$100,4,FALSE) -> #NAME? | CA22: =VLOOKUP($BV22,TACT!$A$3:$AH$100,21,FALSE) -> #NAME? | CB22: =VLOOKUP($BV22,TACT!$A$3:$AH$100,32,FALSE) -> #NAME? | CC22: =VLOOKUP($BV22,TACT!$A$3:$AH$100,33,FALSE) -> #NAME? | CD22: =IF(LEFT(VLOOKUP($BV22,TACT!$A$3:$AH$100,6,FALSE),1)="#","-",VLOOKUP($BV22,TACT!$A$3:$AH$100,6,FALSE)) -> #NAME? | CE22: =IF(LEFT(VLOOKUP($BV22,TACT!$A$3:$AH$100,7,FALSE),1)="#","-",VLOOKUP($BV22,TACT!$A$3:$AH$100,7,FALSE)) -> #NAME? | CF22: =IF(LEFT(VLOOKUP($BV22,TACT!$A$3:$AH$100,8,FALSE),1)="#","-",VLOOKUP($BV22,TACT!$A$3:$AH$100,8,FALSE)) -> #NAME?
T23: =VLOOKUP($AD23,'市場監控 '!$E$7:$W$194,6,FALSE) -> #NAME? | U23: =VLOOKUP($AD23,'市場監控 '!$E$7:$W$194,7,FALSE) -> #NAME? | V23: =VLOOKUP($AD23,'市場監控 '!$E$7:$W$194,8,FALSE) -> - | W23: =VLOOKUP($AD23,'市場監控 '!$E$7:$W$194,10,FALSE) -> - | X23: =VLOOKUP($AD23,'市場監控 '!$E$7:$W$194,12,FALSE) -> - | Y23: =VLOOKUP($AD23,'市場監控 '!$E$7:$W$194,14,FALSE) -> - | Z23: =VLOOKUP($AD23,'市場監控 '!$E$7:$W$194,15,FALSE) -> - | AA23: =VLOOKUP($AD23,'市場監控 '!$E$7:$W$194,17,FALSE) -> #NAME? | AB23: =VLOOKUP($AD23,'市場監控 '!$E$7:$W$194,18,FALSE) -> #NAME? | AC23: =VLOOKUP($AD23,'市場監控 '!$E$7:$W$194,19,FALSE) -> #NAME? | AD23: CBK GR Equity | AE23: 匯豐控股 | BB23: =VLOOKUP($BD23,NI!$B$5:$AL$2030,6,FALSE) -> #NAME? | BC23: =VLOOKUP($BD23,NI!$B$37:$AL$2030,2,FALSE) -> #NAME? | BD23: =NI!$B81 -> #NAME? | BE23: =VLOOKUP($BD23,NI!$B$5:$AL$2030,11,FALSE) -> #NAME? | BF23: =VLOOKUP($BD23,NI!$B$5:$AL$2030,12,FALSE)/1000000 -> #NAME? | BH23: =IF(ISNUMBER(VLOOKUP($BD23,NI!$B$5:$AL$2030,13,FALSE)),VLOOKUP($BD23,NI!$B$5:$AL$2030,13,FALSE),"-") -> - | BI23: =VLOOKUP($BD23,NI!$B$5:$AL$2030,4,FALSE) -> #NAME? | BJ23: =VLOOKUP($BD23,NI!$B$5:$AL$2030,3,FALSE) -> #NAME? | BK23: =VLOOKUP($BD23,NI!$B$5:$AL$2030,4,FALSE) -> #NAME? | BL23: =IF(LEFT(VLOOKUP($BD23,NI!$B$5:$AL$2030,31,FALSE),1)="#","-",VLOOKUP($BD23,NI!$B$5:$AL$2030,31,FALSE)) -> #NAME? | BM23: =IF(LEFT(VLOOKUP($BD23,NI!$B$5:$AL$2030,32,FALSE),1)="#","-",VLOOKUP($BD23,NI!$B$5:$AL$2030,32,FALSE)) -> #NAME? | BN23: =IF(LEFT(VLOOKUP($BD23,NI!$B$5:$AL$2030,33,FALSE),1)="#","-",VLOOKUP($BD23,NI!$B$5:$AL$2030,33,FALSE)) -> #NAME? | BO23: =VLOOKUP($BD23,NI!$B$5:$AL$2030,22,FALSE) -> #NAME? | BT23: =VLOOKUP($BV23,TACT!$A$3:$AH$100,2,FALSE) -> #NAME? | BU23: =VLOOKUP($BV23,TACT!$A$3:$AH$100,3,FALSE) -> #NAME? | BV23: =TACT!$A18 -> #NAME? | BW23: =VLOOKUP($BV23,TACT!$A$3:$AH$100,11,FALSE) -> #NAME? | BX23: =VLOOKUP($BV23,TACT!$A$3:$AH$100,5,FALSE) -> #NAME? | BZ23: =VLOOKUP($BV23,TACT!$A$3:$AH$100,4,FALSE) -> #NAME? | CA23: =VLOOKUP($BV23,TACT!$A$3:$AH$100,21,FALSE) -> #NAME? | CB23: =VLOOKUP($BV23,TACT!$A$3:$AH$100,32,FALSE) -> #NAME? | CC23: =VLOOKUP($BV23,TACT!$A$3:$AH$100,33,FALSE) -> #NAME? | CD23: =IF(LEFT(VLOOKUP($BV23,TACT!$A$3:$AH$100,6,FALSE),1)="#","-",VLOOKUP($BV23,TACT!$A$3:$AH$100,6,FALSE)) -> #NAME? | CE23: =IF(LEFT(VLOOKUP($BV23,TACT!$A$3:$AH$100,7,FALSE),1)="#","-",VLOOKUP($BV23,TACT!$A$3:$AH$100,7,FALSE)) -> #NAME? | CF23: =IF(LEFT(VLOOKUP($BV23,TACT!$A$3:$AH$100,8,FALSE),1)="#","-",VLOOKUP($BV23,TACT!$A$3:$AH$100,8,FALSE)) -> #NAME?
T24: =VLOOKUP($AD24,'市場監控 '!$E$7:$W$194,6,FALSE) -> #NAME? | U24: =VLOOKUP($AD24,'市場監控 '!$E$7:$W$194,7,FALSE) -> #NAME? | V24: =VLOOKUP($AD24,'市場監控 '!$E$7:$W$194,8,FALSE) -> - | W24: =VLOOKUP($AD24,'市場監控 '!$E$7:$W$194,10,FALSE) -> - | X24: =VLOOKUP($AD24,'市場監控 '!$E$7:$W$194,12,FALSE) -> - | Y24: =VLOOKUP($AD24,'市場監控 '!$E$7:$W$194,14,FALSE) -> - | Z24: =VLOOKUP($AD24,'市場監控 '!$E$7:$W$194,15,FALSE) -> - | AA24: =VLOOKUP($AD24,'市場監控 '!$E$7:$W$194,17,FALSE) -> #NAME? | AB24: =VLOOKUP($AD24,'市場監控 '!$E$7:$W$194,18,FALSE) -> #NAME? | AC24: =VLOOKUP($AD24,'市場監控 '!$E$7:$W$194,19,FALSE) -> #NAME? | AD24: ABN NA Equity | AE24: 渣打集團 | BB24: =VLOOKUP($BD24,NI!$B$5:$AL$2030,6,FALSE) -> #NAME? | BC24: =VLOOKUP($BD24,NI!$B$37:$AL$2030,2,FALSE) -> #NAME? | BD24: =NI!$B82 -> #NAME? | BE24: =VLOOKUP($BD24,NI!$B$5:$AL$2030,11,FALSE) -> #NAME? | BF24: =VLOOKUP($BD24,NI!$B$5:$AL$2030,12,FALSE)/1000000 -> #NAME? | BH24: =IF(ISNUMBER(VLOOKUP($BD24,NI!$B$5:$AL$2030,13,FALSE)),VLOOKUP($BD24,NI!$B$5:$AL$2030,13,FALSE),"-") -> - | BI24: =VLOOKUP($BD24,NI!$B$5:$AL$2030,4,FALSE) -> #NAME? | BJ24: =VLOOKUP($BD24,NI!$B$5:$AL$2030,3,FALSE) -> #NAME? | BK24: =VLOOKUP($BD24,NI!$B$5:$AL$2030,4,FALSE) -> #NAME? | BL24: =IF(LEFT(VLOOKUP($BD24,NI!$B$5:$AL$2030,31,FALSE),1)="#","-",VLOOKUP($BD24,NI!$B$5:$AL$2030,31,FALSE)) -> #NAME? | BM24: =IF(LEFT(VLOOKUP($BD24,NI!$B$5:$AL$2030,32,FALSE),1)="#","-",VLOOKUP($BD24,NI!$B$5:$AL$2030,32,FALSE)) -> #NAME? | BN24: =IF(LEFT(VLOOKUP($BD24,NI!$B$5:$AL$2030,33,FALSE),1)="#","-",VLOOKUP($BD24,NI!$B$5:$AL$2030,33,FALSE)) -> #NAME? | BO24: =VLOOKUP($BD24,NI!$B$5:$AL$2030,22,FALSE) -> #NAME? | BT24: =VLOOKUP($BV24,TACT!$A$3:$AH$100,2,FALSE) -> #NAME? | BU24: =VLOOKUP($BV24,TACT!$A$3:$AH$100,3,FALSE) -> #NAME? | BV24: =TACT!$A19 -> #NAME? | BW24: =VLOOKUP($BV24,TACT!$A$3:$AH$100,11,FALSE) -> #NAME? | BX24: =VLOOKUP($BV24,TACT!$A$3:$AH$100,5,FALSE) -> #NAME? | BZ24: =VLOOKUP($BV24,TACT!$A$3:$AH$100,4,FALSE) -> #NAME? | CA24: =VLOOKUP($BV24,TACT!$A$3:$AH$100,21,FALSE) -> #NAME? | CB24: =VLOOKUP($BV24,TACT!$A$3:$AH$100,32,FALSE) -> #NAME? | CC24: =VLOOKUP($BV24,TACT!$A$3:$AH$100,33,FALSE) -> #NAME? | CD24: =IF(LEFT(VLOOKUP($BV24,TACT!$A$3:$AH$100,6,FALSE),1)="#","-",VLOOKUP($BV24,TACT!$A$3:$AH$100,6,FALSE)) -> #NAME? | CE24: =IF(LEFT(VLOOKUP($BV24,TACT!$A$3:$AH$100,7,FALSE),1)="#","-",VLOOKUP($BV24,TACT!$A$3:$AH$100,7,FALSE)) -> #NAME? | CF24: =IF(LEFT(VLOOKUP($BV24,TACT!$A$3:$AH$100,8,FALSE),1)="#","-",VLOOKUP($BV24,TACT!$A$3:$AH$100,8,FALSE)) -> #NAME? | EN24: 歐洲 | EO24: 7 | EP24: 1 | EQ24: 2 | ER24: 歐盟目標2030年滿足20%內部需求
T25: =VLOOKUP($AD25,'市場監控 '!$E$7:$W$194,6,FALSE) -> #NAME? | U25: =VLOOKUP($AD25,'市場監控 '!$E$7:$W$194,7,FALSE) -> #NAME? | V25: =VLOOKUP($AD25,'市場監控 '!$E$7:$W$194,8,FALSE) -> - | W25: =VLOOKUP($AD25,'市場監控 '!$E$7:$W$194,10,FALSE) -> - | X25: =VLOOKUP($AD25,'市場監控 '!$E$7:$W$194,12,FALSE) -> - | Y25: =VLOOKUP($AD25,'市場監控 '!$E$7:$W$194,14,FALSE) -> - | Z25: =VLOOKUP($AD25,'市場監控 '!$E$7:$W$194,15,FALSE) -> - | AA25: =VLOOKUP($AD25,'市場監控 '!$E$7:$W$194,17,FALSE) -> #NAME? | AB25: =VLOOKUP($AD25,'市場監控 '!$E$7:$W$194,18,FALSE) -> #NAME? | AC25: =VLOOKUP($AD25,'市場監控 '!$E$7:$W$194,19,FALSE) -> #NAME? | AD25: BBVA SM Equity | AE25: 巴克萊集團 | BB25: =VLOOKUP($BD25,NI!$B$5:$AL$2030,6,FALSE) -> #NAME? | BC25: =VLOOKUP($BD25,NI!$B$37:$AL$2030,2,FALSE) -> #NAME? | BD25: =NI!$B83 -> #NAME? | BE25: =VLOOKUP($BD25,NI!$B$5:$AL$2030,11,FALSE) -> #NAME? | BF25: =VLOOKUP($BD25,NI!$B$5:$AL$2030,12,FALSE)/1000000 -> #NAME? | BH25: =IF(ISNUMBER(VLOOKUP($BD25,NI!$B$5:$AL$2030,13,FALSE)),VLOOKUP($BD25,NI!$B$5:$AL$2030,13,FALSE),"-") -> - | BI25: =VLOOKUP($BD25,NI!$B$5:$AL$2030,4,FALSE) -> #NAME? | BJ25: =VLOOKUP($BD25,NI!$B$5:$AL$2030,3,FALSE) -> #NAME? | BK25: =VLOOKUP($BD25,NI!$B$5:$AL$2030,4,FALSE) -> #NAME? | BL25: =IF(LEFT(VLOOKUP($BD25,NI!$B$5:$AL$2030,31,FALSE),1)="#","-",VLOOKUP($BD25,NI!$B$5:$AL$2030,31,FALSE)) -> #NAME? | BM25: =IF(LEFT(VLOOKUP($BD25,NI!$B$5:$AL$2030,32,FALSE),1)="#","-",VLOOKUP($BD25,NI!$B$5:$AL$2030,32,FALSE)) -> #NAME? | BN25: =IF(LEFT(VLOOKUP($BD25,NI!$B$5:$AL$2030,33,FALSE),1)="#","-",VLOOKUP($BD25,NI!$B$5:$AL$2030,33,FALSE)) -> #NAME? | BO25: =VLOOKUP($BD25,NI!$B$5:$AL$2030,22,FALSE) -> #NAME? | BT25: =VLOOKUP($BV25,TACT!$A$3:$AH$100,2,FALSE) -> #NAME? | BU25: =VLOOKUP($BV25,TACT!$A$3:$AH$100,3,FALSE) -> #NAME? | BV25: =TACT!$A20 -> #NAME? | BW25: =VLOOKUP($BV25,TACT!$A$3:$AH$100,11,FALSE) -> #NAME? | BX25: =VLOOKUP($BV25,TACT!$A$3:$AH$100,5,FALSE) -> #NAME? | BZ25: =VLOOKUP($BV25,TACT!$A$3:$AH$100,4,FALSE) -> #NAME? | CA25: =VLOOKUP($BV25,TACT!$A$3:$AH$100,21,FALSE) -> #NAME? | CB25: =VLOOKUP($BV25,TACT!$A$3:$AH$100,32,FALSE) -> #NAME? | CC25: =VLOOKUP($BV25,TACT!$A$3:$AH$100,33,FALSE) -> #NAME? | CD25: =IF(LEFT(VLOOKUP($BV25,TACT!$A$3:$AH$100,6,FALSE),1)="#","-",VLOOKUP($BV25,TACT!$A$3:$AH$100,6,FALSE)) -> #NAME? | CE25: =IF(LEFT(VLOOKUP($BV25,TACT!$A$3:$AH$100,7,FALSE),1)="#","-",VLOOKUP($BV25,TACT!$A$3:$AH$100,7,FALSE)) -> #NAME? | CF25: =IF(LEFT(VLOOKUP($BV25,TACT!$A$3:$AH$100,8,FALSE),1)="#","-",VLOOKUP($BV25,TACT!$A$3:$AH$100,8,FALSE)) -> #NAME? | EX25: IMF與SEC警示私募信貸風險 | EZ25: 2025年10月 | FA25: 1. IMF呼籲監管機構關注銀行對私募信貸基金的風險敞口。 2. SEC要求私募信貸基金提高透明度。 | FD25: 1. 私募信貸機構面臨合規壓力。 2. 投資人對私募信貸資產重新評價，部分基金遭贖回。 3. 信貸市場流動性與定價能力受挑戰。
T26: =VLOOKUP($AD26,'市場監控 '!$E$7:$W$194,6,FALSE) -> #NAME? | U26: =VLOOKUP($AD26,'市場監控 '!$E$7:$W$194,7,FALSE) -> #NAME? | V26: =VLOOKUP($AD26,'市場監控 '!$E$7:$W$194,8,FALSE) -> - | W26: =VLOOKUP($AD26,'市場監控 '!$E$7:$W$194,10,FALSE) -> - | X26: =VLOOKUP($AD26,'市場監控 '!$E$7:$W$194,12,FALSE) -> - | Y26: =VLOOKUP($AD26,'市場監控 '!$E$7:$W$194,14,FALSE) -> - | Z26: =VLOOKUP($AD26,'市場監控 '!$E$7:$W$194,15,FALSE) -> - | AA26: =VLOOKUP($AD26,'市場監控 '!$E$7:$W$194,17,FALSE) -> #NAME? | AB26: =VLOOKUP($AD26,'市場監控 '!$E$7:$W$194,18,FALSE) -> #NAME? | AC26: =VLOOKUP($AD26,'市場監控 '!$E$7:$W$194,19,FALSE) -> #NAME? | AD26: 8316 JP Equity | AE26: 國民西敏寺銀行集團公開有限公司 | BB26: =VLOOKUP($BD26,NI!$B$5:$AL$2030,6,FALSE) -> #NAME? | BC26: =VLOOKUP($BD26,NI!$B$37:$AL$2030,2,FALSE) -> #NAME? | BD26: =NI!$B84 -> #NAME? | BE26: =VLOOKUP($BD26,NI!$B$5:$AL$2030,11,FALSE) -> #NAME? | BF26: =VLOOKUP($BD26,NI!$B$5:$AL$2030,12,FALSE)/1000000 -> #NAME? | BH26: =IF(ISNUMBER(VLOOKUP($BD26,NI!$B$5:$AL$2030,13,FALSE)),VLOOKUP($BD26,NI!$B$5:$AL$2030,13,FALSE),"-") -> - | BI26: =VLOOKUP($BD26,NI!$B$5:$AL$2030,4,FALSE) -> #NAME? | BJ26: =VLOOKUP($BD26,NI!$B$5:$AL$2030,3,FALSE) -> #NAME? | BK26: =VLOOKUP($BD26,NI!$B$5:$AL$2030,4,FALSE) -> #NAME? | BL26: =IF(LEFT(VLOOKUP($BD26,NI!$B$5:$AL$2030,31,FALSE),1)="#","-",VLOOKUP($BD26,NI!$B$5:$AL$2030,31,FALSE)) -> #NAME? | BM26: =IF(LEFT(VLOOKUP($BD26,NI!$B$5:$AL$2030,32,FALSE),1)="#","-",VLOOKUP($BD26,NI!$B$5:$AL$2030,32,FALSE)) -> #NAME? | BN26: =IF(LEFT(VLOOKUP($BD26,NI!$B$5:$AL$2030,33,FALSE),1)="#","-",VLOOKUP($BD26,NI!$B$5:$AL$2030,33,FALSE)) -> #NAME? | BO26: =VLOOKUP($BD26,NI!$B$5:$AL$2030,22,FALSE) -> #NAME? | BT26: =VLOOKUP($BV26,TACT!$A$3:$AH$100,2,FALSE) -> #NAME? | BU26: =VLOOKUP($BV26,TACT!$A$3:$AH$100,3,FALSE) -> #NAME? | BV26: =TACT!$A21 -> #NAME? | BW26: =VLOOKUP($BV26,TACT!$A$3:$AH$100,11,FALSE) -> #NAME? | BX26: =VLOOKUP($BV26,TACT!$A$3:$AH$100,5,FALSE) -> #NAME? | BZ26: =VLOOKUP($BV26,TACT!$A$3:$AH$100,4,FALSE) -> #NAME? | CA26: =VLOOKUP($BV26,TACT!$A$3:$AH$100,21,FALSE) -> #NAME? | CB26: =VLOOKUP($BV26,TACT!$A$3:$AH$100,32,FALSE) -> #NAME? | CC26: =VLOOKUP($BV26,TACT!$A$3:$AH$100,33,FALSE) -> #NAME? | CD26: =IF(LEFT(VLOOKUP($BV26,TACT!$A$3:$AH$100,6,FALSE),1)="#","-",VLOOKUP($BV26,TACT!$A$3:$AH$100,6,FALSE)) -> #NAME? | CE26: =IF(LEFT(VLOOKUP($BV26,TACT!$A$3:$AH$100,7,FALSE),1)="#","-",VLOOKUP($BV26,TACT!$A$3:$AH$100,7,FALSE)) -> #NAME? | CF26: =IF(LEFT(VLOOKUP($BV26,TACT!$A$3:$AH$100,8,FALSE),1)="#","-",VLOOKUP($BV26,TACT!$A$3:$AH$100,8,FALSE)) -> #NAME?
T27: =VLOOKUP($AD27,'市場監控 '!$E$7:$W$194,6,FALSE) -> #NAME? | U27: =VLOOKUP($AD27,'市場監控 '!$E$7:$W$194,7,FALSE) -> #NAME? | V27: =VLOOKUP($AD27,'市場監控 '!$E$7:$W$194,8,FALSE) -> - | W27: =VLOOKUP($AD27,'市場監控 '!$E$7:$W$194,10,FALSE) -> - | X27: =VLOOKUP($AD27,'市場監控 '!$E$7:$W$194,12,FALSE) -> - | Y27: =VLOOKUP($AD27,'市場監控 '!$E$7:$W$194,14,FALSE) -> - | Z27: =VLOOKUP($AD27,'市場監控 '!$E$7:$W$194,15,FALSE) -> - | AA27: =VLOOKUP($AD27,'市場監控 '!$E$7:$W$194,17,FALSE) -> #NAME? | AB27: =VLOOKUP($AD27,'市場監控 '!$E$7:$W$194,18,FALSE) -> #NAME? | AC27: =VLOOKUP($AD27,'市場監控 '!$E$7:$W$194,19,FALSE) -> #NAME? | AD27: 8411 JP Equity | AE27: 駿懋銀行集團 | BB27: =VLOOKUP($BD27,NI!$B$5:$AL$2030,6,FALSE) -> #NAME? | BC27: =VLOOKUP($BD27,NI!$B$37:$AL$2030,2,FALSE) -> #NAME? | BD27: =NI!$B85 -> #NAME? | BE27: =VLOOKUP($BD27,NI!$B$5:$AL$2030,11,FALSE) -> #NAME? | BF27: =VLOOKUP($BD27,NI!$B$5:$AL$2030,12,FALSE)/1000000 -> #NAME? | BH27: =IF(ISNUMBER(VLOOKUP($BD27,NI!$B$5:$AL$2030,13,FALSE)),VLOOKUP($BD27,NI!$B$5:$AL$2030,13,FALSE),"-") -> - | BI27: =VLOOKUP($BD27,NI!$B$5:$AL$2030,4,FALSE) -> #NAME? | BJ27: =VLOOKUP($BD27,NI!$B$5:$AL$2030,3,FALSE) -> #NAME? | BK27: =VLOOKUP($BD27,NI!$B$5:$AL$2030,4,FALSE) -> #NAME? | BL27: =IF(LEFT(VLOOKUP($BD27,NI!$B$5:$AL$2030,31,FALSE),1)="#","-",VLOOKUP($BD27,NI!$B$5:$AL$2030,31,FALSE)) -> #NAME? | BM27: =IF(LEFT(VLOOKUP($BD27,NI!$B$5:$AL$2030,32,FALSE),1)="#","-",VLOOKUP($BD27,NI!$B$5:$AL$2030,32,FALSE)) -> #NAME? | BN27: =IF(LEFT(VLOOKUP($BD27,NI!$B$5:$AL$2030,33,FALSE),1)="#","-",VLOOKUP($BD27,NI!$B$5:$AL$2030,33,FALSE)) -> #NAME? | BO27: =VLOOKUP($BD27,NI!$B$5:$AL$2030,22,FALSE) -> #NAME? | BT27: =VLOOKUP($BV27,TACT!$A$3:$AH$100,2,FALSE) -> #NAME? | BU27: =VLOOKUP($BV27,TACT!$A$3:$AH$100,3,FALSE) -> #NAME? | BV27: =TACT!$A22 -> #NAME? | BW27: =VLOOKUP($BV27,TACT!$A$3:$AH$100,11,FALSE) -> #NAME? | BX27: =VLOOKUP($BV27,TACT!$A$3:$AH$100,5,FALSE) -> #NAME? | BZ27: =VLOOKUP($BV27,TACT!$A$3:$AH$100,4,FALSE) -> #NAME? | CA27: =VLOOKUP($BV27,TACT!$A$3:$AH$100,21,FALSE) -> #NAME? | CB27: =VLOOKUP($BV27,TACT!$A$3:$AH$100,32,FALSE) -> #NAME? | CC27: =VLOOKUP($BV27,TACT!$A$3:$AH$100,33,FALSE) -> #NAME? | CD27: =IF(LEFT(VLOOKUP($BV27,TACT!$A$3:$AH$100,6,FALSE),1)="#","-",VLOOKUP($BV27,TACT!$A$3:$AH$100,6,FALSE)) -> #NAME? | CE27: =IF(LEFT(VLOOKUP($BV27,TACT!$A$3:$AH$100,7,FALSE),1)="#","-",VLOOKUP($BV27,TACT!$A$3:$AH$100,7,FALSE)) -> #NAME? | CF27: =IF(LEFT(VLOOKUP($BV27,TACT!$A$3:$AH$100,8,FALSE),1)="#","-",VLOOKUP($BV27,TACT!$A$3:$AH$100,8,FALSE)) -> #NAME?
T28: =VLOOKUP($AD28,'市場監控 '!$E$7:$W$194,6,FALSE) -> #NAME? | U28: =VLOOKUP($AD28,'市場監控 '!$E$7:$W$194,7,FALSE) -> #NAME? | V28: =VLOOKUP($AD28,'市場監控 '!$E$7:$W$194,8,FALSE) -> - | W28: =VLOOKUP($AD28,'市場監控 '!$E$7:$W$194,10,FALSE) -> - | X28: =VLOOKUP($AD28,'市場監控 '!$E$7:$W$194,12,FALSE) -> - | Y28: =VLOOKUP($AD28,'市場監控 '!$E$7:$W$194,14,FALSE) -> - | Z28: =VLOOKUP($AD28,'市場監控 '!$E$7:$W$194,15,FALSE) -> - | AA28: =VLOOKUP($AD28,'市場監控 '!$E$7:$W$194,17,FALSE) -> #NAME? | AB28: =VLOOKUP($AD28,'市場監控 '!$E$7:$W$194,18,FALSE) -> #NAME? | AC28: =VLOOKUP($AD28,'市場監控 '!$E$7:$W$194,19,FALSE) -> #NAME? | AD28: 3328 HK Equity | AE28: 德意志銀行 | BB28: =VLOOKUP($BD28,NI!$B$5:$AL$2030,6,FALSE) -> #NAME? | BC28: =VLOOKUP($BD28,NI!$B$37:$AL$2030,2,FALSE) -> #NAME? | BD28: =NI!$B86 -> #NAME? | BE28: =VLOOKUP($BD28,NI!$B$5:$AL$2030,11,FALSE) -> #NAME? | BF28: =VLOOKUP($BD28,NI!$B$5:$AL$2030,12,FALSE)/1000000 -> #NAME? | BH28: =IF(ISNUMBER(VLOOKUP($BD28,NI!$B$5:$AL$2030,13,FALSE)),VLOOKUP($BD28,NI!$B$5:$AL$2030,13,FALSE),"-") -> - | BI28: =VLOOKUP($BD28,NI!$B$5:$AL$2030,4,FALSE) -> #NAME? | BJ28: =VLOOKUP($BD28,NI!$B$5:$AL$2030,3,FALSE) -> #NAME? | BK28: =VLOOKUP($BD28,NI!$B$5:$AL$2030,4,FALSE) -> #NAME? | BL28: =IF(LEFT(VLOOKUP($BD28,NI!$B$5:$AL$2030,31,FALSE),1)="#","-",VLOOKUP($BD28,NI!$B$5:$AL$2030,31,FALSE)) -> #NAME? | BM28: =IF(LEFT(VLOOKUP($BD28,NI!$B$5:$AL$2030,32,FALSE),1)="#","-",VLOOKUP($BD28,NI!$B$5:$AL$2030,32,FALSE)) -> #NAME? | BN28: =IF(LEFT(VLOOKUP($BD28,NI!$B$5:$AL$2030,33,FALSE),1)="#","-",VLOOKUP($BD28,NI!$B$5:$AL$2030,33,FALSE)) -> #NAME? | BO28: =VLOOKUP($BD28,NI!$B$5:$AL$2030,22,FALSE) -> #NAME?
T29: =VLOOKUP($AD29,'市場監控 '!$E$7:$W$194,6,FALSE) -> #NAME? | U29: =VLOOKUP($AD29,'市場監控 '!$E$7:$W$194,7,FALSE) -> #NAME? | V29: =VLOOKUP($AD29,'市場監控 '!$E$7:$W$194,8,FALSE) -> - | W29: =VLOOKUP($AD29,'市場監控 '!$E$7:$W$194,10,FALSE) -> - | X29: =VLOOKUP($AD29,'市場監控 '!$E$7:$W$194,12,FALSE) -> - | Y29: =VLOOKUP($AD29,'市場監控 '!$E$7:$W$194,14,FALSE) -> - | Z29: =VLOOKUP($AD29,'市場監控 '!$E$7:$W$194,15,FALSE) -> - | AA29: =VLOOKUP($AD29,'市場監控 '!$E$7:$W$194,17,FALSE) -> #NAME? | AB29: =VLOOKUP($AD29,'市場監控 '!$E$7:$W$194,18,FALSE) -> #NAME? | AC29: =VLOOKUP($AD29,'市場監控 '!$E$7:$W$194,19,FALSE) -> #NAME? | AD29: BAC US Equity | AE29: 德國商業銀行 | BB29: =VLOOKUP($BD29,NI!$B$5:$AL$2030,6,FALSE) -> #NAME? | BC29: =VLOOKUP($BD29,NI!$B$37:$AL$2030,2,FALSE) -> #NAME? | BD29: =NI!$B87 -> #NAME? | BE29: =VLOOKUP($BD29,NI!$B$5:$AL$2030,11,FALSE) -> #NAME? | BF29: =VLOOKUP($BD29,NI!$B$5:$AL$2030,12,FALSE)/1000000 -> #NAME? | BH29: =IF(ISNUMBER(VLOOKUP($BD29,NI!$B$5:$AL$2030,13,FALSE)),VLOOKUP($BD29,NI!$B$5:$AL$2030,13,FALSE),"-") -> - | BI29: =VLOOKUP($BD29,NI!$B$5:$AL$2030,4,FALSE) -> #NAME? | BJ29: =VLOOKUP($BD29,NI!$B$5:$AL$2030,3,FALSE) -> #NAME? | BK29: =VLOOKUP($BD29,NI!$B$5:$AL$2030,4,FALSE) -> #NAME? | BL29: =IF(LEFT(VLOOKUP($BD29,NI!$B$5:$AL$2030,31,FALSE),1)="#","-",VLOOKUP($BD29,NI!$B$5:$AL$2030,31,FALSE)) -> #NAME? | BM29: =IF(LEFT(VLOOKUP($BD29,NI!$B$5:$AL$2030,32,FALSE),1)="#","-",VLOOKUP($BD29,NI!$B$5:$AL$2030,32,FALSE)) -> #NAME? | BN29: =IF(LEFT(VLOOKUP($BD29,NI!$B$5:$AL$2030,33,FALSE),1)="#","-",VLOOKUP($BD29,NI!$B$5:$AL$2030,33,FALSE)) -> #NAME? | BO29: =VLOOKUP($BD29,NI!$B$5:$AL$2030,22,FALSE) -> #NAME? | CK29: 默克 (MRK) | CR29: 必和必拓 (BHP) | DB29: 甲骨文 (ORCL) | DI29: 杜克能源 (DUK)
T30: =VLOOKUP($AD30,'市場監控 '!$E$7:$W$194,6,FALSE) -> #NAME? | U30: =VLOOKUP($AD30,'市場監控 '!$E$7:$W$194,7,FALSE) -> #NAME? | V30: =VLOOKUP($AD30,'市場監控 '!$E$7:$W$194,8,FALSE) -> - | W30: =VLOOKUP($AD30,'市場監控 '!$E$7:$W$194,10,FALSE) -> - | X30: =VLOOKUP($AD30,'市場監控 '!$E$7:$W$194,12,FALSE) -> - | Y30: =VLOOKUP($AD30,'市場監控 '!$E$7:$W$194,14,FALSE) -> - | Z30: =VLOOKUP($AD30,'市場監控 '!$E$7:$W$194,15,FALSE) -> - | AA30: =VLOOKUP($AD30,'市場監控 '!$E$7:$W$194,17,FALSE) -> #NAME? | AB30: =VLOOKUP($AD30,'市場監控 '!$E$7:$W$194,18,FALSE) -> #NAME? | AC30: =VLOOKUP($AD30,'市場監控 '!$E$7:$W$194,19,FALSE) -> #NAME? | AD30: MS US Equity | AE30: 荷蘭國際集團 | BB30: =VLOOKUP($BD30,NI!$B$5:$AL$2030,6,FALSE) -> #NAME? | BC30: =VLOOKUP($BD30,NI!$B$37:$AL$2030,2,FALSE) -> #NAME? | BD30: =NI!$B88 -> #NAME? | BE30: =VLOOKUP($BD30,NI!$B$5:$AL$2030,11,FALSE) -> #NAME? | BF30: =VLOOKUP($BD30,NI!$B$5:$AL$2030,12,FALSE)/1000000 -> #NAME? | BH30: =IF(ISNUMBER(VLOOKUP($BD30,NI!$B$5:$AL$2030,13,FALSE)),VLOOKUP($BD30,NI!$B$5:$AL$2030,13,FALSE),"-") -> - | BI30: =VLOOKUP($BD30,NI!$B$5:$AL$2030,4,FALSE) -> #NAME? | BJ30: =VLOOKUP($BD30,NI!$B$5:$AL$2030,3,FALSE) -> #NAME? | BK30: =VLOOKUP($BD30,NI!$B$5:$AL$2030,4,FALSE) -> #NAME? | BL30: =IF(LEFT(VLOOKUP($BD30,NI!$B$5:$AL$2030,31,FALSE),1)="#","-",VLOOKUP($BD30,NI!$B$5:$AL$2030,31,FALSE)) -> #NAME? | BM30: =IF(LEFT(VLOOKUP($BD30,NI!$B$5:$AL$2030,32,FALSE),1)="#","-",VLOOKUP($BD30,NI!$B$5:$AL$2030,32,FALSE)) -> #NAME? | BN30: =IF(LEFT(VLOOKUP($BD30,NI!$B$5:$AL$2030,33,FALSE),1)="#","-",VLOOKUP($BD30,NI!$B$5:$AL$2030,33,FALSE)) -> #NAME? | BO30: =VLOOKUP($BD30,NI!$B$5:$AL$2030,22,FALSE) -> #NAME?
T31: =VLOOKUP($AD31,'市場監控 '!$E$7:$W$194,6,FALSE) -> #NAME? | U31: =VLOOKUP($AD31,'市場監控 '!$E$7:$W$194,7,FALSE) -> #NAME? | V31: =VLOOKUP($AD31,'市場監控 '!$E$7:$W$194,8,FALSE) -> - | W31: =VLOOKUP($AD31,'市場監控 '!$E$7:$W$194,10,FALSE) -> - | X31: =VLOOKUP($AD31,'市場監控 '!$E$7:$W$194,12,FALSE) -> - | Y31: =VLOOKUP($AD31,'市場監控 '!$E$7:$W$194,14,FALSE) -> - | Z31: =VLOOKUP($AD31,'市場監控 '!$E$7:$W$194,15,FALSE) -> - | AA31: =VLOOKUP($AD31,'市場監控 '!$E$7:$W$194,17,FALSE) -> #NAME? | AB31: =VLOOKUP($AD31,'市場監控 '!$E$7:$W$194,18,FALSE) -> #NAME? | AC31: =VLOOKUP($AD31,'市場監控 '!$E$7:$W$194,19,FALSE) -> #NAME? | AD31: HSBA LN Equity | AE31: 荷蘭銀行公眾有限公司 | BB31: =VLOOKUP($BD31,NI!$B$5:$AL$2030,6,FALSE) -> #NAME? | BC31: =VLOOKUP($BD31,NI!$B$37:$AL$2030,2,FALSE) -> #NAME? | BD31: =NI!$B89 -> #NAME? | BE31: =VLOOKUP($BD31,NI!$B$5:$AL$2030,11,FALSE) -> #NAME? | BF31: =VLOOKUP($BD31,NI!$B$5:$AL$2030,12,FALSE)/1000000 -> #NAME? | BH31: =IF(ISNUMBER(VLOOKUP($BD31,NI!$B$5:$AL$2030,13,FALSE)),VLOOKUP($BD31,NI!$B$5:$AL$2030,13,FALSE),"-") -> - | BI31: =VLOOKUP($BD31,NI!$B$5:$AL$2030,4,FALSE) -> #NAME? | BJ31: =VLOOKUP($BD31,NI!$B$5:$AL$2030,3,FALSE) -> #NAME? | BK31: =VLOOKUP($BD31,NI!$B$5:$AL$2030,4,FALSE) -> #NAME? | BL31: =IF(LEFT(VLOOKUP($BD31,NI!$B$5:$AL$2030,31,FALSE),1)="#","-",VLOOKUP($BD31,NI!$B$5:$AL$2030,31,FALSE)) -> #NAME? | BM31: =IF(LEFT(VLOOKUP($BD31,NI!$B$5:$AL$2030,32,FALSE),1)="#","-",VLOOKUP($BD31,NI!$B$5:$AL$2030,32,FALSE)) -> #NAME? | BN31: =IF(LEFT(VLOOKUP($BD31,NI!$B$5:$AL$2030,33,FALSE),1)="#","-",VLOOKUP($BD31,NI!$B$5:$AL$2030,33,FALSE)) -> #NAME? | BO31: =VLOOKUP($BD31,NI!$B$5:$AL$2030,22,FALSE) -> #NAME? | CK31: 默克以92億美元收購Cidara Therapeutics，相較於之前的收盤價，溢價超過100%。Cidara專注於開發藥物-Fc結合物，這將與MRK的抗病毒業務相結合。雖然新聞未提及融資細節，但預期MRK可能會回到市場籌資，並且由於交易預計在2026年第一季度完成，他們可能會在今年年底之前或等到2026財年初進行融資。默克近來在併購上呈現明顯「加速感」，顯示公司對Keytruda專利懸崖的時間壓力心知肚明，必須及早透過交易把未來十年的營收空窗補齊，其增量債務/流通股可能會移動到>=5的水平。即便如此，MRK的表現仍可能優於BMY/PFE，但MRK可能會繼續積極進行併購，這將限制其相對於ABBV的交易表現。 11/14消息公布後，默克股價持平，信用利差widen 2bps。 | CR31: 英國法院裁定BHP需對2015年Mariana水壩坍塌事件負法律責任，此判決僅決定誰需負責，而非他們需支付多少賠償金。損害賠償的審判將於10月26日至明年3月27日進行。值得注意的是，Mariana水壩坍塌事件的大部分賠償已透過巴西法律框架處理，因此我們不預期會有巨額賠償。然而，這則新聞增加了一些小幅的尾端風險及新聞風險，可能導致RIOLN的些微利差擴大。 11/14消息公布後，BHP股價盤前一度下跌3.2%。 | DB31: 「銀行為與Oracle相關的新墨西哥數據中心提供180億美元貸款」。與之前類似的消息一樣，這並非ORCL的債務，而是開發商的債務。此消息將是類似於Vantage交易的建設貸款，條件看起來與Vantage交易相似，例如比SOFR高2.5%的利率，期限為4年。這個新墨西哥設施早已宣布，因此這並非新消息或超出預期。 消息公布後，ORCL信用利差widen 6bps。 | DI31: 本季獲利與營收皆優於預期，受惠於零售電力銷售成長與新費率實施。全年EPS指引上修至 $6.25~$6.35，並重申2029年前年均EPS成長率5%~7%。公司宣布五年資本支出計畫上修至 $95bn~$105bn，聚焦電網升級與清潔能源轉型。 營收：$8.54bn（年增 4.8%，優於預期） EPS：$1.81（年增 11.7%，預期 $1.75） 淨利：$1.42bn 營業利潤率：未公布（Adjusted EBITDA 未列） ROE：1.95%（低於產業平均） 11/7財報公布後，股價持平。
T32: =VLOOKUP($AD32,'市場監控 '!$E$7:$W$194,6,FALSE) -> #NAME? | U32: =VLOOKUP($AD32,'市場監控 '!$E$7:$W$194,7,FALSE) -> #NAME? | V32: =VLOOKUP($AD32,'市場監控 '!$E$7:$W$194,8,FALSE) -> - | W32: =VLOOKUP($AD32,'市場監控 '!$E$7:$W$194,10,FALSE) -> - | X32: =VLOOKUP($AD32,'市場監控 '!$E$7:$W$194,12,FALSE) -> - | Y32: =VLOOKUP($AD32,'市場監控 '!$E$7:$W$194,14,FALSE) -> - | Z32: =VLOOKUP($AD32,'市場監控 '!$E$7:$W$194,15,FALSE) -> - | AA32: =VLOOKUP($AD32,'市場監控 '!$E$7:$W$194,17,FALSE) -> #NAME? | AB32: =VLOOKUP($AD32,'市場監控 '!$E$7:$W$194,18,FALSE) -> #NAME? | AC32: =VLOOKUP($AD32,'市場監控 '!$E$7:$W$194,19,FALSE) -> #NAME? | AD32: INGA NA Equity | AE32: 瑞銀集團公司
T33: =VLOOKUP($AD33,'市場監控 '!$E$7:$W$194,6,FALSE) -> #NAME? | U33: =VLOOKUP($AD33,'市場監控 '!$E$7:$W$194,7,FALSE) -> #NAME? | V33: =VLOOKUP($AD33,'市場監控 '!$E$7:$W$194,8,FALSE) -> - | W33: =VLOOKUP($AD33,'市場監控 '!$E$7:$W$194,10,FALSE) -> - | X33: =VLOOKUP($AD33,'市場監控 '!$E$7:$W$194,12,FALSE) -> - | Y33: =VLOOKUP($AD33,'市場監控 '!$E$7:$W$194,14,FALSE) -> - | Z33: =VLOOKUP($AD33,'市場監控 '!$E$7:$W$194,15,FALSE) -> - | AA33: =VLOOKUP($AD33,'市場監控 '!$E$7:$W$194,17,FALSE) -> #NAME? | AB33: =VLOOKUP($AD33,'市場監控 '!$E$7:$W$194,18,FALSE) -> #NAME? | AC33: =VLOOKUP($AD33,'市場監控 '!$E$7:$W$194,19,FALSE) -> #NAME? | AD33: UBSG SW Equity | AE33: 西班牙國際銀行
T34: =VLOOKUP($AD34,'市場監控 '!$E$7:$W$194,6,FALSE) -> #NAME? | U34: =VLOOKUP($AD34,'市場監控 '!$E$7:$W$194,7,FALSE) -> #NAME? | V34: =VLOOKUP($AD34,'市場監控 '!$E$7:$W$194,8,FALSE) -> - | W34: =VLOOKUP($AD34,'市場監控 '!$E$7:$W$194,10,FALSE) -> - | X34: =VLOOKUP($AD34,'市場監控 '!$E$7:$W$194,12,FALSE) -> - | Y34: =VLOOKUP($AD34,'市場監控 '!$E$7:$W$194,14,FALSE) -> - | Z34: =VLOOKUP($AD34,'市場監控 '!$E$7:$W$194,15,FALSE) -> - | AA34: =VLOOKUP($AD34,'市場監控 '!$E$7:$W$194,17,FALSE) -> #NAME? | AB34: =VLOOKUP($AD34,'市場監控 '!$E$7:$W$194,18,FALSE) -> #NAME? | AC34: =VLOOKUP($AD34,'市場監控 '!$E$7:$W$194,19,FALSE) -> #NAME? | AD34: C US Equity | AE34: 畢爾巴鄂比斯開銀行
T35: =VLOOKUP($AD35,'市場監控 '!$E$7:$W$194,6,FALSE) -> #NAME? | U35: =VLOOKUP($AD35,'市場監控 '!$E$7:$W$194,7,FALSE) -> #NAME? | V35: =VLOOKUP($AD35,'市場監控 '!$E$7:$W$194,8,FALSE) -> - | W35: =VLOOKUP($AD35,'市場監控 '!$E$7:$W$194,10,FALSE) -> - | X35: =VLOOKUP($AD35,'市場監控 '!$E$7:$W$194,12,FALSE) -> - | Y35: =VLOOKUP($AD35,'市場監控 '!$E$7:$W$194,14,FALSE) -> - | Z35: =VLOOKUP($AD35,'市場監控 '!$E$7:$W$194,15,FALSE) -> - | AA35: =VLOOKUP($AD35,'市場監控 '!$E$7:$W$194,17,FALSE) -> #NAME? | AB35: =VLOOKUP($AD35,'市場監控 '!$E$7:$W$194,18,FALSE) -> #NAME? | AC35: =VLOOKUP($AD35,'市場監控 '!$E$7:$W$194,19,FALSE) -> #NAME? | AD35: WFC US Equity | AE35: 三菱UFJ金融集團公司 | EX35: 2023年銀行危機時間軸 | FE35: 私募信貸相關股票
T36: =VLOOKUP($AD36,'市場監控 '!$E$7:$W$194,6,FALSE) -> #NAME? | U36: =VLOOKUP($AD36,'市場監控 '!$E$7:$W$194,7,FALSE) -> #NAME? | V36: =VLOOKUP($AD36,'市場監控 '!$E$7:$W$194,8,FALSE) -> - | W36: =VLOOKUP($AD36,'市場監控 '!$E$7:$W$194,10,FALSE) -> - | X36: =VLOOKUP($AD36,'市場監控 '!$E$7:$W$194,12,FALSE) -> - | Y36: =VLOOKUP($AD36,'市場監控 '!$E$7:$W$194,14,FALSE) -> - | Z36: =VLOOKUP($AD36,'市場監控 '!$E$7:$W$194,15,FALSE) -> - | AA36: =VLOOKUP($AD36,'市場監控 '!$E$7:$W$194,17,FALSE) -> #NAME? | AB36: =VLOOKUP($AD36,'市場監控 '!$E$7:$W$194,18,FALSE) -> #NAME? | AC36: =VLOOKUP($AD36,'市場監控 '!$E$7:$W$194,19,FALSE) -> #NAME? | AD36: GS US Equity | AE36: 三井住友金融集團公司 | EG36: 輕稀土 vs. 重稀土 | EN36: 美國稀土相關企業列表
T37: =VLOOKUP($AD37,'市場監控 '!$E$7:$W$194,6,FALSE) -> #NAME? | U37: =VLOOKUP($AD37,'市場監控 '!$E$7:$W$194,7,FALSE) -> #NAME? | V37: =VLOOKUP($AD37,'市場監控 '!$E$7:$W$194,8,FALSE) -> - | W37: =VLOOKUP($AD37,'市場監控 '!$E$7:$W$194,10,FALSE) -> - | X37: =VLOOKUP($AD37,'市場監控 '!$E$7:$W$194,12,FALSE) -> - | Y37: =VLOOKUP($AD37,'市場監控 '!$E$7:$W$194,14,FALSE) -> - | Z37: =VLOOKUP($AD37,'市場監控 '!$E$7:$W$194,15,FALSE) -> - | AA37: =VLOOKUP($AD37,'市場監控 '!$E$7:$W$194,17,FALSE) -> #NAME? | AB37: =VLOOKUP($AD37,'市場監控 '!$E$7:$W$194,18,FALSE) -> #NAME? | AC37: =VLOOKUP($AD37,'市場監控 '!$E$7:$W$194,19,FALSE) -> #NAME? | AD37: STAN LN Equity | AE37: 瑞穗金融集團 | AJ37: 發行狀況統計 | AP37: 上週發行量總量與估計 | BT37: 依產業 | BZ37: 依天期 | EX37: 時間 | EY37: 事件 | FE37: 股票代碼 | FF37: 公司名稱 | FH37: 私募信貸 AUM (十億美元) | FI37: 基金主要資產類型
T38: =VLOOKUP($AD38,'市場監控 '!$E$7:$W$194,6,FALSE) -> #NAME? | U38: =VLOOKUP($AD38,'市場監控 '!$E$7:$W$194,7,FALSE) -> #NAME? | V38: =VLOOKUP($AD38,'市場監控 '!$E$7:$W$194,8,FALSE) -> - | W38: =VLOOKUP($AD38,'市場監控 '!$E$7:$W$194,10,FALSE) -> - | X38: =VLOOKUP($AD38,'市場監控 '!$E$7:$W$194,12,FALSE) -> - | Y38: =VLOOKUP($AD38,'市場監控 '!$E$7:$W$194,14,FALSE) -> - | Z38: =VLOOKUP($AD38,'市場監控 '!$E$7:$W$194,15,FALSE) -> - | AA38: =VLOOKUP($AD38,'市場監控 '!$E$7:$W$194,17,FALSE) -> #NAME? | AB38: =VLOOKUP($AD38,'市場監控 '!$E$7:$W$194,18,FALSE) -> #NAME? | AC38: =VLOOKUP($AD38,'市場監控 '!$E$7:$W$194,19,FALSE) -> #NAME? | AD38: BARC LN Equity | AE38: 澳盛銀行集團控股有限公司 | EG38: 項目 | EI38: 輕稀土 | EK38: 重稀土 | EN38: 公司代碼 | EO38: 產業環節 | EP38: 核心資產/技術 | ER38: 最新進展
T39: =VLOOKUP($AD39,'市場監控 '!$E$7:$W$194,6,FALSE) -> #NAME? | U39: =VLOOKUP($AD39,'市場監控 '!$E$7:$W$194,7,FALSE) -> #NAME? | V39: =VLOOKUP($AD39,'市場監控 '!$E$7:$W$194,8,FALSE) -> - | W39: =VLOOKUP($AD39,'市場監控 '!$E$7:$W$194,10,FALSE) -> - | X39: =VLOOKUP($AD39,'市場監控 '!$E$7:$W$194,12,FALSE) -> - | Y39: =VLOOKUP($AD39,'市場監控 '!$E$7:$W$194,14,FALSE) -> - | Z39: =VLOOKUP($AD39,'市場監控 '!$E$7:$W$194,15,FALSE) -> - | AA39: =VLOOKUP($AD39,'市場監控 '!$E$7:$W$194,17,FALSE) -> #NAME? | AB39: =VLOOKUP($AD39,'市場監控 '!$E$7:$W$194,18,FALSE) -> #NAME? | AC39: =VLOOKUP($AD39,'市場監控 '!$E$7:$W$194,19,FALSE) -> #NAME? | AD39: NWG LN Equity | AE39: 澳洲聯邦銀行 | AJ39: IG (ex-SSA) | AL39: 45978 | AM39: YTD | AN39: 2024 | AP39: 45978 | AR39: Actual | AU39: Projected | EX39: 44993 | EY39: Silvergate Bank倒閉。Silicon Valley Bank宣布$1.8bn損失，其母公司SVB Financial遭到Moody's降評。 | FE39: BX | FF39: Blackstone Inc. | FH39: 297.2 | FI39: Senior Secured Loans, Direct Lending
T40: =VLOOKUP($AD40,'市場監控 '!$E$7:$W$194,6,FALSE) -> #NAME? | U40: =VLOOKUP($AD40,'市場監控 '!$E$7:$W$194,7,FALSE) -> #NAME? | V40: =VLOOKUP($AD40,'市場監控 '!$E$7:$W$194,8,FALSE) -> - | W40: =VLOOKUP($AD40,'市場監控 '!$E$7:$W$194,10,FALSE) -> - | X40: =VLOOKUP($AD40,'市場監控 '!$E$7:$W$194,12,FALSE) -> - | Y40: =VLOOKUP($AD40,'市場監控 '!$E$7:$W$194,14,FALSE) -> - | Z40: =VLOOKUP($AD40,'市場監控 '!$E$7:$W$194,15,FALSE) -> - | AA40: =VLOOKUP($AD40,'市場監控 '!$E$7:$W$194,17,FALSE) -> #NAME? | AB40: =VLOOKUP($AD40,'市場監控 '!$E$7:$W$194,18,FALSE) -> #NAME? | AC40: =VLOOKUP($AD40,'市場監控 '!$E$7:$W$194,19,FALSE) -> #NAME? | AD40: LLOY LN Equity | AE40: 澳大利亞國家銀行 | AJ40: New Issue Concession (bps) | AL40: 2 | AM40: 3.1 | AN40: 3.5 | AP40: Day | AR40: $26.3bn | AU40: - | EG40: 核心成員 | EI40: 釹(Nd)、鐠(Pr) | EK40: 鏑(Dy)、鋱(Tb) | EN40: MP | EO40: 礦山、分離、磁材 | EP40: Mountain Pass礦場、德州磁材場 | ER40: 國防部為最大股東，對釹與鐠產品設定每公斤110美元的保底價格
C41: 美債殖利率曲線 | J41: 美債利差曲線 | T41: =VLOOKUP($AD41,'市場監控 '!$E$7:$W$194,6,FALSE) -> #NAME? | U41: =VLOOKUP($AD41,'市場監控 '!$E$7:$W$194,7,FALSE) -> #NAME? | V41: =VLOOKUP($AD41,'市場監控 '!$E$7:$W$194,8,FALSE) -> - | W41: =VLOOKUP($AD41,'市場監控 '!$E$7:$W$194,10,FALSE) -> - | X41: =VLOOKUP($AD41,'市場監控 '!$E$7:$W$194,12,FALSE) -> - | Y41: =VLOOKUP($AD41,'市場監控 '!$E$7:$W$194,14,FALSE) -> - | Z41: =VLOOKUP($AD41,'市場監控 '!$E$7:$W$194,15,FALSE) -> - | AA41: =VLOOKUP($AD41,'市場監控 '!$E$7:$W$194,17,FALSE) -> #NAME? | AB41: =VLOOKUP($AD41,'市場監控 '!$E$7:$W$194,18,FALSE) -> #NAME? | AC41: =VLOOKUP($AD41,'市場監控 '!$E$7:$W$194,19,FALSE) -> #NAME? | AD41: MQG AU Equity | AE41: 西太平洋銀行公司 | AJ41: Books (Times Covered) | AL41: 3.6 | AM41: 3.9 | AN41: 3.7 | AP41: WTD | AR41: $26bn | AU41: $20bn
T42: =VLOOKUP($AD42,'市場監控 '!$E$7:$W$194,6,FALSE) -> #NAME? | U42: =VLOOKUP($AD42,'市場監控 '!$E$7:$W$194,7,FALSE) -> #NAME? | V42: =VLOOKUP($AD42,'市場監控 '!$E$7:$W$194,8,FALSE) -> - | W42: =VLOOKUP($AD42,'市場監控 '!$E$7:$W$194,10,FALSE) -> - | X42: =VLOOKUP($AD42,'市場監控 '!$E$7:$W$194,12,FALSE) -> - | Y42: =VLOOKUP($AD42,'市場監控 '!$E$7:$W$194,14,FALSE) -> - | Z42: =VLOOKUP($AD42,'市場監控 '!$E$7:$W$194,15,FALSE) -> - | AA42: =VLOOKUP($AD42,'市場監控 '!$E$7:$W$194,17,FALSE) -> #NAME? | AB42: =VLOOKUP($AD42,'市場監控 '!$E$7:$W$194,18,FALSE) -> #NAME? | AC42: =VLOOKUP($AD42,'市場監控 '!$E$7:$W$194,19,FALSE) -> #NAME? | AD42: ANZ AU Equity | AE42: 麥格理集團 | AJ42: Compression (bps) | AL42: -28 | AM42: -27 | AN42: -27 | AP42: MTD | AR42: $110bn | AU42: $120bn | EG42: 核心用途 | EI42: 高性能釹鐵硼(NdFeB)永磁體 | EK42: 讓釹磁鐵在其端高溫下保持性能 | EX42: 44994 | EY42: SVB股價大跌，導致美國銀行、摩根大通、花旗集團和富國銀行市值損失達5200萬美元。 | FE42: ARES | FF42: Ares Management Corp | FH42: 308.6 | FI42: Direct Lending, Opportunistic Credit
S43: 通訊 | T43: =VLOOKUP($AD43,'市場監控 '!$E$7:$W$194,6,FALSE) -> #NAME? | U43: =VLOOKUP($AD43,'市場監控 '!$E$7:$W$194,7,FALSE) -> #NAME? | V43: =VLOOKUP($AD43,'市場監控 '!$E$7:$W$194,8,FALSE) -> - | W43: =VLOOKUP($AD43,'市場監控 '!$E$7:$W$194,10,FALSE) -> - | X43: =VLOOKUP($AD43,'市場監控 '!$E$7:$W$194,12,FALSE) -> - | Y43: =VLOOKUP($AD43,'市場監控 '!$E$7:$W$194,14,FALSE) -> - | Z43: =VLOOKUP($AD43,'市場監控 '!$E$7:$W$194,15,FALSE) -> - | AA43: =VLOOKUP($AD43,'市場監控 '!$E$7:$W$194,17,FALSE) -> #NAME? | AB43: =VLOOKUP($AD43,'市場監控 '!$E$7:$W$194,18,FALSE) -> #NAME? | AC43: =VLOOKUP($AD43,'市場監控 '!$E$7:$W$194,19,FALSE) -> #NAME? | AD43: VZ US Equity | AE43: 沃達豐集團公開有限公司 | AJ43: Attrition (%) | AL43: -40 | AM43: -21 | AN43: -20 | AP43: YTD | AR43: $1,529bn | AU43: $1.5trl | EN43: USAR | EO43: 礦山、分離、磁材 | EP43: Round Top 礦場、RapidSX萃取技術 | ER43: 建構美國本土供應鏈，市場猜測川普政府將入股
T44: =VLOOKUP($AD44,'市場監控 '!$E$7:$W$194,6,FALSE) -> #NAME? | U44: =VLOOKUP($AD44,'市場監控 '!$E$7:$W$194,7,FALSE) -> #NAME? | V44: =VLOOKUP($AD44,'市場監控 '!$E$7:$W$194,8,FALSE) -> - | W44: =VLOOKUP($AD44,'市場監控 '!$E$7:$W$194,10,FALSE) -> - | X44: =VLOOKUP($AD44,'市場監控 '!$E$7:$W$194,12,FALSE) -> - | Y44: =VLOOKUP($AD44,'市場監控 '!$E$7:$W$194,14,FALSE) -> - | Z44: =VLOOKUP($AD44,'市場監控 '!$E$7:$W$194,15,FALSE) -> - | AA44: =VLOOKUP($AD44,'市場監控 '!$E$7:$W$194,17,FALSE) -> #NAME? | AB44: =VLOOKUP($AD44,'市場監控 '!$E$7:$W$194,18,FALSE) -> #NAME? | AC44: =VLOOKUP($AD44,'市場監控 '!$E$7:$W$194,19,FALSE) -> #NAME? | AD44: DTE gr Equity | AE44: 威瑞森電信公司 | EG44: 地殼含量 | EI44: 較高，較易開採 | EK44: 較低，分布稀少
T45: =VLOOKUP($AD45,'市場監控 '!$E$7:$W$194,6,FALSE) -> #NAME? | U45: =VLOOKUP($AD45,'市場監控 '!$E$7:$W$194,7,FALSE) -> #NAME? | V45: =VLOOKUP($AD45,'市場監控 '!$E$7:$W$194,8,FALSE) -> - | W45: =VLOOKUP($AD45,'市場監控 '!$E$7:$W$194,10,FALSE) -> - | X45: =VLOOKUP($AD45,'市場監控 '!$E$7:$W$194,12,FALSE) -> - | Y45: =VLOOKUP($AD45,'市場監控 '!$E$7:$W$194,14,FALSE) -> - | Z45: =VLOOKUP($AD45,'市場監控 '!$E$7:$W$194,15,FALSE) -> - | AA45: =VLOOKUP($AD45,'市場監控 '!$E$7:$W$194,17,FALSE) -> #NAME? | AB45: =VLOOKUP($AD45,'市場監控 '!$E$7:$W$194,18,FALSE) -> #NAME? | AC45: =VLOOKUP($AD45,'市場監控 '!$E$7:$W$194,19,FALSE) -> #NAME? | AD45: VOD LN Equity | AE45: 德意志電信 | EX45: 44995 | EY45: 監管機構宣布接管SVB。 | FE45: KKR | FF45: KKR & Co. Inc | FH45: 115.9 | FI45: Direct Lending, Opportunistic Credit
T46: =VLOOKUP($AD46,'市場監控 '!$E$7:$W$194,6,FALSE) -> #NAME? | U46: =VLOOKUP($AD46,'市場監控 '!$E$7:$W$194,7,FALSE) -> #NAME? | V46: =VLOOKUP($AD46,'市場監控 '!$E$7:$W$194,8,FALSE) -> - | W46: =VLOOKUP($AD46,'市場監控 '!$E$7:$W$194,10,FALSE) -> - | X46: =VLOOKUP($AD46,'市場監控 '!$E$7:$W$194,12,FALSE) -> - | Y46: =VLOOKUP($AD46,'市場監控 '!$E$7:$W$194,14,FALSE) -> - | Z46: =VLOOKUP($AD46,'市場監控 '!$E$7:$W$194,15,FALSE) -> - | AA46: =VLOOKUP($AD46,'市場監控 '!$E$7:$W$194,17,FALSE) -> #NAME? | AB46: =VLOOKUP($AD46,'市場監控 '!$E$7:$W$194,18,FALSE) -> #NAME? | AC46: =VLOOKUP($AD46,'市場監控 '!$E$7:$W$194,19,FALSE) -> #NAME? | AD46: TMUS US Equity | AE46: T-Mobile美國公司 | AJ46: Ticker | AK46: 發行人 | AL46: ISIN | AM46: 定價日 | AN46: 發行量(MM) | AP46: 天期 | AQ46: 票息 | AR46: 償債順位 | AS46: 殖利率 | AT46: S&P | AU46: Moody's | AV46: Fitch | AW46: 認購倍數 | EG46: 供應來源 | EI46: 中國、澳洲、美國 | EK46: 幾乎集中在中國南方礦區(如江西) | EN46: IDR | EO46: 軍功磁材、雷射塗層 | EP46: 軍用磁體技術、雷射塗層材料 | ER46: 提供F-35所需稀土，軍工應用為主
T47: =VLOOKUP($AD47,'市場監控 '!$E$7:$W$194,6,FALSE) -> #NAME? | U47: =VLOOKUP($AD47,'市場監控 '!$E$7:$W$194,7,FALSE) -> #NAME? | V47: =VLOOKUP($AD47,'市場監控 '!$E$7:$W$194,8,FALSE) -> - | W47: =VLOOKUP($AD47,'市場監控 '!$E$7:$W$194,10,FALSE) -> - | X47: =VLOOKUP($AD47,'市場監控 '!$E$7:$W$194,12,FALSE) -> - | Y47: =VLOOKUP($AD47,'市場監控 '!$E$7:$W$194,14,FALSE) -> - | Z47: =VLOOKUP($AD47,'市場監控 '!$E$7:$W$194,15,FALSE) -> - | AA47: =VLOOKUP($AD47,'市場監控 '!$E$7:$W$194,17,FALSE) -> #NAME? | AB47: =VLOOKUP($AD47,'市場監控 '!$E$7:$W$194,18,FALSE) -> #NAME? | AC47: =VLOOKUP($AD47,'市場監控 '!$E$7:$W$194,19,FALSE) -> #NAME? | AD47: T US Equity | AE47: AT&T公司
S48: 科技 | T48: =VLOOKUP($AD48,'市場監控 '!$E$7:$W$194,6,FALSE) -> #NAME? | U48: =VLOOKUP($AD48,'市場監控 '!$E$7:$W$194,7,FALSE) -> #NAME? | V48: =VLOOKUP($AD48,'市場監控 '!$E$7:$W$194,8,FALSE) -> - | W48: =VLOOKUP($AD48,'市場監控 '!$E$7:$W$194,10,FALSE) -> - | X48: =VLOOKUP($AD48,'市場監控 '!$E$7:$W$194,12,FALSE) -> - | Y48: =VLOOKUP($AD48,'市場監控 '!$E$7:$W$194,14,FALSE) -> - | Z48: =VLOOKUP($AD48,'市場監控 '!$E$7:$W$194,15,FALSE) -> - | AA48: =VLOOKUP($AD48,'市場監控 '!$E$7:$W$194,17,FALSE) -> #NAME? | AB48: =VLOOKUP($AD48,'市場監控 '!$E$7:$W$194,18,FALSE) -> #NAME? | AC48: =VLOOKUP($AD48,'市場監控 '!$E$7:$W$194,19,FALSE) -> #NAME? | AD48: MSFT US Equity | AE48: 亞馬遜公司 | AJ48: =VLOOKUP($AL48,NI!$B$5:$AL$2030,6,FALSE) -> #NAME? | AK48: =VLOOKUP($AL48,NI!$B$5:$AL$2030,2,FALSE) -> #NAME? | AL48: =NI!B5 -> #NAME? | AM48: =VLOOKUP($AL48,NI!$B$5:$AL$2030,11,FALSE) -> #NAME? | AN48: =VLOOKUP($AL48,NI!$B$5:$AL$2030,12,FALSE)/1000000 -> #NAME? | AP48: =IF(ISNUMBER(VLOOKUP($AL48,NI!$B$5:$AL$2030,13,FALSE)),VLOOKUP($AL48,NI!$B$5:$AL$2030,13,FALSE),"-") -> - | AQ48: =VLOOKUP($AL48,NI!$B$5:$AL$2030,4,FALSE) -> #NAME? | AR48: =VLOOKUP($AL48,NI!$B$5:$AL$2030,3,FALSE) -> #NAME? | AS48: =VLOOKUP($AL48,NI!$B$5:$AL$2030,4,FALSE) -> #NAME? | AT48: =IF(LEFT(VLOOKUP($AL48,NI!$B$5:$AL$2030,31,FALSE),1)="#","-",VLOOKUP($AL48,NI!$B$5:$AL$2030,31,FALSE)) -> #NAME? | AU48: =IF(LEFT(VLOOKUP($AL48,NI!$B$5:$AL$2030,32,FALSE),1)="#","-",VLOOKUP($AL48,NI!$B$5:$AL$2030,32,FALSE)) -> #NAME? | AV48: =IF(LEFT(VLOOKUP($AL48,NI!$B$5:$AL$2030,33,FALSE),1)="#","-",VLOOKUP($AL48,NI!$B$5:$AL$2030,33,FALSE)) -> #NAME? | AW48: =VLOOKUP($AL48,NI!$B$5:$AL$2030,22,FALSE) -> #NAME? | EG48: 精煉難度 | EI48: 相對較低 | EK48: 分離技術複雜，成本高 | EX48: 44997 | EY48: 監管機構接管Signature Bank，並宣布受影響的銀行客戶將獲得其存款資金的返還。 | FE48: CGBD | FF48: Carlyle Group BDC | FH48: 12 | FI48: Middle Market Loans
T49: =VLOOKUP($AD49,'市場監控 '!$E$7:$W$194,6,FALSE) -> #NAME? | U49: =VLOOKUP($AD49,'市場監控 '!$E$7:$W$194,7,FALSE) -> #NAME? | V49: =VLOOKUP($AD49,'市場監控 '!$E$7:$W$194,8,FALSE) -> - | W49: =VLOOKUP($AD49,'市場監控 '!$E$7:$W$194,10,FALSE) -> - | X49: =VLOOKUP($AD49,'市場監控 '!$E$7:$W$194,12,FALSE) -> - | Y49: =VLOOKUP($AD49,'市場監控 '!$E$7:$W$194,14,FALSE) -> - | Z49: =VLOOKUP($AD49,'市場監控 '!$E$7:$W$194,15,FALSE) -> - | AA49: =VLOOKUP($AD49,'市場監控 '!$E$7:$W$194,17,FALSE) -> #NAME? | AB49: =VLOOKUP($AD49,'市場監控 '!$E$7:$W$194,18,FALSE) -> #NAME? | AC49: =VLOOKUP($AD49,'市場監控 '!$E$7:$W$194,19,FALSE) -> #NAME? | AD49: AAPL US Equity | AE49: 台灣積體電路製造股份有限公司 | AJ49: =VLOOKUP($AL49,NI!$B$5:$AL$2030,6,FALSE) -> #NAME? | AK49: =VLOOKUP($AL49,NI!$B$5:$AL$2030,2,FALSE) -> #NAME? | AL49: =NI!B6 -> #NAME? | AM49: =VLOOKUP($AL49,NI!$B$5:$AL$2030,11,FALSE) -> #NAME? | AN49: =VLOOKUP($AL49,NI!$B$5:$AL$2030,12,FALSE)/1000000 -> #NAME? | AP49: =IF(ISNUMBER(VLOOKUP($AL49,NI!$B$5:$AL$2030,13,FALSE)),VLOOKUP($AL49,NI!$B$5:$AL$2030,13,FALSE),"-") -> - | AQ49: =VLOOKUP($AL49,NI!$B$5:$AL$2030,4,FALSE) -> #NAME? | AR49: =VLOOKUP($AL49,NI!$B$5:$AL$2030,3,FALSE) -> #NAME? | AS49: =VLOOKUP($AL49,NI!$B$5:$AL$2030,4,FALSE) -> #NAME? | AT49: =IF(LEFT(VLOOKUP($AL49,NI!$B$5:$AL$2030,31,FALSE),1)="#","-",VLOOKUP($AL49,NI!$B$5:$AL$2030,31,FALSE)) -> #NAME? | AU49: =IF(LEFT(VLOOKUP($AL49,NI!$B$5:$AL$2030,32,FALSE),1)="#","-",VLOOKUP($AL49,NI!$B$5:$AL$2030,32,FALSE)) -> #NAME? | AV49: =IF(LEFT(VLOOKUP($AL49,NI!$B$5:$AL$2030,33,FALSE),1)="#","-",VLOOKUP($AL49,NI!$B$5:$AL$2030,33,FALSE)) -> #NAME? | AW49: =VLOOKUP($AL49,NI!$B$5:$AL$2030,22,FALSE) -> #NAME? | EN49: UUUU | EO49: 再生料、分離 | EP49: Utah White Mesa Mill | ER49: 可量產中國限制出口的重稀土氧化物
T50: =VLOOKUP($AD50,'市場監控 '!$E$7:$W$194,6,FALSE) -> #NAME? | U50: =VLOOKUP($AD50,'市場監控 '!$E$7:$W$194,7,FALSE) -> #NAME? | V50: =VLOOKUP($AD50,'市場監控 '!$E$7:$W$194,8,FALSE) -> - | W50: =VLOOKUP($AD50,'市場監控 '!$E$7:$W$194,10,FALSE) -> - | X50: =VLOOKUP($AD50,'市場監控 '!$E$7:$W$194,12,FALSE) -> - | Y50: =VLOOKUP($AD50,'市場監控 '!$E$7:$W$194,14,FALSE) -> - | Z50: =VLOOKUP($AD50,'市場監控 '!$E$7:$W$194,15,FALSE) -> - | AA50: =VLOOKUP($AD50,'市場監控 '!$E$7:$W$194,17,FALSE) -> #NAME? | AB50: =VLOOKUP($AD50,'市場監控 '!$E$7:$W$194,18,FALSE) -> #NAME? | AC50: =VLOOKUP($AD50,'市場監控 '!$E$7:$W$194,19,FALSE) -> #NAME? | AD50: Googl US Equity | AE50: 蘋果公司 | AJ50: =VLOOKUP($AL50,NI!$B$5:$AL$2030,6,FALSE) -> #NAME? | AK50: =VLOOKUP($AL50,NI!$B$5:$AL$2030,2,FALSE) -> #NAME? | AL50: =NI!B7 -> #NAME? | AM50: =VLOOKUP($AL50,NI!$B$5:$AL$2030,11,FALSE) -> #NAME? | AN50: =VLOOKUP($AL50,NI!$B$5:$AL$2030,12,FALSE)/1000000 -> #NAME? | AP50: =IF(ISNUMBER(VLOOKUP($AL50,NI!$B$5:$AL$2030,13,FALSE)),VLOOKUP($AL50,NI!$B$5:$AL$2030,13,FALSE),"-") -> - | AQ50: =VLOOKUP($AL50,NI!$B$5:$AL$2030,4,FALSE) -> #NAME? | AR50: =VLOOKUP($AL50,NI!$B$5:$AL$2030,3,FALSE) -> #NAME? | AS50: =VLOOKUP($AL50,NI!$B$5:$AL$2030,4,FALSE) -> #NAME? | AT50: =IF(LEFT(VLOOKUP($AL50,NI!$B$5:$AL$2030,31,FALSE),1)="#","-",VLOOKUP($AL50,NI!$B$5:$AL$2030,31,FALSE)) -> #NAME? | AU50: =IF(LEFT(VLOOKUP($AL50,NI!$B$5:$AL$2030,32,FALSE),1)="#","-",VLOOKUP($AL50,NI!$B$5:$AL$2030,32,FALSE)) -> #NAME? | AV50: =IF(LEFT(VLOOKUP($AL50,NI!$B$5:$AL$2030,33,FALSE),1)="#","-",VLOOKUP($AL50,NI!$B$5:$AL$2030,33,FALSE)) -> #NAME? | AW50: =VLOOKUP($AL50,NI!$B$5:$AL$2030,22,FALSE) -> #NAME? | EG50: 戰略價值 | EI50: 高科技產業基礎 | EK50: 軍功與能源產業關鍵材料
T51: =VLOOKUP($AD51,'市場監控 '!$E$7:$W$194,6,FALSE) -> #NAME? | U51: =VLOOKUP($AD51,'市場監控 '!$E$7:$W$194,7,FALSE) -> #NAME? | V51: =VLOOKUP($AD51,'市場監控 '!$E$7:$W$194,8,FALSE) -> - | W51: =VLOOKUP($AD51,'市場監控 '!$E$7:$W$194,10,FALSE) -> - | X51: =VLOOKUP($AD51,'市場監控 '!$E$7:$W$194,12,FALSE) -> - | Y51: =VLOOKUP($AD51,'市場監控 '!$E$7:$W$194,14,FALSE) -> - | Z51: =VLOOKUP($AD51,'市場監控 '!$E$7:$W$194,15,FALSE) -> - | AA51: =VLOOKUP($AD51,'市場監控 '!$E$7:$W$194,17,FALSE) -> #NAME? | AB51: =VLOOKUP($AD51,'市場監控 '!$E$7:$W$194,18,FALSE) -> #NAME? | AC51: =VLOOKUP($AD51,'市場監控 '!$E$7:$W$194,19,FALSE) -> #NAME? | AD51: AMZN US Equity | AE51: 微軟 | AJ51: =VLOOKUP($AL51,NI!$B$5:$AL$2030,6,FALSE) -> #NAME? | AK51: =VLOOKUP($AL51,NI!$B$5:$AL$2030,2,FALSE) -> #NAME? | AL51: =NI!B8 -> #NAME? | AM51: =VLOOKUP($AL51,NI!$B$5:$AL$2030,11,FALSE) -> #NAME? | AN51: =VLOOKUP($AL51,NI!$B$5:$AL$2030,12,FALSE)/1000000 -> #NAME? | AP51: =IF(ISNUMBER(VLOOKUP($AL51,NI!$B$5:$AL$2030,13,FALSE)),VLOOKUP($AL51,NI!$B$5:$AL$2030,13,FALSE),"-") -> - | AQ51: =VLOOKUP($AL51,NI!$B$5:$AL$2030,4,FALSE) -> #NAME? | AR51: =VLOOKUP($AL51,NI!$B$5:$AL$2030,3,FALSE) -> #NAME? | AS51: =VLOOKUP($AL51,NI!$B$5:$AL$2030,4,FALSE) -> #NAME? | AT51: =IF(LEFT(VLOOKUP($AL51,NI!$B$5:$AL$2030,31,FALSE),1)="#","-",VLOOKUP($AL51,NI!$B$5:$AL$2030,31,FALSE)) -> #NAME? | AU51: =IF(LEFT(VLOOKUP($AL51,NI!$B$5:$AL$2030,32,FALSE),1)="#","-",VLOOKUP($AL51,NI!$B$5:$AL$2030,32,FALSE)) -> #NAME? | AV51: =IF(LEFT(VLOOKUP($AL51,NI!$B$5:$AL$2030,33,FALSE),1)="#","-",VLOOKUP($AL51,NI!$B$5:$AL$2030,33,FALSE)) -> #NAME? | AW51: =VLOOKUP($AL51,NI!$B$5:$AL$2030,22,FALSE) -> #NAME? | EX51: 45000 | EY51: 瑞士信貸銀行股價創低，法國巴黎銀行和德意志銀行等歐洲銀行股價下挫。第一共和銀行信用評等被標普全球降為「垃圾」等級。 | FE51: ARCC | FF51: Ares Capital Corporation | FH51: 20 | FI51: Middle Market Loans
T52: =VLOOKUP($AD52,'市場監控 '!$E$7:$W$194,6,FALSE) -> #NAME? | U52: =VLOOKUP($AD52,'市場監控 '!$E$7:$W$194,7,FALSE) -> #NAME? | V52: =VLOOKUP($AD52,'市場監控 '!$E$7:$W$194,8,FALSE) -> - | W52: =VLOOKUP($AD52,'市場監控 '!$E$7:$W$194,10,FALSE) -> - | X52: =VLOOKUP($AD52,'市場監控 '!$E$7:$W$194,12,FALSE) -> - | Y52: =VLOOKUP($AD52,'市場監控 '!$E$7:$W$194,14,FALSE) -> - | Z52: =VLOOKUP($AD52,'市場監控 '!$E$7:$W$194,15,FALSE) -> - | AA52: =VLOOKUP($AD52,'市場監控 '!$E$7:$W$194,17,FALSE) -> #NAME? | AB52: =VLOOKUP($AD52,'市場監控 '!$E$7:$W$194,18,FALSE) -> #NAME? | AC52: =VLOOKUP($AD52,'市場監控 '!$E$7:$W$194,19,FALSE) -> #NAME? | AD52: NVDA US Equity | AE52: 輝達 | AJ52: =VLOOKUP($AL52,NI!$B$5:$AL$2030,6,FALSE) -> #NAME? | AK52: =VLOOKUP($AL52,NI!$B$5:$AL$2030,2,FALSE) -> #NAME? | AL52: =NI!B9 -> #NAME? | AM52: =VLOOKUP($AL52,NI!$B$5:$AL$2030,11,FALSE) -> #NAME? | AN52: =VLOOKUP($AL52,NI!$B$5:$AL$2030,12,FALSE)/1000000 -> #NAME? | AP52: =IF(ISNUMBER(VLOOKUP($AL52,NI!$B$5:$AL$2030,13,FALSE)),VLOOKUP($AL52,NI!$B$5:$AL$2030,13,FALSE),"-") -> - | AQ52: =VLOOKUP($AL52,NI!$B$5:$AL$2030,4,FALSE) -> #NAME? | AR52: =VLOOKUP($AL52,NI!$B$5:$AL$2030,3,FALSE) -> #NAME? | AS52: =VLOOKUP($AL52,NI!$B$5:$AL$2030,4,FALSE) -> #NAME? | AT52: =IF(LEFT(VLOOKUP($AL52,NI!$B$5:$AL$2030,31,FALSE),1)="#","-",VLOOKUP($AL52,NI!$B$5:$AL$2030,31,FALSE)) -> #NAME? | AU52: =IF(LEFT(VLOOKUP($AL52,NI!$B$5:$AL$2030,32,FALSE),1)="#","-",VLOOKUP($AL52,NI!$B$5:$AL$2030,32,FALSE)) -> #NAME? | AV52: =IF(LEFT(VLOOKUP($AL52,NI!$B$5:$AL$2030,33,FALSE),1)="#","-",VLOOKUP($AL52,NI!$B$5:$AL$2030,33,FALSE)) -> #NAME? | AW52: =VLOOKUP($AL52,NI!$B$5:$AL$2030,22,FALSE) -> #NAME? | EG52: 影響舉例 | EI52: 1. 一輛Model Y的驅動馬達裡，躺著約1公斤的釹磁鐵。缺了釹，電動車革命將直接熄火。 2. 一座海上風力發電機，需要數噸的釹磁鐵來實現高效發電。 3. Iphone的震動馬達、工廠的機器人等，無數設備將癱瘓。 | EK52: 1. 一架F-35戰鬥機需要約450公斤稀土，大部分用於雷達、電子戰系統。導彈制導、潛艇靜音驅動，也依賴重稀土。 | EN52: UAMY | EO52: 銻、沸石、貴金屬 | EP52: 美國唯一銻冶煉廠 | ER52: 與國防部合作，擴展稀土應用
T53: =VLOOKUP($AD53,'市場監控 '!$E$7:$W$194,6,FALSE) -> #NAME? | U53: =VLOOKUP($AD53,'市場監控 '!$E$7:$W$194,7,FALSE) -> #NAME? | V53: =VLOOKUP($AD53,'市場監控 '!$E$7:$W$194,8,FALSE) -> - | W53: =VLOOKUP($AD53,'市場監控 '!$E$7:$W$194,10,FALSE) -> - | X53: =VLOOKUP($AD53,'市場監控 '!$E$7:$W$194,12,FALSE) -> - | Y53: =VLOOKUP($AD53,'市場監控 '!$E$7:$W$194,14,FALSE) -> - | Z53: =VLOOKUP($AD53,'市場監控 '!$E$7:$W$194,15,FALSE) -> - | AA53: =VLOOKUP($AD53,'市場監控 '!$E$7:$W$194,17,FALSE) -> #NAME? | AB53: =VLOOKUP($AD53,'市場監控 '!$E$7:$W$194,18,FALSE) -> #NAME? | AC53: =VLOOKUP($AD53,'市場監控 '!$E$7:$W$194,19,FALSE) -> #NAME? | AD53: 2330 tt Equity | AE53: Meta平台公司 | AJ53: =VLOOKUP($AL53,NI!$B$5:$AL$2030,6,FALSE) -> #NAME? | AK53: =VLOOKUP($AL53,NI!$B$5:$AL$2030,2,FALSE) -> #NAME? | AL53: =NI!B10 -> #NAME? | AM53: =VLOOKUP($AL53,NI!$B$5:$AL$2030,11,FALSE) -> #NAME? | AN53: =VLOOKUP($AL53,NI!$B$5:$AL$2030,12,FALSE)/1000000 -> #NAME? | AP53: =IF(ISNUMBER(VLOOKUP($AL53,NI!$B$5:$AL$2030,13,FALSE)),VLOOKUP($AL53,NI!$B$5:$AL$2030,13,FALSE),"-") -> - | AQ53: =VLOOKUP($AL53,NI!$B$5:$AL$2030,4,FALSE) -> #NAME? | AR53: =VLOOKUP($AL53,NI!$B$5:$AL$2030,3,FALSE) -> #NAME? | AS53: =VLOOKUP($AL53,NI!$B$5:$AL$2030,4,FALSE) -> #NAME? | AT53: =IF(LEFT(VLOOKUP($AL53,NI!$B$5:$AL$2030,31,FALSE),1)="#","-",VLOOKUP($AL53,NI!$B$5:$AL$2030,31,FALSE)) -> #NAME? | AU53: =IF(LEFT(VLOOKUP($AL53,NI!$B$5:$AL$2030,32,FALSE),1)="#","-",VLOOKUP($AL53,NI!$B$5:$AL$2030,32,FALSE)) -> #NAME? | AV53: =IF(LEFT(VLOOKUP($AL53,NI!$B$5:$AL$2030,33,FALSE),1)="#","-",VLOOKUP($AL53,NI!$B$5:$AL$2030,33,FALSE)) -> #NAME? | AW53: =VLOOKUP($AL53,NI!$B$5:$AL$2030,22,FALSE) -> #NAME? | CK53: JBS NV (JBS) | DB53: CNH Industrial (CNH) | DI53: 波克夏 (BRKHEC)
B54: 1 | T54: =VLOOKUP($AD54,'市場監控 '!$E$7:$W$194,6,FALSE) -> #NAME? | U54: =VLOOKUP($AD54,'市場監控 '!$E$7:$W$194,7,FALSE) -> #NAME? | V54: =VLOOKUP($AD54,'市場監控 '!$E$7:$W$194,8,FALSE) -> - | W54: =VLOOKUP($AD54,'市場監控 '!$E$7:$W$194,10,FALSE) -> - | X54: =VLOOKUP($AD54,'市場監控 '!$E$7:$W$194,12,FALSE) -> - | Y54: =VLOOKUP($AD54,'市場監控 '!$E$7:$W$194,14,FALSE) -> - | Z54: =VLOOKUP($AD54,'市場監控 '!$E$7:$W$194,15,FALSE) -> - | AA54: =VLOOKUP($AD54,'市場監控 '!$E$7:$W$194,17,FALSE) -> #NAME? | AB54: =VLOOKUP($AD54,'市場監控 '!$E$7:$W$194,18,FALSE) -> #NAME? | AC54: =VLOOKUP($AD54,'市場監控 '!$E$7:$W$194,19,FALSE) -> #NAME? | AD54: META US Equity | AE54: Alphabet公司 | AJ54: =VLOOKUP($AL54,NI!$B$5:$AL$2030,6,FALSE) -> #NAME? | AK54: =VLOOKUP($AL54,NI!$B$5:$AL$2030,2,FALSE) -> #NAME? | AL54: =NI!B11 -> #NAME? | AM54: =VLOOKUP($AL54,NI!$B$5:$AL$2030,11,FALSE) -> #NAME? | AN54: =VLOOKUP($AL54,NI!$B$5:$AL$2030,12,FALSE)/1000000 -> #NAME? | AP54: =IF(ISNUMBER(VLOOKUP($AL54,NI!$B$5:$AL$2030,13,FALSE)),VLOOKUP($AL54,NI!$B$5:$AL$2030,13,FALSE),"-") -> - | AQ54: =VLOOKUP($AL54,NI!$B$5:$AL$2030,4,FALSE) -> #NAME? | AR54: =VLOOKUP($AL54,NI!$B$5:$AL$2030,3,FALSE) -> #NAME? | AS54: =VLOOKUP($AL54,NI!$B$5:$AL$2030,4,FALSE) -> #NAME? | AT54: =IF(LEFT(VLOOKUP($AL54,NI!$B$5:$AL$2030,31,FALSE),1)="#","-",VLOOKUP($AL54,NI!$B$5:$AL$2030,31,FALSE)) -> #NAME? | AU54: =IF(LEFT(VLOOKUP($AL54,NI!$B$5:$AL$2030,32,FALSE),1)="#","-",VLOOKUP($AL54,NI!$B$5:$AL$2030,32,FALSE)) -> #NAME? | AV54: =IF(LEFT(VLOOKUP($AL54,NI!$B$5:$AL$2030,33,FALSE),1)="#","-",VLOOKUP($AL54,NI!$B$5:$AL$2030,33,FALSE)) -> #NAME? | AW54: =VLOOKUP($AL54,NI!$B$5:$AL$2030,22,FALSE) -> #NAME? | EX54: 45002 | EY54: SVB Financial申請破產保護 | FE54: FSIC | FF54: FS KKR Capital Corp | FH54: 15 | FI54: Middle Market Loans
B55: =+B54+1 -> 2 | T55: =VLOOKUP($AD55,'市場監控 '!$E$7:$W$194,6,FALSE) -> #NAME? | U55: =VLOOKUP($AD55,'市場監控 '!$E$7:$W$194,7,FALSE) -> #NAME? | V55: =VLOOKUP($AD55,'市場監控 '!$E$7:$W$194,8,FALSE) -> - | W55: =VLOOKUP($AD55,'市場監控 '!$E$7:$W$194,10,FALSE) -> - | X55: =VLOOKUP($AD55,'市場監控 '!$E$7:$W$194,12,FALSE) -> - | Y55: =VLOOKUP($AD55,'市場監控 '!$E$7:$W$194,14,FALSE) -> - | Z55: =VLOOKUP($AD55,'市場監控 '!$E$7:$W$194,15,FALSE) -> - | AA55: =VLOOKUP($AD55,'市場監控 '!$E$7:$W$194,17,FALSE) -> #NAME? | AB55: =VLOOKUP($AD55,'市場監控 '!$E$7:$W$194,18,FALSE) -> #NAME? | AC55: =VLOOKUP($AD55,'市場監控 '!$E$7:$W$194,19,FALSE) -> #NAME? | AD55: AVGO US Equity | AE55: 甲骨文公司 | AJ55: =VLOOKUP($AL55,NI!$B$5:$AL$2030,6,FALSE) -> #NAME? | AK55: =VLOOKUP($AL55,NI!$B$5:$AL$2030,2,FALSE) -> #NAME? | AL55: =NI!B12 -> #NAME? | AM55: =VLOOKUP($AL55,NI!$B$5:$AL$2030,11,FALSE) -> #NAME? | AN55: =VLOOKUP($AL55,NI!$B$5:$AL$2030,12,FALSE)/1000000 -> #NAME? | AP55: =IF(ISNUMBER(VLOOKUP($AL55,NI!$B$5:$AL$2030,13,FALSE)),VLOOKUP($AL55,NI!$B$5:$AL$2030,13,FALSE),"-") -> - | AQ55: =VLOOKUP($AL55,NI!$B$5:$AL$2030,4,FALSE) -> #NAME? | AR55: =VLOOKUP($AL55,NI!$B$5:$AL$2030,3,FALSE) -> #NAME? | AS55: =VLOOKUP($AL55,NI!$B$5:$AL$2030,4,FALSE) -> #NAME? | AT55: =IF(LEFT(VLOOKUP($AL55,NI!$B$5:$AL$2030,31,FALSE),1)="#","-",VLOOKUP($AL55,NI!$B$5:$AL$2030,31,FALSE)) -> #NAME? | AU55: =IF(LEFT(VLOOKUP($AL55,NI!$B$5:$AL$2030,32,FALSE),1)="#","-",VLOOKUP($AL55,NI!$B$5:$AL$2030,32,FALSE)) -> #NAME? | AV55: =IF(LEFT(VLOOKUP($AL55,NI!$B$5:$AL$2030,33,FALSE),1)="#","-",VLOOKUP($AL55,NI!$B$5:$AL$2030,33,FALSE)) -> #NAME? | AW55: =VLOOKUP($AL55,NI!$B$5:$AL$2030,22,FALSE) -> #NAME? | CK55: 業績表現優於預期，主要受益於牛肉和雞肉業務的良好表現。電話會議的重點將放在未來的利潤率上，因為牛肉市場仍面臨挑戰，而雞肉市場因其短周期特性也備受關注。JBS似乎動用了約10億美元的短期融資設施，但可能是由於現金流和股票回購的時間安排所致。 營收：$2.26bn，創歷史新高，同比增長 13%，超過市場預期（預測 $2.2bn） 淨利：$581mio，YOY - 16% EPS：$0.52，雖然同比下降，但仍 高於市場預測（$0.4945） 調整後 EBITDA：$18.35 億美元，同比下降 15%，利潤率約 8.1% 自由現金流：$3.83 億美元 槓桿比率：2.39x，維持在公司長期目標範圍 ROE（過去 12 個月）：23.7%，顯示資本回報穩健 11/14消息公布後，JBS股價持平。 | DB55: 儘管EPS大幅優於預期，營收年減且毛利率下滑，導致股價重挫。農業部門受北美重型設備需求崩跌影響，銷售年減 11%；建設部門則年增 8%。全年EPS指引下修至 $0.44~$0.50，反映地緣銷售組合不利與關稅壓力。 營收：$4.4bn（年減 5%，略優於預期） EPS：$0.36（預期 $0.13，驚喜幅度 +176.9%） 淨利：$67mio（年減 78%） Adjusted EPS：$0.08（年減 67%） Adjusted EBIT（工業部門）：$104mio（年減 69%） 自由現金流（工業部門）：吸收 $188mio 毛利率：下滑 5.6 個百分點至 2.8% 11/7財報公布後，CNH股價下跌6%。 | DI55: 巴菲特的Berkshire Hathaway所擁有的公用事業公司PacifiCorp，近日警告可能因2020年勞動節週末奧勒岡州野火的加速審判而面臨流動性壓力。上週五(11/7)，標普將Pacificorp的FMBs（第一抵押債券）評級下調至BBB+，並將展望維持在負面。最值得注意的是，評級機構指出，未來12個月內該評級可能會再被下調超過一級。PacifiCorp已經預留28.5億美元，包括第三季的1億美元，用於應對涉及超過2000個建築物和50萬英畝土地的訴訟，這些訴訟索賠金額高達550億美元。 消息公布後，BRKHEC信用利差widen 9bps。 | EN55: NB | EO55: 新礦開發 | EP55: Nebraska Elk Creek 礦 | ER55: 申請 DOE 融資，含稀土與關鍵金屬
B56: =+B55+1 -> 3 | T56: =VLOOKUP($AD56,'市場監控 '!$E$7:$W$194,6,FALSE) -> #NAME? | U56: =VLOOKUP($AD56,'市場監控 '!$E$7:$W$194,7,FALSE) -> #NAME? | V56: =VLOOKUP($AD56,'市場監控 '!$E$7:$W$194,8,FALSE) -> - | W56: =VLOOKUP($AD56,'市場監控 '!$E$7:$W$194,10,FALSE) -> - | X56: =VLOOKUP($AD56,'市場監控 '!$E$7:$W$194,12,FALSE) -> - | Y56: =VLOOKUP($AD56,'市場監控 '!$E$7:$W$194,14,FALSE) -> - | Z56: =VLOOKUP($AD56,'市場監控 '!$E$7:$W$194,15,FALSE) -> - | AA56: =VLOOKUP($AD56,'市場監控 '!$E$7:$W$194,17,FALSE) -> #NAME? | AB56: =VLOOKUP($AD56,'市場監控 '!$E$7:$W$194,18,FALSE) -> #NAME? | AC56: =VLOOKUP($AD56,'市場監控 '!$E$7:$W$194,19,FALSE) -> #NAME? | AD56: INTC US Equity | AE56: 博通公司 | AJ56: =VLOOKUP($AL56,NI!$B$5:$AL$2030,6,FALSE) -> #NAME? | AK56: =VLOOKUP($AL56,NI!$B$5:$AL$2030,2,FALSE) -> #NAME? | AL56: =NI!B13 -> #NAME? | AM56: =VLOOKUP($AL56,NI!$B$5:$AL$2030,11,FALSE) -> #NAME? | AN56: =VLOOKUP($AL56,NI!$B$5:$AL$2030,12,FALSE)/1000000 -> #NAME? | AP56: =IF(ISNUMBER(VLOOKUP($AL56,NI!$B$5:$AL$2030,13,FALSE)),VLOOKUP($AL56,NI!$B$5:$AL$2030,13,FALSE),"-") -> - | AQ56: =VLOOKUP($AL56,NI!$B$5:$AL$2030,4,FALSE) -> #NAME? | AR56: =VLOOKUP($AL56,NI!$B$5:$AL$2030,3,FALSE) -> #NAME? | AS56: =VLOOKUP($AL56,NI!$B$5:$AL$2030,4,FALSE) -> #NAME? | AT56: =IF(LEFT(VLOOKUP($AL56,NI!$B$5:$AL$2030,31,FALSE),1)="#","-",VLOOKUP($AL56,NI!$B$5:$AL$2030,31,FALSE)) -> #NAME? | AU56: =IF(LEFT(VLOOKUP($AL56,NI!$B$5:$AL$2030,32,FALSE),1)="#","-",VLOOKUP($AL56,NI!$B$5:$AL$2030,32,FALSE)) -> #NAME? | AV56: =IF(LEFT(VLOOKUP($AL56,NI!$B$5:$AL$2030,33,FALSE),1)="#","-",VLOOKUP($AL56,NI!$B$5:$AL$2030,33,FALSE)) -> #NAME? | AW56: =VLOOKUP($AL56,NI!$B$5:$AL$2030,22,FALSE) -> #NAME?
B57: =+B56+1 -> 4 | T57: =VLOOKUP($AD57,'市場監控 '!$E$7:$W$194,6,FALSE) -> #NAME? | U57: =VLOOKUP($AD57,'市場監控 '!$E$7:$W$194,7,FALSE) -> #NAME? | V57: =VLOOKUP($AD57,'市場監控 '!$E$7:$W$194,8,FALSE) -> - | W57: =VLOOKUP($AD57,'市場監控 '!$E$7:$W$194,10,FALSE) -> - | X57: =VLOOKUP($AD57,'市場監控 '!$E$7:$W$194,12,FALSE) -> - | Y57: =VLOOKUP($AD57,'市場監控 '!$E$7:$W$194,14,FALSE) -> - | Z57: =VLOOKUP($AD57,'市場監控 '!$E$7:$W$194,15,FALSE) -> - | AA57: =VLOOKUP($AD57,'市場監控 '!$E$7:$W$194,17,FALSE) -> #NAME? | AB57: =VLOOKUP($AD57,'市場監控 '!$E$7:$W$194,18,FALSE) -> #NAME? | AC57: =VLOOKUP($AD57,'市場監控 '!$E$7:$W$194,19,FALSE) -> #NAME? | AD57: ORCL US Equity | AE57: 英特爾 | AJ57: =VLOOKUP($AL57,NI!$B$5:$AL$2030,6,FALSE) -> #NAME? | AK57: =VLOOKUP($AL57,NI!$B$5:$AL$2030,2,FALSE) -> #NAME? | AL57: =NI!B14 -> #NAME? | AM57: =VLOOKUP($AL57,NI!$B$5:$AL$2030,11,FALSE) -> #NAME? | AN57: =VLOOKUP($AL57,NI!$B$5:$AL$2030,12,FALSE)/1000000 -> #NAME? | AP57: =IF(ISNUMBER(VLOOKUP($AL57,NI!$B$5:$AL$2030,13,FALSE)),VLOOKUP($AL57,NI!$B$5:$AL$2030,13,FALSE),"-") -> - | AQ57: =VLOOKUP($AL57,NI!$B$5:$AL$2030,4,FALSE) -> #NAME? | AR57: =VLOOKUP($AL57,NI!$B$5:$AL$2030,3,FALSE) -> #NAME? | AS57: =VLOOKUP($AL57,NI!$B$5:$AL$2030,4,FALSE) -> #NAME? | AT57: =IF(LEFT(VLOOKUP($AL57,NI!$B$5:$AL$2030,31,FALSE),1)="#","-",VLOOKUP($AL57,NI!$B$5:$AL$2030,31,FALSE)) -> #NAME? | AU57: =IF(LEFT(VLOOKUP($AL57,NI!$B$5:$AL$2030,32,FALSE),1)="#","-",VLOOKUP($AL57,NI!$B$5:$AL$2030,32,FALSE)) -> #NAME? | AV57: =IF(LEFT(VLOOKUP($AL57,NI!$B$5:$AL$2030,33,FALSE),1)="#","-",VLOOKUP($AL57,NI!$B$5:$AL$2030,33,FALSE)) -> #NAME? | AW57: =VLOOKUP($AL57,NI!$B$5:$AL$2030,22,FALSE) -> #NAME? | EX57: 2023年3月18~ 2023年3月27 | EY57: UBS完成對瑞士信貸銀行的收購；JPMorgan計畫穩定第一共和銀行，第一共和銀行股價上漲30%；SVB大部分資產轉移到First Citizens BancShares。 | FE57: GSBD | FF57: Goldman Sachs BDC | FH57: 10 | FI57: Middle Market Loans
B58: =+B57+1 -> 5 | S58: 汽車 | T58: =VLOOKUP($AD58,'市場監控 '!$E$7:$W$194,6,FALSE) -> #NAME? | U58: =VLOOKUP($AD58,'市場監控 '!$E$7:$W$194,7,FALSE) -> #NAME? | V58: =VLOOKUP($AD58,'市場監控 '!$E$7:$W$194,8,FALSE) -> - | W58: =VLOOKUP($AD58,'市場監控 '!$E$7:$W$194,10,FALSE) -> - | X58: =VLOOKUP($AD58,'市場監控 '!$E$7:$W$194,12,FALSE) -> - | Y58: =VLOOKUP($AD58,'市場監控 '!$E$7:$W$194,14,FALSE) -> - | Z58: =VLOOKUP($AD58,'市場監控 '!$E$7:$W$194,15,FALSE) -> - | AA58: =VLOOKUP($AD58,'市場監控 '!$E$7:$W$194,17,FALSE) -> #NAME? | AB58: =VLOOKUP($AD58,'市場監控 '!$E$7:$W$194,18,FALSE) -> #NAME? | AC58: =VLOOKUP($AD58,'市場監控 '!$E$7:$W$194,19,FALSE) -> #NAME? | AD58: 7203 JP Equity | AE58: 特斯拉公司 | AJ58: =VLOOKUP($AL58,NI!$B$5:$AL$2030,6,FALSE) -> #NAME? | AK58: =VLOOKUP($AL58,NI!$B$5:$AL$2030,2,FALSE) -> #NAME? | AL58: =NI!B15 -> #NAME? | AM58: =VLOOKUP($AL58,NI!$B$5:$AL$2030,11,FALSE) -> #NAME? | AN58: =VLOOKUP($AL58,NI!$B$5:$AL$2030,12,FALSE)/1000000 -> #NAME? | AP58: =IF(ISNUMBER(VLOOKUP($AL58,NI!$B$5:$AL$2030,13,FALSE)),VLOOKUP($AL58,NI!$B$5:$AL$2030,13,FALSE),"-") -> - | AQ58: =VLOOKUP($AL58,NI!$B$5:$AL$2030,4,FALSE) -> #NAME? | AR58: =VLOOKUP($AL58,NI!$B$5:$AL$2030,3,FALSE) -> #NAME? | AS58: =VLOOKUP($AL58,NI!$B$5:$AL$2030,4,FALSE) -> #NAME? | AT58: =IF(LEFT(VLOOKUP($AL58,NI!$B$5:$AL$2030,31,FALSE),1)="#","-",VLOOKUP($AL58,NI!$B$5:$AL$2030,31,FALSE)) -> #NAME? | AU58: =IF(LEFT(VLOOKUP($AL58,NI!$B$5:$AL$2030,32,FALSE),1)="#","-",VLOOKUP($AL58,NI!$B$5:$AL$2030,32,FALSE)) -> #NAME? | AV58: =IF(LEFT(VLOOKUP($AL58,NI!$B$5:$AL$2030,33,FALSE),1)="#","-",VLOOKUP($AL58,NI!$B$5:$AL$2030,33,FALSE)) -> #NAME? | AW58: =VLOOKUP($AL58,NI!$B$5:$AL$2030,22,FALSE) -> #NAME? | EN58: UURAF | EO58: 分離技術 | EP58: RapidSX 萃取技術 + Louisiana產線 | ER58: 獲美國防部補助1,840萬美元
B59: =+B58+1 -> 6 | T59: =VLOOKUP($AD59,'市場監控 '!$E$7:$W$194,6,FALSE) -> #NAME? | U59: =VLOOKUP($AD59,'市場監控 '!$E$7:$W$194,7,FALSE) -> #NAME? | V59: =VLOOKUP($AD59,'市場監控 '!$E$7:$W$194,8,FALSE) -> - | W59: =VLOOKUP($AD59,'市場監控 '!$E$7:$W$194,10,FALSE) -> - | X59: =VLOOKUP($AD59,'市場監控 '!$E$7:$W$194,12,FALSE) -> - | Y59: =VLOOKUP($AD59,'市場監控 '!$E$7:$W$194,14,FALSE) -> - | Z59: =VLOOKUP($AD59,'市場監控 '!$E$7:$W$194,15,FALSE) -> - | AA59: =VLOOKUP($AD59,'市場監控 '!$E$7:$W$194,17,FALSE) -> #NAME? | AB59: =VLOOKUP($AD59,'市場監控 '!$E$7:$W$194,18,FALSE) -> #NAME? | AC59: =VLOOKUP($AD59,'市場監控 '!$E$7:$W$194,19,FALSE) -> #NAME? | AD59: TSLA US Equity | AE59: 豐田汽車公司 | AJ59: =VLOOKUP($AL59,NI!$B$5:$AL$2030,6,FALSE) -> #NAME? | AK59: =VLOOKUP($AL59,NI!$B$5:$AL$2030,2,FALSE) -> #NAME? | AL59: =NI!B16 -> #NAME? | AM59: =VLOOKUP($AL59,NI!$B$5:$AL$2030,11,FALSE) -> #NAME? | AN59: =VLOOKUP($AL59,NI!$B$5:$AL$2030,12,FALSE)/1000000 -> #NAME? | AP59: =IF(ISNUMBER(VLOOKUP($AL59,NI!$B$5:$AL$2030,13,FALSE)),VLOOKUP($AL59,NI!$B$5:$AL$2030,13,FALSE),"-") -> - | AQ59: =VLOOKUP($AL59,NI!$B$5:$AL$2030,4,FALSE) -> #NAME? | AR59: =VLOOKUP($AL59,NI!$B$5:$AL$2030,3,FALSE) -> #NAME? | AS59: =VLOOKUP($AL59,NI!$B$5:$AL$2030,4,FALSE) -> #NAME? | AT59: =IF(LEFT(VLOOKUP($AL59,NI!$B$5:$AL$2030,31,FALSE),1)="#","-",VLOOKUP($AL59,NI!$B$5:$AL$2030,31,FALSE)) -> #NAME? | AU59: =IF(LEFT(VLOOKUP($AL59,NI!$B$5:$AL$2030,32,FALSE),1)="#","-",VLOOKUP($AL59,NI!$B$5:$AL$2030,32,FALSE)) -> #NAME? | AV59: =IF(LEFT(VLOOKUP($AL59,NI!$B$5:$AL$2030,33,FALSE),1)="#","-",VLOOKUP($AL59,NI!$B$5:$AL$2030,33,FALSE)) -> #NAME? | AW59: =VLOOKUP($AL59,NI!$B$5:$AL$2030,22,FALSE) -> #NAME? | BT59: 依信評 | BZ59: 依發行人 (Top 10 vol.)
B60: =+B59+1 -> 7 | S60: 消費 | T60: =VLOOKUP($AD60,'市場監控 '!$E$7:$W$194,6,FALSE) -> #NAME? | U60: =VLOOKUP($AD60,'市場監控 '!$E$7:$W$194,7,FALSE) -> #NAME? | V60: =VLOOKUP($AD60,'市場監控 '!$E$7:$W$194,8,FALSE) -> - | W60: =VLOOKUP($AD60,'市場監控 '!$E$7:$W$194,10,FALSE) -> - | X60: =VLOOKUP($AD60,'市場監控 '!$E$7:$W$194,12,FALSE) -> - | Y60: =VLOOKUP($AD60,'市場監控 '!$E$7:$W$194,14,FALSE) -> - | Z60: =VLOOKUP($AD60,'市場監控 '!$E$7:$W$194,15,FALSE) -> - | AA60: =VLOOKUP($AD60,'市場監控 '!$E$7:$W$194,17,FALSE) -> #NAME? | AB60: =VLOOKUP($AD60,'市場監控 '!$E$7:$W$194,18,FALSE) -> #NAME? | AC60: =VLOOKUP($AD60,'市場監控 '!$E$7:$W$194,19,FALSE) -> #NAME? | AD60: WMT US Equity | AE60: 沃爾瑪公司 | AJ60: =VLOOKUP($AL60,NI!$B$5:$AL$2030,6,FALSE) -> #NAME? | AK60: =VLOOKUP($AL60,NI!$B$5:$AL$2030,2,FALSE) -> #NAME? | AL60: =NI!B17 -> #NAME? | AM60: =VLOOKUP($AL60,NI!$B$5:$AL$2030,11,FALSE) -> #NAME? | AN60: =VLOOKUP($AL60,NI!$B$5:$AL$2030,12,FALSE)/1000000 -> #NAME? | AP60: =IF(ISNUMBER(VLOOKUP($AL60,NI!$B$5:$AL$2030,13,FALSE)),VLOOKUP($AL60,NI!$B$5:$AL$2030,13,FALSE),"-") -> - | AQ60: =VLOOKUP($AL60,NI!$B$5:$AL$2030,4,FALSE) -> #NAME? | AR60: =VLOOKUP($AL60,NI!$B$5:$AL$2030,3,FALSE) -> #NAME? | AS60: =VLOOKUP($AL60,NI!$B$5:$AL$2030,4,FALSE) -> #NAME? | AT60: =IF(LEFT(VLOOKUP($AL60,NI!$B$5:$AL$2030,31,FALSE),1)="#","-",VLOOKUP($AL60,NI!$B$5:$AL$2030,31,FALSE)) -> #NAME? | AU60: =IF(LEFT(VLOOKUP($AL60,NI!$B$5:$AL$2030,32,FALSE),1)="#","-",VLOOKUP($AL60,NI!$B$5:$AL$2030,32,FALSE)) -> #NAME? | AV60: =IF(LEFT(VLOOKUP($AL60,NI!$B$5:$AL$2030,33,FALSE),1)="#","-",VLOOKUP($AL60,NI!$B$5:$AL$2030,33,FALSE)) -> #NAME? | AW60: =VLOOKUP($AL60,NI!$B$5:$AL$2030,22,FALSE) -> #NAME? | EX60: 2023年4月 | EY60: 第一共和銀行臨近破產，暫停派息、股價下跌。 | FE60: APO | FF60: Apollo Global Management | FH60: 480 | FI60: Direct Lending, Structured Credit, Opportunistic Credit
B61: =+B60+1 -> 8 | T61: =VLOOKUP($AD61,'市場監控 '!$E$7:$W$194,6,FALSE) -> #NAME? | U61: =VLOOKUP($AD61,'市場監控 '!$E$7:$W$194,7,FALSE) -> #NAME? | V61: =VLOOKUP($AD61,'市場監控 '!$E$7:$W$194,8,FALSE) -> - | W61: =VLOOKUP($AD61,'市場監控 '!$E$7:$W$194,10,FALSE) -> - | X61: =VLOOKUP($AD61,'市場監控 '!$E$7:$W$194,12,FALSE) -> - | Y61: =VLOOKUP($AD61,'市場監控 '!$E$7:$W$194,14,FALSE) -> - | Z61: =VLOOKUP($AD61,'市場監控 '!$E$7:$W$194,15,FALSE) -> - | AA61: =VLOOKUP($AD61,'市場監控 '!$E$7:$W$194,17,FALSE) -> #NAME? | AB61: =VLOOKUP($AD61,'市場監控 '!$E$7:$W$194,18,FALSE) -> #NAME? | AC61: =VLOOKUP($AD61,'市場監控 '!$E$7:$W$194,19,FALSE) -> #NAME? | AD61: cost US Equity | AE61: 好市多公司 | AJ61: =VLOOKUP($AL61,NI!$B$5:$AL$2030,6,FALSE) -> #NAME? | AK61: =VLOOKUP($AL61,NI!$B$5:$AL$2030,2,FALSE) -> #NAME? | AL61: =NI!B18 -> #NAME? | AM61: =VLOOKUP($AL61,NI!$B$5:$AL$2030,11,FALSE) -> #NAME? | AN61: =VLOOKUP($AL61,NI!$B$5:$AL$2030,12,FALSE)/1000000 -> #NAME? | AP61: =IF(ISNUMBER(VLOOKUP($AL61,NI!$B$5:$AL$2030,13,FALSE)),VLOOKUP($AL61,NI!$B$5:$AL$2030,13,FALSE),"-") -> - | AQ61: =VLOOKUP($AL61,NI!$B$5:$AL$2030,4,FALSE) -> #NAME? | AR61: =VLOOKUP($AL61,NI!$B$5:$AL$2030,3,FALSE) -> #NAME? | AS61: =VLOOKUP($AL61,NI!$B$5:$AL$2030,4,FALSE) -> #NAME? | AT61: =IF(LEFT(VLOOKUP($AL61,NI!$B$5:$AL$2030,31,FALSE),1)="#","-",VLOOKUP($AL61,NI!$B$5:$AL$2030,31,FALSE)) -> #NAME? | AU61: =IF(LEFT(VLOOKUP($AL61,NI!$B$5:$AL$2030,32,FALSE),1)="#","-",VLOOKUP($AL61,NI!$B$5:$AL$2030,32,FALSE)) -> #NAME? | AV61: =IF(LEFT(VLOOKUP($AL61,NI!$B$5:$AL$2030,33,FALSE),1)="#","-",VLOOKUP($AL61,NI!$B$5:$AL$2030,33,FALSE)) -> #NAME? | AW61: =VLOOKUP($AL61,NI!$B$5:$AL$2030,22,FALSE) -> #NAME? | EN61: MTRN | EO61: 合金/磁粉 | EP61: Ohio工廠生產高溫磁粉 | ER61: 與歐洲車廠簽長期供應協議
B62: =+B61+1 -> 9 | T62: =VLOOKUP($AD62,'市場監控 '!$E$7:$W$194,6,FALSE) -> #NAME? | U62: =VLOOKUP($AD62,'市場監控 '!$E$7:$W$194,7,FALSE) -> #NAME? | V62: =VLOOKUP($AD62,'市場監控 '!$E$7:$W$194,8,FALSE) -> - | W62: =VLOOKUP($AD62,'市場監控 '!$E$7:$W$194,10,FALSE) -> - | X62: =VLOOKUP($AD62,'市場監控 '!$E$7:$W$194,12,FALSE) -> - | Y62: =VLOOKUP($AD62,'市場監控 '!$E$7:$W$194,14,FALSE) -> - | Z62: =VLOOKUP($AD62,'市場監控 '!$E$7:$W$194,15,FALSE) -> - | AA62: =VLOOKUP($AD62,'市場監控 '!$E$7:$W$194,17,FALSE) -> #NAME? | AB62: =VLOOKUP($AD62,'市場監控 '!$E$7:$W$194,18,FALSE) -> #NAME? | AC62: =VLOOKUP($AD62,'市場監控 '!$E$7:$W$194,19,FALSE) -> #NAME? | AD62: abt us Equity | AE62: 亞培 | AJ62: =VLOOKUP($AL62,NI!$B$5:$AL$2030,6,FALSE) -> #NAME? | AK62: =VLOOKUP($AL62,NI!$B$5:$AL$2030,2,FALSE) -> #NAME? | AL62: =NI!B19 -> #NAME? | AM62: =VLOOKUP($AL62,NI!$B$5:$AL$2030,11,FALSE) -> #NAME? | AN62: =VLOOKUP($AL62,NI!$B$5:$AL$2030,12,FALSE)/1000000 -> #NAME? | AP62: =IF(ISNUMBER(VLOOKUP($AL62,NI!$B$5:$AL$2030,13,FALSE)),VLOOKUP($AL62,NI!$B$5:$AL$2030,13,FALSE),"-") -> - | AQ62: =VLOOKUP($AL62,NI!$B$5:$AL$2030,4,FALSE) -> #NAME? | AR62: =VLOOKUP($AL62,NI!$B$5:$AL$2030,3,FALSE) -> #NAME? | AS62: =VLOOKUP($AL62,NI!$B$5:$AL$2030,4,FALSE) -> #NAME? | AT62: =IF(LEFT(VLOOKUP($AL62,NI!$B$5:$AL$2030,31,FALSE),1)="#","-",VLOOKUP($AL62,NI!$B$5:$AL$2030,31,FALSE)) -> #NAME? | AU62: =IF(LEFT(VLOOKUP($AL62,NI!$B$5:$AL$2030,32,FALSE),1)="#","-",VLOOKUP($AL62,NI!$B$5:$AL$2030,32,FALSE)) -> #NAME? | AV62: =IF(LEFT(VLOOKUP($AL62,NI!$B$5:$AL$2030,33,FALSE),1)="#","-",VLOOKUP($AL62,NI!$B$5:$AL$2030,33,FALSE)) -> #NAME? | AW62: =VLOOKUP($AL62,NI!$B$5:$AL$2030,22,FALSE) -> #NAME?
B63: =+B62+1 -> 10 | T63: =VLOOKUP($AD63,'市場監控 '!$E$7:$W$194,6,FALSE) -> #NAME? | U63: =VLOOKUP($AD63,'市場監控 '!$E$7:$W$194,7,FALSE) -> #NAME? | V63: =VLOOKUP($AD63,'市場監控 '!$E$7:$W$194,8,FALSE) -> - | W63: =VLOOKUP($AD63,'市場監控 '!$E$7:$W$194,10,FALSE) -> - | X63: =VLOOKUP($AD63,'市場監控 '!$E$7:$W$194,12,FALSE) -> - | Y63: =VLOOKUP($AD63,'市場監控 '!$E$7:$W$194,14,FALSE) -> - | Z63: =VLOOKUP($AD63,'市場監控 '!$E$7:$W$194,15,FALSE) -> - | AA63: =VLOOKUP($AD63,'市場監控 '!$E$7:$W$194,17,FALSE) -> #NAME? | AB63: =VLOOKUP($AD63,'市場監控 '!$E$7:$W$194,18,FALSE) -> #NAME? | AC63: =VLOOKUP($AD63,'市場監控 '!$E$7:$W$194,19,FALSE) -> #NAME? | AD63: nesn sw Equity | AE63: 麥當勞公司 | AJ63: =VLOOKUP($AL63,NI!$B$5:$AL$2030,6,FALSE) -> #NAME? | AK63: =VLOOKUP($AL63,NI!$B$5:$AL$2030,2,FALSE) -> #NAME? | AL63: =NI!B20 -> #NAME? | AM63: =VLOOKUP($AL63,NI!$B$5:$AL$2030,11,FALSE) -> #NAME? | AN63: =VLOOKUP($AL63,NI!$B$5:$AL$2030,12,FALSE)/1000000 -> #NAME? | AP63: =IF(ISNUMBER(VLOOKUP($AL63,NI!$B$5:$AL$2030,13,FALSE)),VLOOKUP($AL63,NI!$B$5:$AL$2030,13,FALSE),"-") -> - | AQ63: =VLOOKUP($AL63,NI!$B$5:$AL$2030,4,FALSE) -> #NAME? | AR63: =VLOOKUP($AL63,NI!$B$5:$AL$2030,3,FALSE) -> #NAME? | AS63: =VLOOKUP($AL63,NI!$B$5:$AL$2030,4,FALSE) -> #NAME? | AT63: =IF(LEFT(VLOOKUP($AL63,NI!$B$5:$AL$2030,31,FALSE),1)="#","-",VLOOKUP($AL63,NI!$B$5:$AL$2030,31,FALSE)) -> #NAME? | AU63: =IF(LEFT(VLOOKUP($AL63,NI!$B$5:$AL$2030,32,FALSE),1)="#","-",VLOOKUP($AL63,NI!$B$5:$AL$2030,32,FALSE)) -> #NAME? | AV63: =IF(LEFT(VLOOKUP($AL63,NI!$B$5:$AL$2030,33,FALSE),1)="#","-",VLOOKUP($AL63,NI!$B$5:$AL$2030,33,FALSE)) -> #NAME? | AW63: =VLOOKUP($AL63,NI!$B$5:$AL$2030,22,FALSE) -> #NAME? | EX63: 45047 | EY63: 監管機構接管了第一共和銀行。隨後，其他地區性銀行出現連鎖反應，存款價值下跌。 | FE63: OWL | FF63: Blue Owl Capital | FH63: 95.1 | FI63: Direct Lending, GP Financing, Triple Net Lease
B64: =+B63+1 -> 11 | T64: =VLOOKUP($AD64,'市場監控 '!$E$7:$W$194,6,FALSE) -> #NAME? | U64: =VLOOKUP($AD64,'市場監控 '!$E$7:$W$194,7,FALSE) -> #NAME? | V64: =VLOOKUP($AD64,'市場監控 '!$E$7:$W$194,8,FALSE) -> - | W64: =VLOOKUP($AD64,'市場監控 '!$E$7:$W$194,10,FALSE) -> - | X64: =VLOOKUP($AD64,'市場監控 '!$E$7:$W$194,12,FALSE) -> - | Y64: =VLOOKUP($AD64,'市場監控 '!$E$7:$W$194,14,FALSE) -> - | Z64: =VLOOKUP($AD64,'市場監控 '!$E$7:$W$194,15,FALSE) -> - | AA64: =VLOOKUP($AD64,'市場監控 '!$E$7:$W$194,17,FALSE) -> #NAME? | AB64: =VLOOKUP($AD64,'市場監控 '!$E$7:$W$194,18,FALSE) -> #NAME? | AC64: =VLOOKUP($AD64,'市場監控 '!$E$7:$W$194,19,FALSE) -> #NAME? | AD64: pg us Equity | AE64: 雀巢 | AJ64: =VLOOKUP($AL64,NI!$B$5:$AL$2030,6,FALSE) -> #NAME? | AK64: =VLOOKUP($AL64,NI!$B$5:$AL$2030,2,FALSE) -> #NAME? | AL64: =NI!B21 -> #NAME? | AM64: =VLOOKUP($AL64,NI!$B$5:$AL$2030,11,FALSE) -> #NAME? | AN64: =VLOOKUP($AL64,NI!$B$5:$AL$2030,12,FALSE)/1000000 -> #NAME? | AP64: =IF(ISNUMBER(VLOOKUP($AL64,NI!$B$5:$AL$2030,13,FALSE)),VLOOKUP($AL64,NI!$B$5:$AL$2030,13,FALSE),"-") -> - | AQ64: =VLOOKUP($AL64,NI!$B$5:$AL$2030,4,FALSE) -> #NAME? | AR64: =VLOOKUP($AL64,NI!$B$5:$AL$2030,3,FALSE) -> #NAME? | AS64: =VLOOKUP($AL64,NI!$B$5:$AL$2030,4,FALSE) -> #NAME? | AT64: =IF(LEFT(VLOOKUP($AL64,NI!$B$5:$AL$2030,31,FALSE),1)="#","-",VLOOKUP($AL64,NI!$B$5:$AL$2030,31,FALSE)) -> #NAME? | AU64: =IF(LEFT(VLOOKUP($AL64,NI!$B$5:$AL$2030,32,FALSE),1)="#","-",VLOOKUP($AL64,NI!$B$5:$AL$2030,32,FALSE)) -> #NAME? | AV64: =IF(LEFT(VLOOKUP($AL64,NI!$B$5:$AL$2030,33,FALSE),1)="#","-",VLOOKUP($AL64,NI!$B$5:$AL$2030,33,FALSE)) -> #NAME? | AW64: =VLOOKUP($AL64,NI!$B$5:$AL$2030,22,FALSE) -> #NAME? | EN64: AREC | EO64: 稀土回收 | EP64: 回收與再利用技術 | ER64: 聚焦環保稀土回收，股價波動大
B65: =+B64+1 -> 12 | T65: =VLOOKUP($AD65,'市場監控 '!$E$7:$W$194,6,FALSE) -> #NAME? | U65: =VLOOKUP($AD65,'市場監控 '!$E$7:$W$194,7,FALSE) -> #NAME? | V65: =VLOOKUP($AD65,'市場監控 '!$E$7:$W$194,8,FALSE) -> - | W65: =VLOOKUP($AD65,'市場監控 '!$E$7:$W$194,10,FALSE) -> - | X65: =VLOOKUP($AD65,'市場監控 '!$E$7:$W$194,12,FALSE) -> - | Y65: =VLOOKUP($AD65,'市場監控 '!$E$7:$W$194,14,FALSE) -> - | Z65: =VLOOKUP($AD65,'市場監控 '!$E$7:$W$194,15,FALSE) -> - | AA65: =VLOOKUP($AD65,'市場監控 '!$E$7:$W$194,17,FALSE) -> #NAME? | AB65: =VLOOKUP($AD65,'市場監控 '!$E$7:$W$194,18,FALSE) -> #NAME? | AC65: =VLOOKUP($AD65,'市場監控 '!$E$7:$W$194,19,FALSE) -> #NAME? | AD65: KO US Equity | AE65: 寶僑公司 | AJ65: =VLOOKUP($AL65,NI!$B$5:$AL$2030,6,FALSE) -> #NAME? | AK65: =VLOOKUP($AL65,NI!$B$5:$AL$2030,2,FALSE) -> #NAME? | AL65: =NI!B22 -> #NAME? | AM65: =VLOOKUP($AL65,NI!$B$5:$AL$2030,11,FALSE) -> #NAME? | AN65: =VLOOKUP($AL65,NI!$B$5:$AL$2030,12,FALSE)/1000000 -> #NAME? | AP65: =IF(ISNUMBER(VLOOKUP($AL65,NI!$B$5:$AL$2030,13,FALSE)),VLOOKUP($AL65,NI!$B$5:$AL$2030,13,FALSE),"-") -> - | AQ65: =VLOOKUP($AL65,NI!$B$5:$AL$2030,4,FALSE) -> #NAME? | AR65: =VLOOKUP($AL65,NI!$B$5:$AL$2030,3,FALSE) -> #NAME? | AS65: =VLOOKUP($AL65,NI!$B$5:$AL$2030,4,FALSE) -> #NAME? | AT65: =IF(LEFT(VLOOKUP($AL65,NI!$B$5:$AL$2030,31,FALSE),1)="#","-",VLOOKUP($AL65,NI!$B$5:$AL$2030,31,FALSE)) -> #NAME? | AU65: =IF(LEFT(VLOOKUP($AL65,NI!$B$5:$AL$2030,32,FALSE),1)="#","-",VLOOKUP($AL65,NI!$B$5:$AL$2030,32,FALSE)) -> #NAME? | AV65: =IF(LEFT(VLOOKUP($AL65,NI!$B$5:$AL$2030,33,FALSE),1)="#","-",VLOOKUP($AL65,NI!$B$5:$AL$2030,33,FALSE)) -> #NAME? | AW65: =VLOOKUP($AL65,NI!$B$5:$AL$2030,22,FALSE) -> #NAME?
B66: =+B65+1 -> 13 | C66: 公債市場 | J66: 美國短天期利率承壓 | T66: =VLOOKUP($AD66,'市場監控 '!$E$7:$W$194,6,FALSE) -> #NAME? | U66: =VLOOKUP($AD66,'市場監控 '!$E$7:$W$194,7,FALSE) -> #NAME? | V66: =VLOOKUP($AD66,'市場監控 '!$E$7:$W$194,8,FALSE) -> - | W66: =VLOOKUP($AD66,'市場監控 '!$E$7:$W$194,10,FALSE) -> - | X66: =VLOOKUP($AD66,'市場監控 '!$E$7:$W$194,12,FALSE) -> - | Y66: =VLOOKUP($AD66,'市場監控 '!$E$7:$W$194,14,FALSE) -> - | Z66: =VLOOKUP($AD66,'市場監控 '!$E$7:$W$194,15,FALSE) -> - | AA66: =VLOOKUP($AD66,'市場監控 '!$E$7:$W$194,17,FALSE) -> #NAME? | AB66: =VLOOKUP($AD66,'市場監控 '!$E$7:$W$194,18,FALSE) -> #NAME? | AC66: =VLOOKUP($AD66,'市場監控 '!$E$7:$W$194,19,FALSE) -> #NAME? | AD66: MCD US Equity | AE66: 可口可樂公司 | AJ66: =VLOOKUP($AL66,NI!$B$5:$AL$2030,6,FALSE) -> #NAME? | AK66: =VLOOKUP($AL66,NI!$B$5:$AL$2030,2,FALSE) -> #NAME? | AL66: =NI!B23 -> #NAME? | AM66: =VLOOKUP($AL66,NI!$B$5:$AL$2030,11,FALSE) -> #NAME? | AN66: =VLOOKUP($AL66,NI!$B$5:$AL$2030,12,FALSE)/1000000 -> #NAME? | AP66: =IF(ISNUMBER(VLOOKUP($AL66,NI!$B$5:$AL$2030,13,FALSE)),VLOOKUP($AL66,NI!$B$5:$AL$2030,13,FALSE),"-") -> - | AQ66: =VLOOKUP($AL66,NI!$B$5:$AL$2030,4,FALSE) -> #NAME? | AR66: =VLOOKUP($AL66,NI!$B$5:$AL$2030,3,FALSE) -> #NAME? | AS66: =VLOOKUP($AL66,NI!$B$5:$AL$2030,4,FALSE) -> #NAME? | AT66: =IF(LEFT(VLOOKUP($AL66,NI!$B$5:$AL$2030,31,FALSE),1)="#","-",VLOOKUP($AL66,NI!$B$5:$AL$2030,31,FALSE)) -> #NAME? | AU66: =IF(LEFT(VLOOKUP($AL66,NI!$B$5:$AL$2030,32,FALSE),1)="#","-",VLOOKUP($AL66,NI!$B$5:$AL$2030,32,FALSE)) -> #NAME? | AV66: =IF(LEFT(VLOOKUP($AL66,NI!$B$5:$AL$2030,33,FALSE),1)="#","-",VLOOKUP($AL66,NI!$B$5:$AL$2030,33,FALSE)) -> #NAME? | AW66: =VLOOKUP($AL66,NI!$B$5:$AL$2030,22,FALSE) -> #NAME?
B67: =+B66+1 -> 14 | T67: =VLOOKUP($AD67,'市場監控 '!$E$7:$W$194,6,FALSE) -> #NAME? | U67: =VLOOKUP($AD67,'市場監控 '!$E$7:$W$194,7,FALSE) -> #NAME? | V67: =VLOOKUP($AD67,'市場監控 '!$E$7:$W$194,8,FALSE) -> - | W67: =VLOOKUP($AD67,'市場監控 '!$E$7:$W$194,10,FALSE) -> - | X67: =VLOOKUP($AD67,'市場監控 '!$E$7:$W$194,12,FALSE) -> - | Y67: =VLOOKUP($AD67,'市場監控 '!$E$7:$W$194,14,FALSE) -> - | Z67: =VLOOKUP($AD67,'市場監控 '!$E$7:$W$194,15,FALSE) -> - | AA67: =VLOOKUP($AD67,'市場監控 '!$E$7:$W$194,17,FALSE) -> #NAME? | AB67: =VLOOKUP($AD67,'市場監控 '!$E$7:$W$194,18,FALSE) -> #NAME? | AC67: =VLOOKUP($AD67,'市場監控 '!$E$7:$W$194,19,FALSE) -> #NAME? | AD67: MMM US Equity | AE67: 3M | AJ67: =VLOOKUP($AL67,NI!$B$5:$AL$2030,6,FALSE) -> #NAME? | AK67: =VLOOKUP($AL67,NI!$B$5:$AL$2030,2,FALSE) -> #NAME? | AL67: =NI!B24 -> #NAME? | AM67: =VLOOKUP($AL67,NI!$B$5:$AL$2030,11,FALSE) -> #NAME? | AN67: =VLOOKUP($AL67,NI!$B$5:$AL$2030,12,FALSE)/1000000 -> #NAME? | AP67: =IF(ISNUMBER(VLOOKUP($AL67,NI!$B$5:$AL$2030,13,FALSE)),VLOOKUP($AL67,NI!$B$5:$AL$2030,13,FALSE),"-") -> - | AQ67: =VLOOKUP($AL67,NI!$B$5:$AL$2030,4,FALSE) -> #NAME? | AR67: =VLOOKUP($AL67,NI!$B$5:$AL$2030,3,FALSE) -> #NAME? | AS67: =VLOOKUP($AL67,NI!$B$5:$AL$2030,4,FALSE) -> #NAME? | AT67: =IF(LEFT(VLOOKUP($AL67,NI!$B$5:$AL$2030,31,FALSE),1)="#","-",VLOOKUP($AL67,NI!$B$5:$AL$2030,31,FALSE)) -> #NAME? | AU67: =IF(LEFT(VLOOKUP($AL67,NI!$B$5:$AL$2030,32,FALSE),1)="#","-",VLOOKUP($AL67,NI!$B$5:$AL$2030,32,FALSE)) -> #NAME? | AV67: =IF(LEFT(VLOOKUP($AL67,NI!$B$5:$AL$2030,33,FALSE),1)="#","-",VLOOKUP($AL67,NI!$B$5:$AL$2030,33,FALSE)) -> #NAME? | AW67: =VLOOKUP($AL67,NI!$B$5:$AL$2030,22,FALSE) -> #NAME? | EN67: CRML | EO67: 礦場開發 | EP67: 格陵蘭稀土礦權 | ER67: 美國政府擬入股，擴展北極供應鏈
B68: =+B67+1 -> 15 | C68: 主要公債 | E68: 利率 | F68: 前週利率 | G68: 週變化 | H68: 週變化(%) | T68: =VLOOKUP($AD68,'市場監控 '!$E$7:$W$194,6,FALSE) -> #NAME? | U68: =VLOOKUP($AD68,'市場監控 '!$E$7:$W$194,7,FALSE) -> #NAME? | V68: =VLOOKUP($AD68,'市場監控 '!$E$7:$W$194,8,FALSE) -> - | W68: =VLOOKUP($AD68,'市場監控 '!$E$7:$W$194,10,FALSE) -> - | X68: =VLOOKUP($AD68,'市場監控 '!$E$7:$W$194,12,FALSE) -> - | Y68: =VLOOKUP($AD68,'市場監控 '!$E$7:$W$194,14,FALSE) -> - | Z68: =VLOOKUP($AD68,'市場監控 '!$E$7:$W$194,15,FALSE) -> - | AA68: =VLOOKUP($AD68,'市場監控 '!$E$7:$W$194,17,FALSE) -> #NAME? | AB68: =VLOOKUP($AD68,'市場監控 '!$E$7:$W$194,18,FALSE) -> #NAME? | AC68: =VLOOKUP($AD68,'市場監控 '!$E$7:$W$194,19,FALSE) -> #NAME? | AD68: unh us Equity | AE68: 聯合健康集團公司 | AJ68: =VLOOKUP($AL68,NI!$B$5:$AL$2030,6,FALSE) -> #NAME? | AK68: =VLOOKUP($AL68,NI!$B$5:$AL$2030,2,FALSE) -> #NAME? | AL68: =NI!B25 -> #NAME? | AM68: =VLOOKUP($AL68,NI!$B$5:$AL$2030,11,FALSE) -> #NAME? | AN68: =VLOOKUP($AL68,NI!$B$5:$AL$2030,12,FALSE)/1000000 -> #NAME? | AP68: =IF(ISNUMBER(VLOOKUP($AL68,NI!$B$5:$AL$2030,13,FALSE)),VLOOKUP($AL68,NI!$B$5:$AL$2030,13,FALSE),"-") -> - | AQ68: =VLOOKUP($AL68,NI!$B$5:$AL$2030,4,FALSE) -> #NAME? | AR68: =VLOOKUP($AL68,NI!$B$5:$AL$2030,3,FALSE) -> #NAME? | AS68: =VLOOKUP($AL68,NI!$B$5:$AL$2030,4,FALSE) -> #NAME? | AT68: =IF(LEFT(VLOOKUP($AL68,NI!$B$5:$AL$2030,31,FALSE),1)="#","-",VLOOKUP($AL68,NI!$B$5:$AL$2030,31,FALSE)) -> #NAME? | AU68: =IF(LEFT(VLOOKUP($AL68,NI!$B$5:$AL$2030,32,FALSE),1)="#","-",VLOOKUP($AL68,NI!$B$5:$AL$2030,32,FALSE)) -> #NAME? | AV68: =IF(LEFT(VLOOKUP($AL68,NI!$B$5:$AL$2030,33,FALSE),1)="#","-",VLOOKUP($AL68,NI!$B$5:$AL$2030,33,FALSE)) -> #NAME? | AW68: =VLOOKUP($AL68,NI!$B$5:$AL$2030,22,FALSE) -> #NAME? | EX68: 歷年銀行倒閉家數及資產規模 | FE68: 私募信貸AUM
B69: =+B68+1 -> 16 | C69: =Comment_page!$B9 -> 美國2Y公債 | E69: =Comment_page!$C9 -> #NAME? | F69: =Comment_page!D9 -> #NAME? | G69: =Comment_page!E9 -> #NAME? | H69: =Comment_page!F9 -> #NAME? | S69: 能源 | T69: =VLOOKUP($AD69,'市場監控 '!$E$7:$W$194,6,FALSE) -> #NAME? | U69: =VLOOKUP($AD69,'市場監控 '!$E$7:$W$194,7,FALSE) -> #NAME? | V69: =VLOOKUP($AD69,'市場監控 '!$E$7:$W$194,8,FALSE) -> - | W69: =VLOOKUP($AD69,'市場監控 '!$E$7:$W$194,10,FALSE) -> - | X69: =VLOOKUP($AD69,'市場監控 '!$E$7:$W$194,12,FALSE) -> - | Y69: =VLOOKUP($AD69,'市場監控 '!$E$7:$W$194,14,FALSE) -> - | Z69: =VLOOKUP($AD69,'市場監控 '!$E$7:$W$194,15,FALSE) -> - | AA69: =VLOOKUP($AD69,'市場監控 '!$E$7:$W$194,17,FALSE) -> #NAME? | AB69: =VLOOKUP($AD69,'市場監控 '!$E$7:$W$194,18,FALSE) -> #NAME? | AC69: =VLOOKUP($AD69,'市場監控 '!$E$7:$W$194,19,FALSE) -> #NAME? | AD69: xom us Equity | AE69: 墨西哥石油公司 | AJ69: =VLOOKUP($AL69,NI!$B$5:$AL$2030,6,FALSE) -> #NAME? | AK69: =VLOOKUP($AL69,NI!$B$5:$AL$2030,2,FALSE) -> #NAME? | AL69: =NI!B26 -> #NAME? | AM69: =VLOOKUP($AL69,NI!$B$5:$AL$2030,11,FALSE) -> #NAME? | AN69: =VLOOKUP($AL69,NI!$B$5:$AL$2030,12,FALSE)/1000000 -> #NAME? | AP69: =IF(ISNUMBER(VLOOKUP($AL69,NI!$B$5:$AL$2030,13,FALSE)),VLOOKUP($AL69,NI!$B$5:$AL$2030,13,FALSE),"-") -> - | AQ69: =VLOOKUP($AL69,NI!$B$5:$AL$2030,4,FALSE) -> #NAME? | AR69: =VLOOKUP($AL69,NI!$B$5:$AL$2030,3,FALSE) -> #NAME? | AS69: =VLOOKUP($AL69,NI!$B$5:$AL$2030,4,FALSE) -> #NAME? | AT69: =IF(LEFT(VLOOKUP($AL69,NI!$B$5:$AL$2030,31,FALSE),1)="#","-",VLOOKUP($AL69,NI!$B$5:$AL$2030,31,FALSE)) -> #NAME? | AU69: =IF(LEFT(VLOOKUP($AL69,NI!$B$5:$AL$2030,32,FALSE),1)="#","-",VLOOKUP($AL69,NI!$B$5:$AL$2030,32,FALSE)) -> #NAME? | AV69: =IF(LEFT(VLOOKUP($AL69,NI!$B$5:$AL$2030,33,FALSE),1)="#","-",VLOOKUP($AL69,NI!$B$5:$AL$2030,33,FALSE)) -> #NAME? | AW69: =VLOOKUP($AL69,NI!$B$5:$AL$2030,22,FALSE) -> #NAME?
B70: =+B69+1 -> 17 | C70: =Comment_page!$B10 -> 美國5Y公債 | E70: =Comment_page!$C10 -> #NAME? | F70: =Comment_page!D10 -> #NAME? | G70: =Comment_page!E10 -> #NAME? | H70: =Comment_page!F10 -> #NAME? | T70: =VLOOKUP($AD70,'市場監控 '!$E$7:$W$194,6,FALSE) -> #NAME? | U70: =VLOOKUP($AD70,'市場監控 '!$E$7:$W$194,7,FALSE) -> #NAME? | V70: =VLOOKUP($AD70,'市場監控 '!$E$7:$W$194,8,FALSE) -> - | W70: =VLOOKUP($AD70,'市場監控 '!$E$7:$W$194,10,FALSE) -> - | X70: =VLOOKUP($AD70,'市場監控 '!$E$7:$W$194,12,FALSE) -> - | Y70: =VLOOKUP($AD70,'市場監控 '!$E$7:$W$194,14,FALSE) -> - | Z70: =VLOOKUP($AD70,'市場監控 '!$E$7:$W$194,15,FALSE) -> - | AA70: =VLOOKUP($AD70,'市場監控 '!$E$7:$W$194,17,FALSE) -> #NAME? | AB70: =VLOOKUP($AD70,'市場監控 '!$E$7:$W$194,18,FALSE) -> #NAME? | AC70: =VLOOKUP($AD70,'市場監控 '!$E$7:$W$194,19,FALSE) -> #NAME? | AD70: shel ln Equity | AE70: 印尼國家石油有限公司 | AJ70: =VLOOKUP($AL70,NI!$B$5:$AL$2030,6,FALSE) -> #NAME? | AK70: =VLOOKUP($AL70,NI!$B$5:$AL$2030,2,FALSE) -> #NAME? | AL70: =NI!B27 -> #NAME? | AM70: =VLOOKUP($AL70,NI!$B$5:$AL$2030,11,FALSE) -> #NAME? | AN70: =VLOOKUP($AL70,NI!$B$5:$AL$2030,12,FALSE)/1000000 -> #NAME? | AP70: =IF(ISNUMBER(VLOOKUP($AL70,NI!$B$5:$AL$2030,13,FALSE)),VLOOKUP($AL70,NI!$B$5:$AL$2030,13,FALSE),"-") -> - | AQ70: =VLOOKUP($AL70,NI!$B$5:$AL$2030,4,FALSE) -> #NAME? | AR70: =VLOOKUP($AL70,NI!$B$5:$AL$2030,3,FALSE) -> #NAME? | AS70: =VLOOKUP($AL70,NI!$B$5:$AL$2030,4,FALSE) -> #NAME? | AT70: =IF(LEFT(VLOOKUP($AL70,NI!$B$5:$AL$2030,31,FALSE),1)="#","-",VLOOKUP($AL70,NI!$B$5:$AL$2030,31,FALSE)) -> #NAME? | AU70: =IF(LEFT(VLOOKUP($AL70,NI!$B$5:$AL$2030,32,FALSE),1)="#","-",VLOOKUP($AL70,NI!$B$5:$AL$2030,32,FALSE)) -> #NAME? | AV70: =IF(LEFT(VLOOKUP($AL70,NI!$B$5:$AL$2030,33,FALSE),1)="#","-",VLOOKUP($AL70,NI!$B$5:$AL$2030,33,FALSE)) -> #NAME? | AW70: =VLOOKUP($AL70,NI!$B$5:$AL$2030,22,FALSE) -> #NAME?
B71: =+B70+1 -> 18 | C71: =Comment_page!$B11 -> 美國10Y公債 | E71: =Comment_page!$C11 -> #NAME? | F71: =Comment_page!D11 -> #NAME? | G71: =Comment_page!E11 -> #NAME? | H71: =Comment_page!F11 -> #NAME? | T71: =VLOOKUP($AD71,'市場監控 '!$E$7:$W$194,6,FALSE) -> #NAME? | U71: =VLOOKUP($AD71,'市場監控 '!$E$7:$W$194,7,FALSE) -> #NAME? | V71: =VLOOKUP($AD71,'市場監控 '!$E$7:$W$194,8,FALSE) -> - | W71: =VLOOKUP($AD71,'市場監控 '!$E$7:$W$194,10,FALSE) -> - | X71: =VLOOKUP($AD71,'市場監控 '!$E$7:$W$194,12,FALSE) -> - | Y71: =VLOOKUP($AD71,'市場監控 '!$E$7:$W$194,14,FALSE) -> - | Z71: =VLOOKUP($AD71,'市場監控 '!$E$7:$W$194,15,FALSE) -> - | AA71: =VLOOKUP($AD71,'市場監控 '!$E$7:$W$194,17,FALSE) -> #NAME? | AB71: =VLOOKUP($AD71,'市場監控 '!$E$7:$W$194,18,FALSE) -> #NAME? | AC71: =VLOOKUP($AD71,'市場監控 '!$E$7:$W$194,19,FALSE) -> #NAME? | AD71: 1232Z MM Equity | AE71: 沙烏地阿拉伯國家石油公司 | AJ71: =VLOOKUP($AL71,NI!$B$5:$AL$2030,6,FALSE) -> #NAME? | AK71: =VLOOKUP($AL71,NI!$B$5:$AL$2030,2,FALSE) -> #NAME? | AL71: =NI!B28 -> #NAME? | AM71: =VLOOKUP($AL71,NI!$B$5:$AL$2030,11,FALSE) -> #NAME? | AN71: =VLOOKUP($AL71,NI!$B$5:$AL$2030,12,FALSE)/1000000 -> #NAME? | AP71: =IF(ISNUMBER(VLOOKUP($AL71,NI!$B$5:$AL$2030,13,FALSE)),VLOOKUP($AL71,NI!$B$5:$AL$2030,13,FALSE),"-") -> - | AQ71: =VLOOKUP($AL71,NI!$B$5:$AL$2030,4,FALSE) -> #NAME? | AR71: =VLOOKUP($AL71,NI!$B$5:$AL$2030,3,FALSE) -> #NAME? | AS71: =VLOOKUP($AL71,NI!$B$5:$AL$2030,4,FALSE) -> #NAME? | AT71: =IF(LEFT(VLOOKUP($AL71,NI!$B$5:$AL$2030,31,FALSE),1)="#","-",VLOOKUP($AL71,NI!$B$5:$AL$2030,31,FALSE)) -> #NAME? | AU71: =IF(LEFT(VLOOKUP($AL71,NI!$B$5:$AL$2030,32,FALSE),1)="#","-",VLOOKUP($AL71,NI!$B$5:$AL$2030,32,FALSE)) -> #NAME? | AV71: =IF(LEFT(VLOOKUP($AL71,NI!$B$5:$AL$2030,33,FALSE),1)="#","-",VLOOKUP($AL71,NI!$B$5:$AL$2030,33,FALSE)) -> #NAME? | AW71: =VLOOKUP($AL71,NI!$B$5:$AL$2030,22,FALSE) -> #NAME?
C72: =Comment_page!$B12 -> 美國30Y公債 | E72: =Comment_page!$C12 -> #NAME? | F72: =Comment_page!D12 -> #NAME? | G72: =Comment_page!E12 -> #NAME? | H72: =Comment_page!F12 -> #NAME? | T72: =VLOOKUP($AD72,'市場監控 '!$E$7:$W$194,6,FALSE) -> #NAME? | U72: =VLOOKUP($AD72,'市場監控 '!$E$7:$W$194,7,FALSE) -> #NAME? | V72: =VLOOKUP($AD72,'市場監控 '!$E$7:$W$194,8,FALSE) -> - | W72: =VLOOKUP($AD72,'市場監控 '!$E$7:$W$194,10,FALSE) -> - | X72: =VLOOKUP($AD72,'市場監控 '!$E$7:$W$194,12,FALSE) -> - | Y72: =VLOOKUP($AD72,'市場監控 '!$E$7:$W$194,14,FALSE) -> - | Z72: =VLOOKUP($AD72,'市場監控 '!$E$7:$W$194,15,FALSE) -> - | AA72: =VLOOKUP($AD72,'市場監控 '!$E$7:$W$194,17,FALSE) -> #NAME? | AB72: =VLOOKUP($AD72,'市場監控 '!$E$7:$W$194,18,FALSE) -> #NAME? | AC72: =VLOOKUP($AD72,'市場監控 '!$E$7:$W$194,19,FALSE) -> #NAME? | AD72: PERT IJ Equity | AE72: 殼牌公開有限公司 | AJ72: =VLOOKUP($AL72,NI!$B$5:$AL$2030,6,FALSE) -> #NAME? | AK72: =VLOOKUP($AL72,NI!$B$5:$AL$2030,2,FALSE) -> #NAME? | AL72: =NI!B29 -> #NAME? | AM72: =VLOOKUP($AL72,NI!$B$5:$AL$2030,11,FALSE) -> #NAME? | AN72: =VLOOKUP($AL72,NI!$B$5:$AL$2030,12,FALSE)/1000000 -> #NAME? | AP72: =IF(ISNUMBER(VLOOKUP($AL72,NI!$B$5:$AL$2030,13,FALSE)),VLOOKUP($AL72,NI!$B$5:$AL$2030,13,FALSE),"-") -> - | AQ72: =VLOOKUP($AL72,NI!$B$5:$AL$2030,4,FALSE) -> #NAME? | AR72: =VLOOKUP($AL72,NI!$B$5:$AL$2030,3,FALSE) -> #NAME? | AS72: =VLOOKUP($AL72,NI!$B$5:$AL$2030,4,FALSE) -> #NAME? | AT72: =IF(LEFT(VLOOKUP($AL72,NI!$B$5:$AL$2030,31,FALSE),1)="#","-",VLOOKUP($AL72,NI!$B$5:$AL$2030,31,FALSE)) -> #NAME? | AU72: =IF(LEFT(VLOOKUP($AL72,NI!$B$5:$AL$2030,32,FALSE),1)="#","-",VLOOKUP($AL72,NI!$B$5:$AL$2030,32,FALSE)) -> #NAME? | AV72: =IF(LEFT(VLOOKUP($AL72,NI!$B$5:$AL$2030,33,FALSE),1)="#","-",VLOOKUP($AL72,NI!$B$5:$AL$2030,33,FALSE)) -> #NAME? | AW72: =VLOOKUP($AL72,NI!$B$5:$AL$2030,22,FALSE) -> #NAME?
C73: =Comment_page!$B13 -> 日本10Y公債 | E73: =Comment_page!$C13 -> #NAME? | F73: =Comment_page!D13 -> #NAME? | G73: =Comment_page!E13 -> #NAME? | H73: =Comment_page!F13 -> #NAME? | T73: =VLOOKUP($AD73,'市場監控 '!$E$7:$W$194,6,FALSE) -> #NAME? | U73: =VLOOKUP($AD73,'市場監控 '!$E$7:$W$194,7,FALSE) -> #NAME? | V73: =VLOOKUP($AD73,'市場監控 '!$E$7:$W$194,8,FALSE) -> - | W73: =VLOOKUP($AD73,'市場監控 '!$E$7:$W$194,10,FALSE) -> - | X73: =VLOOKUP($AD73,'市場監控 '!$E$7:$W$194,12,FALSE) -> - | Y73: =VLOOKUP($AD73,'市場監控 '!$E$7:$W$194,14,FALSE) -> - | Z73: =VLOOKUP($AD73,'市場監控 '!$E$7:$W$194,15,FALSE) -> - | AA73: =VLOOKUP($AD73,'市場監控 '!$E$7:$W$194,17,FALSE) -> #NAME? | AB73: =VLOOKUP($AD73,'市場監控 '!$E$7:$W$194,18,FALSE) -> #NAME? | AC73: =VLOOKUP($AD73,'市場監控 '!$E$7:$W$194,19,FALSE) -> #NAME? | AD73: ARAMCO AB Equity | AE73: 埃克森美孚公司 | AJ73: =VLOOKUP($AL73,NI!$B$5:$AL$2030,6,FALSE) -> #NAME? | AK73: =VLOOKUP($AL73,NI!$B$5:$AL$2030,2,FALSE) -> #NAME? | AL73: =NI!B30 -> #NAME? | AM73: =VLOOKUP($AL73,NI!$B$5:$AL$2030,11,FALSE) -> #NAME? | AN73: =VLOOKUP($AL73,NI!$B$5:$AL$2030,12,FALSE)/1000000 -> #NAME? | AP73: =IF(ISNUMBER(VLOOKUP($AL73,NI!$B$5:$AL$2030,13,FALSE)),VLOOKUP($AL73,NI!$B$5:$AL$2030,13,FALSE),"-") -> - | AQ73: =VLOOKUP($AL73,NI!$B$5:$AL$2030,4,FALSE) -> #NAME? | AR73: =VLOOKUP($AL73,NI!$B$5:$AL$2030,3,FALSE) -> #NAME? | AS73: =VLOOKUP($AL73,NI!$B$5:$AL$2030,4,FALSE) -> #NAME? | AT73: =IF(LEFT(VLOOKUP($AL73,NI!$B$5:$AL$2030,31,FALSE),1)="#","-",VLOOKUP($AL73,NI!$B$5:$AL$2030,31,FALSE)) -> #NAME? | AU73: =IF(LEFT(VLOOKUP($AL73,NI!$B$5:$AL$2030,32,FALSE),1)="#","-",VLOOKUP($AL73,NI!$B$5:$AL$2030,32,FALSE)) -> #NAME? | AV73: =IF(LEFT(VLOOKUP($AL73,NI!$B$5:$AL$2030,33,FALSE),1)="#","-",VLOOKUP($AL73,NI!$B$5:$AL$2030,33,FALSE)) -> #NAME? | AW73: =VLOOKUP($AL73,NI!$B$5:$AL$2030,22,FALSE) -> #NAME?
C74: =Comment_page!$B14 -> 澳洲10Y公債 | E74: =Comment_page!$C14 -> #NAME? | F74: =Comment_page!D14 -> #NAME? | G74: =Comment_page!E14 -> #NAME? | H74: =Comment_page!F14 -> #NAME? | S74: 製藥 | T74: =VLOOKUP($AD74,'市場監控 '!$E$7:$W$194,6,FALSE) -> #NAME? | U74: =VLOOKUP($AD74,'市場監控 '!$E$7:$W$194,7,FALSE) -> #NAME? | V74: =VLOOKUP($AD74,'市場監控 '!$E$7:$W$194,8,FALSE) -> - | W74: =VLOOKUP($AD74,'市場監控 '!$E$7:$W$194,10,FALSE) -> - | X74: =VLOOKUP($AD74,'市場監控 '!$E$7:$W$194,12,FALSE) -> - | Y74: =VLOOKUP($AD74,'市場監控 '!$E$7:$W$194,14,FALSE) -> - | Z74: =VLOOKUP($AD74,'市場監控 '!$E$7:$W$194,15,FALSE) -> - | AA74: =VLOOKUP($AD74,'市場監控 '!$E$7:$W$194,17,FALSE) -> #NAME? | AB74: =VLOOKUP($AD74,'市場監控 '!$E$7:$W$194,18,FALSE) -> #NAME? | AC74: =VLOOKUP($AD74,'市場監控 '!$E$7:$W$194,19,FALSE) -> #NAME? | AD74: JNJ US Equity | AE74: 嬌生公司 | AJ74: =VLOOKUP($AL74,NI!$B$5:$AL$2030,6,FALSE) -> #NAME? | AK74: =VLOOKUP($AL74,NI!$B$5:$AL$2030,2,FALSE) -> #NAME? | AL74: =NI!B31 -> #NAME? | AM74: =VLOOKUP($AL74,NI!$B$5:$AL$2030,11,FALSE) -> #NAME? | AN74: =VLOOKUP($AL74,NI!$B$5:$AL$2030,12,FALSE)/1000000 -> #NAME? | AP74: =IF(ISNUMBER(VLOOKUP($AL74,NI!$B$5:$AL$2030,13,FALSE)),VLOOKUP($AL74,NI!$B$5:$AL$2030,13,FALSE),"-") -> - | AQ74: =VLOOKUP($AL74,NI!$B$5:$AL$2030,4,FALSE) -> #NAME? | AR74: =VLOOKUP($AL74,NI!$B$5:$AL$2030,3,FALSE) -> #NAME? | AS74: =VLOOKUP($AL74,NI!$B$5:$AL$2030,4,FALSE) -> #NAME? | AT74: =IF(LEFT(VLOOKUP($AL74,NI!$B$5:$AL$2030,31,FALSE),1)="#","-",VLOOKUP($AL74,NI!$B$5:$AL$2030,31,FALSE)) -> #NAME? | AU74: =IF(LEFT(VLOOKUP($AL74,NI!$B$5:$AL$2030,32,FALSE),1)="#","-",VLOOKUP($AL74,NI!$B$5:$AL$2030,32,FALSE)) -> #NAME? | AV74: =IF(LEFT(VLOOKUP($AL74,NI!$B$5:$AL$2030,33,FALSE),1)="#","-",VLOOKUP($AL74,NI!$B$5:$AL$2030,33,FALSE)) -> #NAME? | AW74: =VLOOKUP($AL74,NI!$B$5:$AL$2030,22,FALSE) -> #NAME?
C75: =Comment_page!$B15 -> 德國10Y公債 | E75: =Comment_page!$C15 -> #NAME? | F75: =Comment_page!D15 -> #NAME? | G75: =Comment_page!E15 -> #NAME? | H75: =Comment_page!F15 -> #NAME? | T75: =VLOOKUP($AD75,'市場監控 '!$E$7:$W$194,6,FALSE) -> #NAME? | U75: =VLOOKUP($AD75,'市場監控 '!$E$7:$W$194,7,FALSE) -> #NAME? | V75: =VLOOKUP($AD75,'市場監控 '!$E$7:$W$194,8,FALSE) -> - | W75: =VLOOKUP($AD75,'市場監控 '!$E$7:$W$194,10,FALSE) -> - | X75: =VLOOKUP($AD75,'市場監控 '!$E$7:$W$194,12,FALSE) -> - | Y75: =VLOOKUP($AD75,'市場監控 '!$E$7:$W$194,14,FALSE) -> - | Z75: =VLOOKUP($AD75,'市場監控 '!$E$7:$W$194,15,FALSE) -> - | AA75: =VLOOKUP($AD75,'市場監控 '!$E$7:$W$194,17,FALSE) -> #NAME? | AB75: =VLOOKUP($AD75,'市場監控 '!$E$7:$W$194,18,FALSE) -> #NAME? | AC75: =VLOOKUP($AD75,'市場監控 '!$E$7:$W$194,19,FALSE) -> #NAME? | AD75: novn sw Equity | AE75: 艾伯維公司 | AJ75: =VLOOKUP($AL75,NI!$B$5:$AL$2030,6,FALSE) -> #NAME? | AK75: =VLOOKUP($AL75,NI!$B$5:$AL$2030,2,FALSE) -> #NAME? | AL75: =NI!B32 -> #NAME? | AM75: =VLOOKUP($AL75,NI!$B$5:$AL$2030,11,FALSE) -> #NAME? | AN75: =VLOOKUP($AL75,NI!$B$5:$AL$2030,12,FALSE)/1000000 -> #NAME? | AP75: =IF(ISNUMBER(VLOOKUP($AL75,NI!$B$5:$AL$2030,13,FALSE)),VLOOKUP($AL75,NI!$B$5:$AL$2030,13,FALSE),"-") -> - | AQ75: =VLOOKUP($AL75,NI!$B$5:$AL$2030,4,FALSE) -> #NAME? | AR75: =VLOOKUP($AL75,NI!$B$5:$AL$2030,3,FALSE) -> #NAME? | AS75: =VLOOKUP($AL75,NI!$B$5:$AL$2030,4,FALSE) -> #NAME? | AT75: =IF(LEFT(VLOOKUP($AL75,NI!$B$5:$AL$2030,31,FALSE),1)="#","-",VLOOKUP($AL75,NI!$B$5:$AL$2030,31,FALSE)) -> #NAME? | AU75: =IF(LEFT(VLOOKUP($AL75,NI!$B$5:$AL$2030,32,FALSE),1)="#","-",VLOOKUP($AL75,NI!$B$5:$AL$2030,32,FALSE)) -> #NAME? | AV75: =IF(LEFT(VLOOKUP($AL75,NI!$B$5:$AL$2030,33,FALSE),1)="#","-",VLOOKUP($AL75,NI!$B$5:$AL$2030,33,FALSE)) -> #NAME? | AW75: =VLOOKUP($AL75,NI!$B$5:$AL$2030,22,FALSE) -> #NAME?
C76: =Comment_page!$B16 -> 英國10Y公債 | E76: =Comment_page!$C16 -> #NAME? | F76: =Comment_page!D16 -> #NAME? | G76: =Comment_page!E16 -> #NAME? | H76: =Comment_page!F16 -> #NAME? | T76: =VLOOKUP($AD76,'市場監控 '!$E$7:$W$194,6,FALSE) -> #NAME? | U76: =VLOOKUP($AD76,'市場監控 '!$E$7:$W$194,7,FALSE) -> #NAME? | V76: =VLOOKUP($AD76,'市場監控 '!$E$7:$W$194,8,FALSE) -> - | W76: =VLOOKUP($AD76,'市場監控 '!$E$7:$W$194,10,FALSE) -> - | X76: =VLOOKUP($AD76,'市場監控 '!$E$7:$W$194,12,FALSE) -> - | Y76: =VLOOKUP($AD76,'市場監控 '!$E$7:$W$194,14,FALSE) -> - | Z76: =VLOOKUP($AD76,'市場監控 '!$E$7:$W$194,15,FALSE) -> - | AA76: =VLOOKUP($AD76,'市場監控 '!$E$7:$W$194,17,FALSE) -> #NAME? | AB76: =VLOOKUP($AD76,'市場監控 '!$E$7:$W$194,18,FALSE) -> #NAME? | AC76: =VLOOKUP($AD76,'市場監控 '!$E$7:$W$194,19,FALSE) -> #NAME? | AD76: lly us Equity | AE76: 禮來公司 | AJ76: =VLOOKUP($AL76,NI!$B$5:$AL$2030,6,FALSE) -> #NAME? | AK76: =VLOOKUP($AL76,NI!$B$5:$AL$2030,2,FALSE) -> #NAME? | AL76: =NI!B33 -> #NAME? | AM76: =VLOOKUP($AL76,NI!$B$5:$AL$2030,11,FALSE) -> #NAME? | AN76: =VLOOKUP($AL76,NI!$B$5:$AL$2030,12,FALSE)/1000000 -> #NAME? | AP76: =IF(ISNUMBER(VLOOKUP($AL76,NI!$B$5:$AL$2030,13,FALSE)),VLOOKUP($AL76,NI!$B$5:$AL$2030,13,FALSE),"-") -> - | AQ76: =VLOOKUP($AL76,NI!$B$5:$AL$2030,4,FALSE) -> #NAME? | AR76: =VLOOKUP($AL76,NI!$B$5:$AL$2030,3,FALSE) -> #NAME? | AS76: =VLOOKUP($AL76,NI!$B$5:$AL$2030,4,FALSE) -> #NAME? | AT76: =IF(LEFT(VLOOKUP($AL76,NI!$B$5:$AL$2030,31,FALSE),1)="#","-",VLOOKUP($AL76,NI!$B$5:$AL$2030,31,FALSE)) -> #NAME? | AU76: =IF(LEFT(VLOOKUP($AL76,NI!$B$5:$AL$2030,32,FALSE),1)="#","-",VLOOKUP($AL76,NI!$B$5:$AL$2030,32,FALSE)) -> #NAME? | AV76: =IF(LEFT(VLOOKUP($AL76,NI!$B$5:$AL$2030,33,FALSE),1)="#","-",VLOOKUP($AL76,NI!$B$5:$AL$2030,33,FALSE)) -> #NAME? | AW76: =VLOOKUP($AL76,NI!$B$5:$AL$2030,22,FALSE) -> #NAME?
C77: =Comment_page!$B17 -> 法國10Y公債 | E77: =Comment_page!$C17 -> #NAME? | F77: =Comment_page!D17 -> #NAME? | G77: =Comment_page!E17 -> #NAME? | H77: =Comment_page!F17 -> #NAME? | T77: =VLOOKUP($AD77,'市場監控 '!$E$7:$W$194,6,FALSE) -> #NAME? | U77: =VLOOKUP($AD77,'市場監控 '!$E$7:$W$194,7,FALSE) -> #NAME? | V77: =VLOOKUP($AD77,'市場監控 '!$E$7:$W$194,8,FALSE) -> - | W77: =VLOOKUP($AD77,'市場監控 '!$E$7:$W$194,10,FALSE) -> - | X77: =VLOOKUP($AD77,'市場監控 '!$E$7:$W$194,12,FALSE) -> - | Y77: =VLOOKUP($AD77,'市場監控 '!$E$7:$W$194,14,FALSE) -> - | Z77: =VLOOKUP($AD77,'市場監控 '!$E$7:$W$194,15,FALSE) -> - | AA77: =VLOOKUP($AD77,'市場監控 '!$E$7:$W$194,17,FALSE) -> #NAME? | AB77: =VLOOKUP($AD77,'市場監控 '!$E$7:$W$194,18,FALSE) -> #NAME? | AC77: =VLOOKUP($AD77,'市場監控 '!$E$7:$W$194,19,FALSE) -> #NAME? | AD77: ABBV US Equity | AE77: 諾華公司 | AJ77: =VLOOKUP($AL77,NI!$B$5:$AL$2030,6,FALSE) -> #NAME? | AK77: =VLOOKUP($AL77,NI!$B$5:$AL$2030,2,FALSE) -> #NAME? | AL77: =NI!B34 -> #NAME? | AM77: =VLOOKUP($AL77,NI!$B$5:$AL$2030,11,FALSE) -> #NAME? | AN77: =VLOOKUP($AL77,NI!$B$5:$AL$2030,12,FALSE)/1000000 -> #NAME? | AP77: =IF(ISNUMBER(VLOOKUP($AL77,NI!$B$5:$AL$2030,13,FALSE)),VLOOKUP($AL77,NI!$B$5:$AL$2030,13,FALSE),"-") -> - | AQ77: =VLOOKUP($AL77,NI!$B$5:$AL$2030,4,FALSE) -> #NAME? | AR77: =VLOOKUP($AL77,NI!$B$5:$AL$2030,3,FALSE) -> #NAME? | AS77: =VLOOKUP($AL77,NI!$B$5:$AL$2030,4,FALSE) -> #NAME? | AT77: =IF(LEFT(VLOOKUP($AL77,NI!$B$5:$AL$2030,31,FALSE),1)="#","-",VLOOKUP($AL77,NI!$B$5:$AL$2030,31,FALSE)) -> #NAME? | AU77: =IF(LEFT(VLOOKUP($AL77,NI!$B$5:$AL$2030,32,FALSE),1)="#","-",VLOOKUP($AL77,NI!$B$5:$AL$2030,32,FALSE)) -> #NAME? | AV77: =IF(LEFT(VLOOKUP($AL77,NI!$B$5:$AL$2030,33,FALSE),1)="#","-",VLOOKUP($AL77,NI!$B$5:$AL$2030,33,FALSE)) -> #NAME? | AW77: =VLOOKUP($AL77,NI!$B$5:$AL$2030,22,FALSE) -> #NAME?
C78: =Comment_page!$B18 -> 義大利10Y公債 | E78: =Comment_page!$C18 -> #NAME? | F78: =Comment_page!D18 -> #NAME? | G78: =Comment_page!E18 -> #NAME? | H78: =Comment_page!F18 -> #NAME? | S78: 公用事業 | T78: =VLOOKUP($AD78,'市場監控 '!$E$7:$W$194,6,FALSE) -> #NAME? | U78: =VLOOKUP($AD78,'市場監控 '!$E$7:$W$194,7,FALSE) -> #NAME? | V78: =VLOOKUP($AD78,'市場監控 '!$E$7:$W$194,8,FALSE) -> - | W78: =VLOOKUP($AD78,'市場監控 '!$E$7:$W$194,10,FALSE) -> - | X78: =VLOOKUP($AD78,'市場監控 '!$E$7:$W$194,12,FALSE) -> - | Y78: =VLOOKUP($AD78,'市場監控 '!$E$7:$W$194,14,FALSE) -> - | Z78: =VLOOKUP($AD78,'市場監控 '!$E$7:$W$194,15,FALSE) -> - | AA78: =VLOOKUP($AD78,'市場監控 '!$E$7:$W$194,17,FALSE) -> #NAME? | AB78: =VLOOKUP($AD78,'市場監控 '!$E$7:$W$194,18,FALSE) -> #NAME? | AC78: =VLOOKUP($AD78,'市場監控 '!$E$7:$W$194,19,FALSE) -> #NAME? | AD78: EDF FP Equity | AE78: 法國電力有限責任公司 | AJ78: =VLOOKUP($AL78,NI!$B$5:$AL$2030,6,FALSE) -> #NAME? | AK78: =VLOOKUP($AL78,NI!$B$5:$AL$2030,2,FALSE) -> #NAME? | AL78: =NI!B35 -> #NAME? | AM78: =VLOOKUP($AL78,NI!$B$5:$AL$2030,11,FALSE) -> #NAME? | AN78: =VLOOKUP($AL78,NI!$B$5:$AL$2030,12,FALSE)/1000000 -> #NAME? | AP78: =IF(ISNUMBER(VLOOKUP($AL78,NI!$B$5:$AL$2030,13,FALSE)),VLOOKUP($AL78,NI!$B$5:$AL$2030,13,FALSE),"-") -> - | AQ78: =VLOOKUP($AL78,NI!$B$5:$AL$2030,4,FALSE) -> #NAME? | AR78: =VLOOKUP($AL78,NI!$B$5:$AL$2030,3,FALSE) -> #NAME? | AS78: =VLOOKUP($AL78,NI!$B$5:$AL$2030,4,FALSE) -> #NAME? | AT78: =IF(LEFT(VLOOKUP($AL78,NI!$B$5:$AL$2030,31,FALSE),1)="#","-",VLOOKUP($AL78,NI!$B$5:$AL$2030,31,FALSE)) -> #NAME? | AU78: =IF(LEFT(VLOOKUP($AL78,NI!$B$5:$AL$2030,32,FALSE),1)="#","-",VLOOKUP($AL78,NI!$B$5:$AL$2030,32,FALSE)) -> #NAME? | AV78: =IF(LEFT(VLOOKUP($AL78,NI!$B$5:$AL$2030,33,FALSE),1)="#","-",VLOOKUP($AL78,NI!$B$5:$AL$2030,33,FALSE)) -> #NAME? | AW78: =VLOOKUP($AL78,NI!$B$5:$AL$2030,22,FALSE) -> #NAME?
T79: =VLOOKUP($AD79,'市場監控 '!$E$7:$W$194,6,FALSE) -> #NAME? | U79: =VLOOKUP($AD79,'市場監控 '!$E$7:$W$194,7,FALSE) -> #NAME? | V79: =VLOOKUP($AD79,'市場監控 '!$E$7:$W$194,8,FALSE) -> - | W79: =VLOOKUP($AD79,'市場監控 '!$E$7:$W$194,10,FALSE) -> - | X79: =VLOOKUP($AD79,'市場監控 '!$E$7:$W$194,12,FALSE) -> - | Y79: =VLOOKUP($AD79,'市場監控 '!$E$7:$W$194,14,FALSE) -> - | Z79: =VLOOKUP($AD79,'市場監控 '!$E$7:$W$194,15,FALSE) -> - | AA79: =VLOOKUP($AD79,'市場監控 '!$E$7:$W$194,17,FALSE) -> #NAME? | AB79: =VLOOKUP($AD79,'市場監控 '!$E$7:$W$194,18,FALSE) -> #NAME? | AC79: =VLOOKUP($AD79,'市場監控 '!$E$7:$W$194,19,FALSE) -> #NAME? | AD79: enel im Equity | AE79: 聯邦電力委員會 | AJ79: =VLOOKUP($AL79,NI!$B$5:$AL$2030,6,FALSE) -> #NAME? | AK79: =VLOOKUP($AL79,NI!$B$5:$AL$2030,2,FALSE) -> #NAME? | AL79: =NI!B36 -> #NAME? | AM79: =VLOOKUP($AL79,NI!$B$5:$AL$2030,11,FALSE) -> #NAME? | AN79: =VLOOKUP($AL79,NI!$B$5:$AL$2030,12,FALSE)/1000000 -> #NAME? | AP79: =IF(ISNUMBER(VLOOKUP($AL79,NI!$B$5:$AL$2030,13,FALSE)),VLOOKUP($AL79,NI!$B$5:$AL$2030,13,FALSE),"-") -> - | AQ79: =VLOOKUP($AL79,NI!$B$5:$AL$2030,4,FALSE) -> #NAME? | AR79: =VLOOKUP($AL79,NI!$B$5:$AL$2030,3,FALSE) -> #NAME? | AS79: =VLOOKUP($AL79,NI!$B$5:$AL$2030,4,FALSE) -> #NAME? | AT79: =IF(LEFT(VLOOKUP($AL79,NI!$B$5:$AL$2030,31,FALSE),1)="#","-",VLOOKUP($AL79,NI!$B$5:$AL$2030,31,FALSE)) -> #NAME? | AU79: =IF(LEFT(VLOOKUP($AL79,NI!$B$5:$AL$2030,32,FALSE),1)="#","-",VLOOKUP($AL79,NI!$B$5:$AL$2030,32,FALSE)) -> #NAME? | AV79: =IF(LEFT(VLOOKUP($AL79,NI!$B$5:$AL$2030,33,FALSE),1)="#","-",VLOOKUP($AL79,NI!$B$5:$AL$2030,33,FALSE)) -> #NAME? | AW79: =VLOOKUP($AL79,NI!$B$5:$AL$2030,22,FALSE) -> #NAME?
T80: =VLOOKUP($AD80,'市場監控 '!$E$7:$W$194,6,FALSE) -> #NAME? | U80: =VLOOKUP($AD80,'市場監控 '!$E$7:$W$194,7,FALSE) -> #NAME? | V80: =VLOOKUP($AD80,'市場監控 '!$E$7:$W$194,8,FALSE) -> - | W80: =VLOOKUP($AD80,'市場監控 '!$E$7:$W$194,10,FALSE) -> - | X80: =VLOOKUP($AD80,'市場監控 '!$E$7:$W$194,12,FALSE) -> - | Y80: =VLOOKUP($AD80,'市場監控 '!$E$7:$W$194,14,FALSE) -> - | Z80: =VLOOKUP($AD80,'市場監控 '!$E$7:$W$194,15,FALSE) -> - | AA80: =VLOOKUP($AD80,'市場監控 '!$E$7:$W$194,17,FALSE) -> #NAME? | AB80: =VLOOKUP($AD80,'市場監控 '!$E$7:$W$194,18,FALSE) -> #NAME? | AC80: =VLOOKUP($AD80,'市場監控 '!$E$7:$W$194,19,FALSE) -> #NAME? | AD80: PLN IJ Equity | AE80: 義大利國家電力公司 | AJ80: =VLOOKUP($AL80,NI!$B$5:$AL$2030,6,FALSE) -> #NAME? | AK80: =VLOOKUP($AL80,NI!$B$5:$AL$2030,2,FALSE) -> #NAME? | AL80: =NI!B37 -> #NAME? | AM80: =VLOOKUP($AL80,NI!$B$5:$AL$2030,11,FALSE) -> #NAME? | AN80: =VLOOKUP($AL80,NI!$B$5:$AL$2030,12,FALSE)/1000000 -> #NAME? | AP80: =IF(ISNUMBER(VLOOKUP($AL80,NI!$B$5:$AL$2030,13,FALSE)),VLOOKUP($AL80,NI!$B$5:$AL$2030,13,FALSE),"-") -> - | AQ80: =VLOOKUP($AL80,NI!$B$5:$AL$2030,4,FALSE) -> #NAME? | AR80: =VLOOKUP($AL80,NI!$B$5:$AL$2030,3,FALSE) -> #NAME? | AS80: =VLOOKUP($AL80,NI!$B$5:$AL$2030,4,FALSE) -> #NAME? | AT80: =IF(LEFT(VLOOKUP($AL80,NI!$B$5:$AL$2030,31,FALSE),1)="#","-",VLOOKUP($AL80,NI!$B$5:$AL$2030,31,FALSE)) -> #NAME? | AU80: =IF(LEFT(VLOOKUP($AL80,NI!$B$5:$AL$2030,32,FALSE),1)="#","-",VLOOKUP($AL80,NI!$B$5:$AL$2030,32,FALSE)) -> #NAME? | AV80: =IF(LEFT(VLOOKUP($AL80,NI!$B$5:$AL$2030,33,FALSE),1)="#","-",VLOOKUP($AL80,NI!$B$5:$AL$2030,33,FALSE)) -> #NAME? | AW80: =VLOOKUP($AL80,NI!$B$5:$AL$2030,22,FALSE) -> #NAME?
T81: =VLOOKUP($AD81,'市場監控 '!$E$7:$W$194,6,FALSE) -> #NAME? | U81: =VLOOKUP($AD81,'市場監控 '!$E$7:$W$194,7,FALSE) -> #NAME? | V81: =VLOOKUP($AD81,'市場監控 '!$E$7:$W$194,8,FALSE) -> - | W81: =VLOOKUP($AD81,'市場監控 '!$E$7:$W$194,10,FALSE) -> - | X81: =VLOOKUP($AD81,'市場監控 '!$E$7:$W$194,12,FALSE) -> - | Y81: =VLOOKUP($AD81,'市場監控 '!$E$7:$W$194,14,FALSE) -> - | Z81: =VLOOKUP($AD81,'市場監控 '!$E$7:$W$194,15,FALSE) -> - | AA81: =VLOOKUP($AD81,'市場監控 '!$E$7:$W$194,17,FALSE) -> #NAME? | AB81: =VLOOKUP($AD81,'市場監控 '!$E$7:$W$194,18,FALSE) -> #NAME? | AC81: =VLOOKUP($AD81,'市場監控 '!$E$7:$W$194,19,FALSE) -> #NAME? | AD81: 1016Z MM Equity | AE81: 國家電力公司 | AJ81: =VLOOKUP($AL81,NI!$B$5:$AL$2030,6,FALSE) -> #NAME? | AK81: =VLOOKUP($AL81,NI!$B$5:$AL$2030,2,FALSE) -> #NAME? | AL81: =NI!B38 -> #NAME? | AM81: =VLOOKUP($AL81,NI!$B$5:$AL$2030,11,FALSE) -> #NAME? | AN81: =VLOOKUP($AL81,NI!$B$5:$AL$2030,12,FALSE)/1000000 -> #NAME? | AP81: =IF(ISNUMBER(VLOOKUP($AL81,NI!$B$5:$AL$2030,13,FALSE)),VLOOKUP($AL81,NI!$B$5:$AL$2030,13,FALSE),"-") -> - | AQ81: =VLOOKUP($AL81,NI!$B$5:$AL$2030,4,FALSE) -> #NAME? | AR81: =VLOOKUP($AL81,NI!$B$5:$AL$2030,3,FALSE) -> #NAME? | AS81: =VLOOKUP($AL81,NI!$B$5:$AL$2030,4,FALSE) -> #NAME? | AT81: =IF(LEFT(VLOOKUP($AL81,NI!$B$5:$AL$2030,31,FALSE),1)="#","-",VLOOKUP($AL81,NI!$B$5:$AL$2030,31,FALSE)) -> #NAME? | AU81: =IF(LEFT(VLOOKUP($AL81,NI!$B$5:$AL$2030,32,FALSE),1)="#","-",VLOOKUP($AL81,NI!$B$5:$AL$2030,32,FALSE)) -> #NAME? | AV81: =IF(LEFT(VLOOKUP($AL81,NI!$B$5:$AL$2030,33,FALSE),1)="#","-",VLOOKUP($AL81,NI!$B$5:$AL$2030,33,FALSE)) -> #NAME? | AW81: =VLOOKUP($AL81,NI!$B$5:$AL$2030,22,FALSE) -> #NAME? | BT81: 資料來源：Bloomberg
S82: 原物料 | T82: =VLOOKUP($AD82,'市場監控 '!$E$7:$W$194,6,FALSE) -> #NAME? | U82: =VLOOKUP($AD82,'市場監控 '!$E$7:$W$194,7,FALSE) -> #NAME? | V82: =VLOOKUP($AD82,'市場監控 '!$E$7:$W$194,8,FALSE) -> - | W82: =VLOOKUP($AD82,'市場監控 '!$E$7:$W$194,10,FALSE) -> - | X82: =VLOOKUP($AD82,'市場監控 '!$E$7:$W$194,12,FALSE) -> - | Y82: =VLOOKUP($AD82,'市場監控 '!$E$7:$W$194,14,FALSE) -> - | Z82: =VLOOKUP($AD82,'市場監控 '!$E$7:$W$194,15,FALSE) -> - | AA82: =VLOOKUP($AD82,'市場監控 '!$E$7:$W$194,17,FALSE) -> #NAME? | AB82: =VLOOKUP($AD82,'市場監控 '!$E$7:$W$194,18,FALSE) -> #NAME? | AC82: =VLOOKUP($AD82,'市場監控 '!$E$7:$W$194,19,FALSE) -> #NAME? | AD82: RIO ln Equity | AE82: 必和必拓集團有限公司
T83: =VLOOKUP($AD83,'市場監控 '!$E$7:$W$194,6,FALSE) -> #NAME? | U83: =VLOOKUP($AD83,'市場監控 '!$E$7:$W$194,7,FALSE) -> #NAME? | V83: =VLOOKUP($AD83,'市場監控 '!$E$7:$W$194,8,FALSE) -> - | W83: =VLOOKUP($AD83,'市場監控 '!$E$7:$W$194,10,FALSE) -> - | X83: =VLOOKUP($AD83,'市場監控 '!$E$7:$W$194,12,FALSE) -> - | Y83: =VLOOKUP($AD83,'市場監控 '!$E$7:$W$194,14,FALSE) -> - | Z83: =VLOOKUP($AD83,'市場監控 '!$E$7:$W$194,15,FALSE) -> - | AA83: =VLOOKUP($AD83,'市場監控 '!$E$7:$W$194,17,FALSE) -> #NAME? | AB83: =VLOOKUP($AD83,'市場監控 '!$E$7:$W$194,18,FALSE) -> #NAME? | AC83: =VLOOKUP($AD83,'市場監控 '!$E$7:$W$194,19,FALSE) -> #NAME? | AD83: BHP AU Equity | AE83: 智利國家銅業公司
T84: =VLOOKUP($AD84,'市場監控 '!$E$7:$W$194,6,FALSE) -> #NAME? | U84: =VLOOKUP($AD84,'市場監控 '!$E$7:$W$194,7,FALSE) -> #NAME? | V84: =VLOOKUP($AD84,'市場監控 '!$E$7:$W$194,8,FALSE) -> - | W84: =VLOOKUP($AD84,'市場監控 '!$E$7:$W$194,10,FALSE) -> - | X84: =VLOOKUP($AD84,'市場監控 '!$E$7:$W$194,12,FALSE) -> - | Y84: =VLOOKUP($AD84,'市場監控 '!$E$7:$W$194,14,FALSE) -> - | Z84: =VLOOKUP($AD84,'市場監控 '!$E$7:$W$194,15,FALSE) -> - | AA84: =VLOOKUP($AD84,'市場監控 '!$E$7:$W$194,17,FALSE) -> #NAME? | AB84: =VLOOKUP($AD84,'市場監控 '!$E$7:$W$194,18,FALSE) -> #NAME? | AC84: =VLOOKUP($AD84,'市場監控 '!$E$7:$W$194,19,FALSE) -> #NAME? | AD84: 1006z ci Equity | AE84: 力拓公開有限公司
S85: 媒體 | T85: =VLOOKUP($AD85,'市場監控 '!$E$7:$W$194,6,FALSE) -> #NAME? | U85: =VLOOKUP($AD85,'市場監控 '!$E$7:$W$194,7,FALSE) -> #NAME? | V85: =VLOOKUP($AD85,'市場監控 '!$E$7:$W$194,8,FALSE) -> - | W85: =VLOOKUP($AD85,'市場監控 '!$E$7:$W$194,10,FALSE) -> - | X85: =VLOOKUP($AD85,'市場監控 '!$E$7:$W$194,12,FALSE) -> - | Y85: =VLOOKUP($AD85,'市場監控 '!$E$7:$W$194,14,FALSE) -> - | Z85: =VLOOKUP($AD85,'市場監控 '!$E$7:$W$194,15,FALSE) -> - | AA85: =VLOOKUP($AD85,'市場監控 '!$E$7:$W$194,17,FALSE) -> #NAME? | AB85: =VLOOKUP($AD85,'市場監控 '!$E$7:$W$194,18,FALSE) -> #NAME? | AC85: =VLOOKUP($AD85,'市場監控 '!$E$7:$W$194,19,FALSE) -> #NAME? | AD85: NFLX US Equity | AE85: 網飛公司
C86: 股票市場 | J86: 外匯市場 | T86: =VLOOKUP($AD86,'市場監控 '!$E$7:$W$194,6,FALSE) -> #NAME? | U86: =VLOOKUP($AD86,'市場監控 '!$E$7:$W$194,7,FALSE) -> #NAME? | V86: =VLOOKUP($AD86,'市場監控 '!$E$7:$W$194,8,FALSE) -> - | W86: =VLOOKUP($AD86,'市場監控 '!$E$7:$W$194,10,FALSE) -> - | X86: =VLOOKUP($AD86,'市場監控 '!$E$7:$W$194,12,FALSE) -> - | Y86: =VLOOKUP($AD86,'市場監控 '!$E$7:$W$194,14,FALSE) -> - | Z86: =VLOOKUP($AD86,'市場監控 '!$E$7:$W$194,15,FALSE) -> - | AA86: =VLOOKUP($AD86,'市場監控 '!$E$7:$W$194,17,FALSE) -> #NAME? | AB86: =VLOOKUP($AD86,'市場監控 '!$E$7:$W$194,18,FALSE) -> #NAME? | AC86: =VLOOKUP($AD86,'市場監控 '!$E$7:$W$194,19,FALSE) -> #NAME? | AD86: DIS US Equity | AE86: 華特迪士尼公司
T87: =VLOOKUP($AD87,'市場監控 '!$E$7:$W$194,6,FALSE) -> #NAME? | U87: =VLOOKUP($AD87,'市場監控 '!$E$7:$W$194,7,FALSE) -> #NAME? | V87: =VLOOKUP($AD87,'市場監控 '!$E$7:$W$194,8,FALSE) -> - | W87: =VLOOKUP($AD87,'市場監控 '!$E$7:$W$194,10,FALSE) -> - | X87: =VLOOKUP($AD87,'市場監控 '!$E$7:$W$194,12,FALSE) -> - | Y87: =VLOOKUP($AD87,'市場監控 '!$E$7:$W$194,14,FALSE) -> - | Z87: =VLOOKUP($AD87,'市場監控 '!$E$7:$W$194,15,FALSE) -> - | AA87: =VLOOKUP($AD87,'市場監控 '!$E$7:$W$194,17,FALSE) -> #NAME? | AB87: =VLOOKUP($AD87,'市場監控 '!$E$7:$W$194,18,FALSE) -> #NAME? | AC87: =VLOOKUP($AD87,'市場監控 '!$E$7:$W$194,19,FALSE) -> #NAME? | AD87: 6758 JP Equity | AE87: 索尼
C88: 主要股票指數 | E88: 價格 | F88: 前週價格 | G88: 週變化 | H88: 週變化(%) | J88: 主要外匯 | L88: 價格 | M88: 前週價格 | N88: 週變化 | O88: 週變化(%) | T88: =VLOOKUP($AD88,'市場監控 '!$E$7:$W$194,6,FALSE) -> #NAME? | U88: =VLOOKUP($AD88,'市場監控 '!$E$7:$W$194,7,FALSE) -> #NAME? | V88: =VLOOKUP($AD88,'市場監控 '!$E$7:$W$194,8,FALSE) -> - | W88: =VLOOKUP($AD88,'市場監控 '!$E$7:$W$194,10,FALSE) -> - | X88: =VLOOKUP($AD88,'市場監控 '!$E$7:$W$194,12,FALSE) -> - | Y88: =VLOOKUP($AD88,'市場監控 '!$E$7:$W$194,14,FALSE) -> - | Z88: =VLOOKUP($AD88,'市場監控 '!$E$7:$W$194,15,FALSE) -> - | AA88: =VLOOKUP($AD88,'市場監控 '!$E$7:$W$194,17,FALSE) -> #NAME? | AB88: =VLOOKUP($AD88,'市場監控 '!$E$7:$W$194,18,FALSE) -> #NAME? | AC88: =VLOOKUP($AD88,'市場監控 '!$E$7:$W$194,19,FALSE) -> #NAME? | AD88: PARA US Equity | AE88: 派拉蒙全球
C89: =Comment_page!B20 -> 道瓊工業指數 | E89: =Comment_page!C20 -> #NAME? | F89: =Comment_page!D20 -> #NAME? | G89: =Comment_page!E20 -> #NAME? | H89: =Comment_page!F20 -> #NAME? | J89: =Comment_page!$B31 -> 美元指數 | L89: =Comment_page!$C31 -> #NAME? | M89: =Comment_page!$D31 -> #NAME? | N89: =Comment_page!E31 -> #NAME? | O89: =Comment_page!F31 -> #NAME? | S89: 航太 | T89: =VLOOKUP($AD89,'市場監控 '!$E$7:$W$194,6,FALSE) -> #NAME? | U89: =VLOOKUP($AD89,'市場監控 '!$E$7:$W$194,7,FALSE) -> #NAME? | V89: =VLOOKUP($AD89,'市場監控 '!$E$7:$W$194,8,FALSE) -> - | W89: =VLOOKUP($AD89,'市場監控 '!$E$7:$W$194,10,FALSE) -> - | X89: =VLOOKUP($AD89,'市場監控 '!$E$7:$W$194,12,FALSE) -> - | Y89: =VLOOKUP($AD89,'市場監控 '!$E$7:$W$194,14,FALSE) -> - | Z89: =VLOOKUP($AD89,'市場監控 '!$E$7:$W$194,15,FALSE) -> - | AA89: =VLOOKUP($AD89,'市場監控 '!$E$7:$W$194,17,FALSE) -> #NAME? | AB89: =VLOOKUP($AD89,'市場監控 '!$E$7:$W$194,18,FALSE) -> #NAME? | AC89: =VLOOKUP($AD89,'市場監控 '!$E$7:$W$194,19,FALSE) -> #NAME? | AD89: air fp equity | AE89: 空中巴士公司
C90: =Comment_page!B21 -> S&P 500指數 | E90: =Comment_page!C21 -> #NAME? | F90: =Comment_page!D21 -> #NAME? | G90: =Comment_page!E21 -> #NAME? | H90: =Comment_page!F21 -> #NAME? | J90: =Comment_page!$B32 -> USDTWD | L90: =Comment_page!$C32 -> #NAME? | M90: =Comment_page!$D32 -> #NAME? | N90: =Comment_page!E32 -> #NAME? | O90: =Comment_page!F32 -> #NAME? | T90: =VLOOKUP($AD90,'市場監控 '!$E$7:$W$194,6,FALSE) -> #NAME? | U90: =VLOOKUP($AD90,'市場監控 '!$E$7:$W$194,7,FALSE) -> #NAME? | V90: =VLOOKUP($AD90,'市場監控 '!$E$7:$W$194,8,FALSE) -> - | W90: =VLOOKUP($AD90,'市場監控 '!$E$7:$W$194,10,FALSE) -> - | X90: =VLOOKUP($AD90,'市場監控 '!$E$7:$W$194,12,FALSE) -> - | Y90: =VLOOKUP($AD90,'市場監控 '!$E$7:$W$194,14,FALSE) -> - | Z90: =VLOOKUP($AD90,'市場監控 '!$E$7:$W$194,15,FALSE) -> - | AA90: =VLOOKUP($AD90,'市場監控 '!$E$7:$W$194,17,FALSE) -> #NAME? | AB90: =VLOOKUP($AD90,'市場監控 '!$E$7:$W$194,18,FALSE) -> #NAME? | AC90: =VLOOKUP($AD90,'市場監控 '!$E$7:$W$194,19,FALSE) -> #NAME? | AD90: BA US Equity | AE90: 波音公司 | EX90: 資料來源：FDIC
C91: =Comment_page!B22 -> 那斯達克指數 | E91: =Comment_page!C22 -> #NAME? | F91: =Comment_page!D22 -> #NAME? | G91: =Comment_page!E22 -> #NAME? | H91: =Comment_page!F22 -> #NAME? | J91: =Comment_page!$B33 -> EURUSD | L91: =Comment_page!$C33 -> #NAME? | M91: =Comment_page!$D33 -> #NAME? | N91: =Comment_page!E33 -> #NAME? | O91: =Comment_page!F33 -> #NAME? | S91: 主權 | T91: =VLOOKUP($AD91,'市場監控 '!$E$7:$W$194,6,FALSE) -> #NAME? | U91: =VLOOKUP($AD91,'市場監控 '!$E$7:$W$194,7,FALSE) -> #NAME? | V91: =VLOOKUP($AD91,'市場監控 '!$E$7:$W$194,8,FALSE) -> - | W91: =VLOOKUP($AD91,'市場監控 '!$E$7:$W$194,10,FALSE) -> - | X91: =VLOOKUP($AD91,'市場監控 '!$E$7:$W$194,12,FALSE) -> - | Y91: =VLOOKUP($AD91,'市場監控 '!$E$7:$W$194,14,FALSE) -> - | Z91: =VLOOKUP($AD91,'市場監控 '!$E$7:$W$194,15,FALSE) -> - | AA91: =VLOOKUP($AD91,'市場監控 '!$E$7:$W$194,17,FALSE) -> #NAME? | AB91: =VLOOKUP($AD91,'市場監控 '!$E$7:$W$194,18,FALSE) -> #NAME? | AC91: =VLOOKUP($AD91,'市場監控 '!$E$7:$W$194,19,FALSE) -> #NAME? | AD91: 3344650Z QD Equity | AE91: 智利共和國
C92: =Comment_page!B23 -> 德國DAX指數 | E92: =Comment_page!C23 -> #NAME? | F92: =Comment_page!D23 -> #NAME? | G92: =Comment_page!E23 -> #NAME? | H92: =Comment_page!F23 -> #NAME? | J92: =Comment_page!$B34 -> GBPUSD | L92: =Comment_page!$C34 -> #NAME? | M92: =Comment_page!$D34 -> #NAME? | N92: =Comment_page!E34 -> #NAME? | O92: =Comment_page!F34 -> #NAME? | T92: =VLOOKUP($AD92,'市場監控 '!$E$7:$W$194,6,FALSE) -> #NAME? | U92: =VLOOKUP($AD92,'市場監控 '!$E$7:$W$194,7,FALSE) -> #NAME? | V92: =VLOOKUP($AD92,'市場監控 '!$E$7:$W$194,8,FALSE) -> - | W92: =VLOOKUP($AD92,'市場監控 '!$E$7:$W$194,10,FALSE) -> - | X92: =VLOOKUP($AD92,'市場監控 '!$E$7:$W$194,12,FALSE) -> - | Y92: =VLOOKUP($AD92,'市場監控 '!$E$7:$W$194,14,FALSE) -> - | Z92: =VLOOKUP($AD92,'市場監控 '!$E$7:$W$194,15,FALSE) -> - | AA92: =VLOOKUP($AD92,'市場監控 '!$E$7:$W$194,17,FALSE) -> #NAME? | AB92: =VLOOKUP($AD92,'市場監控 '!$E$7:$W$194,18,FALSE) -> #NAME? | AC92: =VLOOKUP($AD92,'市場監控 '!$E$7:$W$194,19,FALSE) -> #NAME? | AD92: 3344642Z AB Equity | AE92: 墨西哥合眾國
C93: =Comment_page!B24 -> 英國FTSE指數 | E93: =Comment_page!C24 -> #NAME? | F93: =Comment_page!D24 -> #NAME? | G93: =Comment_page!E24 -> #NAME? | H93: =Comment_page!F24 -> #NAME? | J93: =Comment_page!$B35 -> AUDUSD | L93: =Comment_page!$C35 -> #NAME? | M93: =Comment_page!$D35 -> #NAME? | N93: =Comment_page!E35 -> #NAME? | O93: =Comment_page!F35 -> #NAME? | T93: =VLOOKUP($AD93,'市場監控 '!$E$7:$W$194,6,FALSE) -> #NAME? | U93: =VLOOKUP($AD93,'市場監控 '!$E$7:$W$194,7,FALSE) -> #NAME? | V93: =VLOOKUP($AD93,'市場監控 '!$E$7:$W$194,8,FALSE) -> - | W93: =VLOOKUP($AD93,'市場監控 '!$E$7:$W$194,10,FALSE) -> - | X93: =VLOOKUP($AD93,'市場監控 '!$E$7:$W$194,12,FALSE) -> - | Y93: =VLOOKUP($AD93,'市場監控 '!$E$7:$W$194,14,FALSE) -> - | Z93: =VLOOKUP($AD93,'市場監控 '!$E$7:$W$194,15,FALSE) -> - | AA93: =VLOOKUP($AD93,'市場監控 '!$E$7:$W$194,17,FALSE) -> #NAME? | AB93: =VLOOKUP($AD93,'市場監控 '!$E$7:$W$194,18,FALSE) -> #NAME? | AC93: =VLOOKUP($AD93,'市場監控 '!$E$7:$W$194,19,FALSE) -> #NAME? | AD93: 45793z ci Equity | AE93: 南非共和國
C94: =Comment_page!B25 -> 法國CAC指數 | E94: =Comment_page!C25 -> #NAME? | F94: =Comment_page!D25 -> #NAME? | G94: =Comment_page!E25 -> #NAME? | H94: =Comment_page!F25 -> #NAME? | J94: =Comment_page!$B36 -> USDJPY | L94: =Comment_page!$C36 -> #NAME? | M94: =Comment_page!$D36 -> #NAME? | N94: =Comment_page!E36 -> #NAME? | O94: =Comment_page!F36 -> #NAME? | T94: =VLOOKUP($AD94,'市場監控 '!$E$7:$W$194,6,FALSE) -> #NAME? | U94: =VLOOKUP($AD94,'市場監控 '!$E$7:$W$194,7,FALSE) -> #NAME? | V94: =VLOOKUP($AD94,'市場監控 '!$E$7:$W$194,8,FALSE) -> - | W94: =VLOOKUP($AD94,'市場監控 '!$E$7:$W$194,10,FALSE) -> - | X94: =VLOOKUP($AD94,'市場監控 '!$E$7:$W$194,12,FALSE) -> - | Y94: =VLOOKUP($AD94,'市場監控 '!$E$7:$W$194,14,FALSE) -> - | Z94: =VLOOKUP($AD94,'市場監控 '!$E$7:$W$194,15,FALSE) -> - | AA94: =VLOOKUP($AD94,'市場監控 '!$E$7:$W$194,17,FALSE) -> #NAME? | AB94: =VLOOKUP($AD94,'市場監控 '!$E$7:$W$194,18,FALSE) -> #NAME? | AC94: =VLOOKUP($AD94,'市場監控 '!$E$7:$W$194,19,FALSE) -> #NAME? | AD94: 1426Z MM Equity | AE94: 印尼共和國
C95: =Comment_page!B26 -> 台灣加權指數 | E95: =Comment_page!C26 -> #NAME? | F95: =Comment_page!D26 -> #NAME? | G95: =Comment_page!E26 -> #NAME? | H95: =Comment_page!F26 -> #NAME? | J95: =Comment_page!$B37 -> USDCNY | L95: =Comment_page!$C37 -> #NAME? | M95: =Comment_page!$D37 -> #NAME? | N95: =Comment_page!E37 -> #NAME? | O95: =Comment_page!F37 -> #NAME? | T95: =VLOOKUP($AD95,'市場監控 '!$E$7:$W$194,6,FALSE) -> #NAME? | U95: =VLOOKUP($AD95,'市場監控 '!$E$7:$W$194,7,FALSE) -> #NAME? | V95: =VLOOKUP($AD95,'市場監控 '!$E$7:$W$194,8,FALSE) -> - | W95: =VLOOKUP($AD95,'市場監控 '!$E$7:$W$194,10,FALSE) -> - | X95: =VLOOKUP($AD95,'市場監控 '!$E$7:$W$194,12,FALSE) -> - | Y95: =VLOOKUP($AD95,'市場監控 '!$E$7:$W$194,14,FALSE) -> - | Z95: =VLOOKUP($AD95,'市場監控 '!$E$7:$W$194,15,FALSE) -> - | AA95: =VLOOKUP($AD95,'市場監控 '!$E$7:$W$194,17,FALSE) -> #NAME? | AB95: =VLOOKUP($AD95,'市場監控 '!$E$7:$W$194,18,FALSE) -> #NAME? | AC95: =VLOOKUP($AD95,'市場監控 '!$E$7:$W$194,19,FALSE) -> #NAME? | AD95: 1133Z IJ Equity | AE95: 沙烏地阿拉伯王國
C96: =Comment_page!B27 -> 日經225指數 | E96: =Comment_page!C27 -> #NAME? | F96: =Comment_page!D27 -> #NAME? | G96: =Comment_page!E27 -> #NAME? | H96: =Comment_page!F27 -> #NAME? | T96: =VLOOKUP($AD96,'市場監控 '!$E$7:$W$194,6,FALSE) -> #NAME? | U96: =VLOOKUP($AD96,'市場監控 '!$E$7:$W$194,7,FALSE) -> #NAME? | V96: =VLOOKUP($AD96,'市場監控 '!$E$7:$W$194,8,FALSE) -> - | W96: =VLOOKUP($AD96,'市場監控 '!$E$7:$W$194,10,FALSE) -> - | X96: =VLOOKUP($AD96,'市場監控 '!$E$7:$W$194,12,FALSE) -> - | Y96: =VLOOKUP($AD96,'市場監控 '!$E$7:$W$194,14,FALSE) -> - | Z96: =VLOOKUP($AD96,'市場監控 '!$E$7:$W$194,15,FALSE) -> - | AA96: =VLOOKUP($AD96,'市場監控 '!$E$7:$W$194,17,FALSE) -> #NAME? | AB96: =VLOOKUP($AD96,'市場監控 '!$E$7:$W$194,18,FALSE) -> #NAME? | AC96: =VLOOKUP($AD96,'市場監控 '!$E$7:$W$194,19,FALSE) -> #NAME? | AD96: 50184Z SJ Equity | AE96: 卡達
C97: =Comment_page!B28 -> 恆生指數 | E97: =Comment_page!C28 -> #NAME? | F97: =Comment_page!D28 -> #NAME? | G97: =Comment_page!E28 -> #NAME? | H97: =Comment_page!F28 -> #NAME?
C98: =Comment_page!B29 -> 上證綜合指數 | E98: =Comment_page!C29 -> #NAME? | F98: =Comment_page!D29 -> #NAME? | G98: =Comment_page!E29 -> #NAME? | H98: =Comment_page!F29 -> #NAME?

Sheet 市場監控 
E1: =TODAY() -> 46241 | F1: =WORKDAY(E1,-3) -> 46238 | V1: RTG_MDY_SEN_UNSECURED_DEBT
E2: =TODAY()-1 -> 46240 | V2: RTG_MOODY_LONG_TERM | X2: RTG_SP_OUTLOOK | AX2: RTG_moody_long_term_date
F3: CDS_SPREAD_TICKER_5Y | J3: SECURITY_NAME | K3: NAME_CHINESE_TRADITIONAL | L3: PX_LAST | M3: CHG_PCT_1D | N3: CHG_PCT_5D | O3: CHG_PCT_YTD | P3: PX_Last | Q3: CHG_NET_1D | R3: CHG_NET_5D | S3: CHG_NET_YTD | U3: RTG_SP_LT_FC_ISSUER_Credit | V3: RTG_MDY_ISSUER | W3: RTG_FITCH_LT_ISSUER_DEFAULT | X3: RTG_SP_OUTLOOK | Y3: RTG_MDY_OUTLOOK | Z3: RTG_Fitch_Outlook | AT3: issuer | AU3: issuer | AV3: issuer | AX3: rtg_mdy_issuer_rtg_dt
I4: =TODAY() -> 46241 | T4: {=(_xll.BDP("US0003M Index","PX_LAST")+110/10000*100)%} -> #NAME? | AO4: mkt cap | AR4: mkt $ bn | AT4: S&P | AU4: Moody's | AV4: FITCH
G5: mkt cap US bn | I5: 產業 | J5: 公司名稱 | K5: 中文名稱 | L5: 股價/匯率觀察 | P5: CDS警示 | T5: 信評警示 | X5: Outlook | AH5: Rating Checking | AK5: Outlook Checking | AN5: 評等改變 | AT5: 評等改變 | AU5: 評等改變 | AV5: 評等改變 | AW5: S&P | AX5: Moody's | AY5: FITCH
L6: 最新股價 | M6: previous 1w | N6: 1W %△ | O6: YTD %△ | P6: 最新CDS | Q6: previous 1w | R6: 1W △ | S6: YTD △ | T6: 變動? | U6: S&P | V6: Moody's | W6: Fitch | X6: S&P | Y6: Moody's | Z6: Fitch | AB6: S&P | AC6: Moody's | AD6: Fitch | AE6: S&P | AF6: Moody's | AG6: Fitch | AH6: S&P | AI6: Moody's | AJ6: Fitch | AK6: S&P | AL6: Moody's | AM6: Fitch | AN6: Y? | AT6: =SUM(AT7:AT195) -> 0 | AU6: =SUM(AU7:AU195) -> 0 | AV6: =SUM(AV7:AV195) -> 0 | AW6: RTG_SP_LT_LC_ISS_cred_rtg_dt | AY6: RTG_FITCH_LT_issuer_dflt_rtg_dt | AZ6: 上周五收盤 | BA6: 上上周五收盤 | BB6: 一周變化
E7: 1301 TT Equity | F7: =_xll.BDP($E7,F$3)&" BEST Curncy" -> #NAME? | G7: =AR7 -> #NAME? | I7: 原物料 | J7: =_xll.BDP($E7,J$3) -> #NAME? | K7: =_xll.BDP($E7,K$3) -> #NAME? | L7: =IF(ISNUMBER(_xll.BDH($E7,"PX_LAST",TEXT($E$2,"YYYYMMDD"),TEXT($E$2,"YYYYMMDD"),"days=a","fill=p")),_xll.BDH($E7,"PX_LAST",TEXT($E$2,"YYYYMMDD"),TEXT($E$2,"YYYYMMDD"),"days=a","fill=p"),"-") -> - | M7: =IF(ISNUMBER(_xll.BDH($E7,"PX_LAST",TEXT($E$2-7,"YYYYMMDD"),TEXT($E$2-7,"YYYYMMDD"),"days=a","fill=p")),_xll.BDH($E7,"PX_LAST",TEXT($E$2-7,"YYYYMMDD"),TEXT($E$2-7,"YYYYMMDD"),"days=a","fill=p"),"-") -> - | N7: =IF(ISNUMBER(($L7-$M7)/$M7),($L7-$M7)/$M7,"-") -> - | O7: =IF(OR(_xll.BDP($E7,O$3)="#N/A N/A",_xll.BDP($E7,O$3)="#N/A Invalid Security"), "-", _xll.BDP($E7,O$3)) -> #NAME? | P7: =IF(ISNUMBER(_xll.BDH($F7,"PX_LAST",TEXT($E$2,"YYYYMMDD"),TEXT($E$2,"YYYYMMDD"),"days=a","fill=p")),_xll.BDH($F7,"PX_LAST",TEXT($E$2,"YYYYMMDD"),TEXT($E$2,"YYYYMMDD"),"days=a","fill=p"),"-") -> - | Q7: =IF(ISNUMBER(_xll.BDH($F7,"PX_LAST",TEXT($E$2-7,"YYYYMMDD"),TEXT($E$2-7,"YYYYMMDD"),"days=a","fill=p")),_xll.BDH($F7,"PX_LAST",TEXT($E$2-7,"YYYYMMDD"),TEXT($E$2-7,"YYYYMMDD"),"days=a","fill=p"),"-") -> - | R7: =IF(ISNUMBER($P7-$Q7),$P7-$Q7,"-") -> - | S7: =IF(ISNUMBER(_xll.BDP($F7,S$3)),_xll.BDP($F7,S$3),"-") -> - | T7: =IF(OR(AH7>0, AI7>0, AJ7>0, AK7>0, AL7>0, AM7>0), "Y"," ") -> #NAME? | U7: =IF(OR(_xll.BDP($E7,U$3)="#N/A N/A",_xll.BDP($E7,U$3)="#N/A Invalid Security"), "-", _xll.BDP($E7,U$3)) -> #NAME? | V7: =IF(OR(_xll.BDP($E7,V$2)="#N/A N/A",_xll.BDP($E7,V$2)="#N/A Invalid Security"), "-", _xll.BDP($E7,V$2)) -> #NAME? | W7: =IF(OR(_xll.BDP($E7,W$3)="#N/A N/A",_xll.BDP($E7,W$3)="#N/A Invalid Security"), "-", _xll.BDP($E7,W$3)) -> #NAME? | X7: =IF(OR(_xll.BDP($E7,X$3)="#N/A N/A",_xll.BDP($E7,X$3)="#N/A Invalid Security"), " ", _xll.BDP($E7,X$3)) -> #NAME? | Y7: =IF(OR(_xll.BDP($E7,Y$3)="#N/A N/A",_xll.BDP($E7,Y$3)="#N/A Invalid Security"), " ", _xll.BDP($E7,Y$3)) -> #NAME? | Z7: =IF(OR(_xll.BDP($E7,Z$3)="#N/A N/A",_xll.BDP($E7,Z$3)="#N/A Invalid Security"), " ", _xll.BDP($E7,Z$3)) -> #NAME? | AB7: BBB | AC7: Baa1 | AD7: - | AE7: NEG | AF7: NEG | AH7: =IF(U7=AB7, 0,1) -> #NAME? | AI7: =IF(V7=AC7, 0,1) -> #NAME? | AJ7: =IF(W7=AD7, 0,1) -> #NAME? | AK7: =IF(X7=AE7, 0,1) -> #NAME? | AL7: =IF(Y7=AF7, 0,1) -> #NAME? | AM7: =IF(Z7=AG7, 0,1) -> #NAME? | AN7: =IF(SUM(AT7:AV7)>0,"Y","") | AO7: {=_xll.BDP($E7,"cur_mkt_cap")} -> #NAME? | AP7: {=_xll.BDP($E7,"crncy")} -> #NAME? | AQ7: {=_xll.BDP("USD"&AP7&" curncy","px_last")} -> #NAME? | AR7: =AO7/AQ7/1000000000 -> #NAME? | AT7: =IF(AND(AW7<=$E$1,AW7>=$F$1),1,"") | AU7: =IF(AND(AX7<=$E$1,AX7>=$F$1),1,"") | AV7: =IF(AND(AY7<=$E$1,AY7>=$F$1),1,"") | AW7: {=IF(ISERROR(DATEVALUE(_xll.BDP($E7,AW$6))),"",DATEVALUE(_xll.BDP($E7,AW$6)))} | AX7: {=IF(ISERROR(DATEVALUE(_xll.BDP($E7,AX$2))),"",DATEVALUE(_xll.BDP($E7,AX$2)))} | AY7: {=IF(ISERROR(DATEVALUE(_xll.BDP($E7,AY$6))),"",DATEVALUE(_xll.BDP($E7,AY$6)))} | AZ7: {=IF(_xll.BQL($E7, "last(matches(px_last(dates=range(-1w,0d)), dayofweek(px_last(dates=range(-1w,0d)).date)==6))")="#N/A","-",_xll.BQL($E7, "last(matches(px_last(dates=range(-1w,0d)), dayofweek(px_last(dates=range(-1w,0d)).date)==6))"))} -> #NAME? | BA7: {=IF(_xll.BQL(E7,"first(last(matches(px_last(dates=range(-1M,0D)),dayofweek(px_last(dates=range(-1M,0D)).date)==6),2),1)")="#N/A","-",_xll.BQL(E7,"first(last(matches(px_last(dates=range(-1M,0D)),dayofweek(px_last(dates=range(-1M,0D)).date)==6),2),1)"))} -> #NAME? | BB7: =IF(ISERROR((AZ7/BA7-1)*100),"-",(AZ7/BA7-1)*100) -> -
E8: BHP AU Equity | F8: =_xll.BDP($E8,F$3)&" BEST Curncy" -> #NAME? | G8: =AR8 -> #NAME? | J8: =_xll.BDP($E8,J$3) -> #NAME? | K8: =_xll.BDP($E8,K$3) -> #NAME? | L8: =IF(ISNUMBER(_xll.BDH($E8,"PX_LAST",TEXT($E$2,"YYYYMMDD"),TEXT($E$2,"YYYYMMDD"),"days=a","fill=p")),_xll.BDH($E8,"PX_LAST",TEXT($E$2,"YYYYMMDD"),TEXT($E$2,"YYYYMMDD"),"days=a","fill=p"),"-") -> - | M8: =IF(ISNUMBER(_xll.BDH($E8,"PX_LAST",TEXT($E$2-7,"YYYYMMDD"),TEXT($E$2-7,"YYYYMMDD"),"days=a","fill=p")),_xll.BDH($E8,"PX_LAST",TEXT($E$2-7,"YYYYMMDD"),TEXT($E$2-7,"YYYYMMDD"),"days=a","fill=p"),"-") -> - | N8: =IF(ISNUMBER(($L8-$M8)/$M8),($L8-$M8)/$M8,"-") -> - | O8: =IF(OR(_xll.BDP($E8,O$3)="#N/A N/A",_xll.BDP($E8,O$3)="#N/A Invalid Security"), "-", _xll.BDP($E8,O$3)) -> #NAME? | P8: =IF(ISNUMBER(_xll.BDH($F8,"PX_LAST",TEXT($E$2,"YYYYMMDD"),TEXT($E$2,"YYYYMMDD"),"days=a","fill=p")),_xll.BDH($F8,"PX_LAST",TEXT($E$2,"YYYYMMDD"),TEXT($E$2,"YYYYMMDD"),"days=a","fill=p"),"-") -> - | Q8: =IF(ISNUMBER(_xll.BDH($F8,"PX_LAST",TEXT($E$2-7,"YYYYMMDD"),TEXT($E$2-7,"YYYYMMDD"),"days=a","fill=p")),_xll.BDH($F8,"PX_LAST",TEXT($E$2-7,"YYYYMMDD"),TEXT($E$2-7,"YYYYMMDD"),"days=a","fill=p"),"-") -> - | R8: =IF(ISNUMBER($P8-$Q8),$P8-$Q8,"-") -> - | S8: =IF(ISNUMBER(_xll.BDP($F8,S$3)),_xll.BDP($F8,S$3),"-") -> - | T8: =IF(OR(AH8>0, AI8>0, AJ8>0, AK8>0, AL8>0, AM8>0), "Y"," ") -> #NAME? | U8: =IF(OR(_xll.BDP($E8,U$3)="#N/A N/A",_xll.BDP($E8,U$3)="#N/A Invalid Security"), "-", _xll.BDP($E8,U$3)) -> #NAME? | V8: =IF(OR(_xll.BDP($E8,V$2)="#N/A N/A",_xll.BDP($E8,V$2)="#N/A Invalid Security"), "-", _xll.BDP($E8,V$2)) -> #NAME? | W8: =IF(OR(_xll.BDP($E8,W$3)="#N/A N/A",_xll.BDP($E8,W$3)="#N/A Invalid Security"), "-", _xll.BDP($E8,W$3)) -> #NAME? | X8: =IF(OR(_xll.BDP($E8,X$3)="#N/A N/A",_xll.BDP($E8,X$3)="#N/A Invalid Security"), " ", _xll.BDP($E8,X$3)) -> #NAME? | Y8: =IF(OR(_xll.BDP($E8,Y$3)="#N/A N/A",_xll.BDP($E8,Y$3)="#N/A Invalid Security"), " ", _xll.BDP($E8,Y$3)) -> #NAME? | Z8: =IF(OR(_xll.BDP($E8,Z$3)="#N/A N/A",_xll.BDP($E8,Z$3)="#N/A Invalid Security"), " ", _xll.BDP($E8,Z$3)) -> #NAME? | AB8: A- | AC8: A1 | AD8: A | AE8: STABLE | AF8: STABLE | AG8: STABLE | AH8: =IF(U8=AB8, 0,1) -> #NAME? | AI8: =IF(V8=AC8, 0,1) -> #NAME? | AJ8: =IF(W8=AD8, 0,1) -> #NAME? | AK8: =IF(X8=AE8, 0,1) -> #NAME? | AL8: =IF(Y8=AF8, 0,1) -> #NAME? | AM8: =IF(Z8=AG8, 0,1) -> #NAME? | AN8: =IF(SUM(AT8:AV8)>0,"Y","") | AO8: {=_xll.BDP($E8,"cur_mkt_cap")} -> #NAME? | AP8: {=_xll.BDP($E8,"crncy")} -> #NAME? | AQ8: {=_xll.BDP("USD"&AP8&" curncy","px_last")} -> #NAME? | AR8: =AO8/AQ8/1000000000 -> #NAME? | AT8: =IF(AND(AW8<=$E$1,AW8>=$F$1),1,"") | AU8: =IF(AND(AX8<=$E$1,AX8>=$F$1),1,"") | AV8: =IF(AND(AY8<=$E$1,AY8>=$F$1),1,"") | AW8: {=IF(ISERROR(DATEVALUE(_xll.BDP($E8,AW$6))),"",DATEVALUE(_xll.BDP($E8,AW$6)))} | AX8: {=IF(ISERROR(DATEVALUE(_xll.BDP($E8,AX$2))),"",DATEVALUE(_xll.BDP($E8,AX$2)))} | AY8: {=IF(ISERROR(DATEVALUE(_xll.BDP($E8,AY$6))),"",DATEVALUE(_xll.BDP($E8,AY$6)))} | AZ8: {=IF(_xll.BQL($E8, "last(matches(px_last(dates=range(-1w,0d)), dayofweek(px_last(dates=range(-1w,0d)).date)==6))")="#N/A","-",_xll.BQL($E8, "last(matches(px_last(dates=range(-1w,0d)), dayofweek(px_last(dates=range(-1w,0d)).date)==6))"))} -> #NAME? | BA8: {=IF(_xll.BQL(E8,"first(last(matches(px_last(dates=range(-1M,0D)),dayofweek(px_last(dates=range(-1M,0D)).date)==6),2),1)")="#N/A","-",_xll.BQL(E8,"first(last(matches(px_last(dates=range(-1M,0D)),dayofweek(px_last(dates=range(-1M,0D)).date)==6),2),1)"))} -> #NAME? | BB8: =IF(ISERROR((AZ8/BA8-1)*100),"-",(AZ8/BA8-1)*100) -> -
E9: BAS gr Equity | F9: =_xll.BDP($E9,F$3)&" BEST Curncy" -> #NAME? | G9: =AR9 -> #NAME? | J9: =_xll.BDP($E9,J$3) -> #NAME? | K9: =_xll.BDP($E9,K$3) -> #NAME? | L9: =IF(ISNUMBER(_xll.BDH($E9,"PX_LAST",TEXT($E$2,"YYYYMMDD"),TEXT($E$2,"YYYYMMDD"),"days=a","fill=p")),_xll.BDH($E9,"PX_LAST",TEXT($E$2,"YYYYMMDD"),TEXT($E$2,"YYYYMMDD"),"days=a","fill=p"),"-") -> - | M9: =IF(ISNUMBER(_xll.BDH($E9,"PX_LAST",TEXT($E$2-7,"YYYYMMDD"),TEXT($E$2-7,"YYYYMMDD"),"days=a","fill=p")),_xll.BDH($E9,"PX_LAST",TEXT($E$2-7,"YYYYMMDD"),TEXT($E$2-7,"YYYYMMDD"),"days=a","fill=p"),"-") -> - | N9: =IF(ISNUMBER(($L9-$M9)/$M9),($L9-$M9)/$M9,"-") -> - | O9: =IF(OR(_xll.BDP($E9,O$3)="#N/A N/A",_xll.BDP($E9,O$3)="#N/A Invalid Security"), "-", _xll.BDP($E9,O$3)) -> #NAME? | P9: =IF(ISNUMBER(_xll.BDH($F9,"PX_LAST",TEXT($E$2,"YYYYMMDD"),TEXT($E$2,"YYYYMMDD"),"days=a","fill=p")),_xll.BDH($F9,"PX_LAST",TEXT($E$2,"YYYYMMDD"),TEXT($E$2,"YYYYMMDD"),"days=a","fill=p"),"-") -> - | Q9: =IF(ISNUMBER(_xll.BDH($F9,"PX_LAST",TEXT($E$2-7,"YYYYMMDD"),TEXT($E$2-7,"YYYYMMDD"),"days=a","fill=p")),_xll.BDH($F9,"PX_LAST",TEXT($E$2-7,"YYYYMMDD"),TEXT($E$2-7,"YYYYMMDD"),"days=a","fill=p"),"-") -> - | R9: =IF(ISNUMBER($P9-$Q9),$P9-$Q9,"-") -> - | S9: =IF(ISNUMBER(_xll.BDP($F9,S$3)),_xll.BDP($F9,S$3),"-") -> - | T9: =IF(OR(AH9>0, AI9>0, AJ9>0, AK9>0, AL9>0, AM9>0), "Y"," ") -> #NAME? | U9: =IF(OR(_xll.BDP($E9,U$3)="#N/A N/A",_xll.BDP($E9,U$3)="#N/A Invalid Security"), "-", _xll.BDP($E9,U$3)) -> #NAME? | V9: =IF(OR(_xll.BDP($E9,V$2)="#N/A N/A",_xll.BDP($E9,V$2)="#N/A Invalid Security"), "-", _xll.BDP($E9,V$2)) -> #NAME? | W9: =IF(OR(_xll.BDP($E9,W$3)="#N/A N/A",_xll.BDP($E9,W$3)="#N/A Invalid Security"), "-", _xll.BDP($E9,W$3)) -> #NAME? | X9: =IF(OR(_xll.BDP($E9,X$3)="#N/A N/A",_xll.BDP($E9,X$3)="#N/A Invalid Security"), " ", _xll.BDP($E9,X$3)) -> #NAME? | Y9: =IF(OR(_xll.BDP($E9,Y$3)="#N/A N/A",_xll.BDP($E9,Y$3)="#N/A Invalid Security"), " ", _xll.BDP($E9,Y$3)) -> #NAME? | Z9: =IF(OR(_xll.BDP($E9,Z$3)="#N/A N/A",_xll.BDP($E9,Z$3)="#N/A Invalid Security"), " ", _xll.BDP($E9,Z$3)) -> #NAME? | AB9: A- | AC9: A3 | AD9: A | AE9: STABLE | AF9: STABLE | AG9: STABLE | AH9: =IF(U9=AB9, 0,1) -> #NAME? | AI9: =IF(V9=AC9, 0,1) -> #NAME? | AJ9: =IF(W9=AD9, 0,1) -> #NAME? | AK9: =IF(X9=AE9, 0,1) -> #NAME? | AL9: =IF(Y9=AF9, 0,1) -> #NAME? | AM9: =IF(Z9=AG9, 0,1) -> #NAME? | AN9: =IF(SUM(AT9:AV9)>0,"Y","") | AO9: {=_xll.BDP($E9,"cur_mkt_cap")} -> #NAME? | AP9: {=_xll.BDP($E9,"crncy")} -> #NAME? | AQ9: {=_xll.BDP("USD"&AP9&" curncy","px_last")} -> #NAME? | AR9: =AO9/AQ9/1000000000 -> #NAME? | AT9: =IF(AND(AW9<=$E$1,AW9>=$F$1),1,"") | AU9: =IF(AND(AX9<=$E$1,AX9>=$F$1),1,"") | AV9: =IF(AND(AY9<=$E$1,AY9>=$F$1),1,"") | AW9: {=IF(ISERROR(DATEVALUE(_xll.BDP($E9,AW$6))),"",DATEVALUE(_xll.BDP($E9,AW$6)))} | AX9: {=IF(ISERROR(DATEVALUE(_xll.BDP($E9,AX$2))),"",DATEVALUE(_xll.BDP($E9,AX$2)))} | AY9: {=IF(ISERROR(DATEVALUE(_xll.BDP($E9,AY$6))),"",DATEVALUE(_xll.BDP($E9,AY$6)))} | AZ9: {=IF(_xll.BQL($E9, "last(matches(px_last(dates=range(-1w,0d)), dayofweek(px_last(dates=range(-1w,0d)).date)==6))")="#N/A","-",_xll.BQL($E9, "last(matches(px_last(dates=range(-1w,0d)), dayofweek(px_last(dates=range(-1w,0d)).date)==6))"))} -> #NAME? | BA9: {=IF(_xll.BQL(E9,"first(last(matches(px_last(dates=range(-1M,0D)),dayofweek(px_last(dates=range(-1M,0D)).date)==6),2),1)")="#N/A","-",_xll.BQL(E9,"first(last(matches(px_last(dates=range(-1M,0D)),dayofweek(px_last(dates=range(-1M,0D)).date)==6),2),1)"))} -> #NAME? | BB9: =IF(ISERROR((AZ9/BA9-1)*100),"-",(AZ9/BA9-1)*100) -> -
E10: RIO ln Equity | F10: =_xll.BDP($E10,F$3)&" BEST Curncy" -> #NAME? | G10: =AR10 -> #NAME? | J10: =_xll.BDP($E10,J$3) -> #NAME? | K10: =_xll.BDP($E10,K$3) -> #NAME? | L10: =IF(ISNUMBER(_xll.BDH($E10,"PX_LAST",TEXT($E$2,"YYYYMMDD"),TEXT($E$2,"YYYYMMDD"),"days=a","fill=p")),_xll.BDH($E10,"PX_LAST",TEXT($E$2,"YYYYMMDD"),TEXT($E$2,"YYYYMMDD"),"days=a","fill=p"),"-") -> - | M10: =IF(ISNUMBER(_xll.BDH($E10,"PX_LAST",TEXT($E$2-7,"YYYYMMDD"),TEXT($E$2-7,"YYYYMMDD"),"days=a","fill=p")),_xll.BDH($E10,"PX_LAST",TEXT($E$2-7,"YYYYMMDD"),TEXT($E$2-7,"YYYYMMDD"),"days=a","fill=p"),"-") -> - | N10: =IF(ISNUMBER(($L10-$M10)/$M10),($L10-$M10)/$M10,"-") -> - | O10: =IF(OR(_xll.BDP($E10,O$3)="#N/A N/A",_xll.BDP($E10,O$3)="#N/A Invalid Security"), "-", _xll.BDP($E10,O$3)) -> #NAME? | P10: =IF(ISNUMBER(_xll.BDH($F10,"PX_LAST",TEXT($E$2,"YYYYMMDD"),TEXT($E$2,"YYYYMMDD"),"days=a","fill=p")),_xll.BDH($F10,"PX_LAST",TEXT($E$2,"YYYYMMDD"),TEXT($E$2,"YYYYMMDD"),"days=a","fill=p"),"-") -> - | Q10: =IF(ISNUMBER(_xll.BDH($F10,"PX_LAST",TEXT($E$2-7,"YYYYMMDD"),TEXT($E$2-7,"YYYYMMDD"),"days=a","fill=p")),_xll.BDH($F10,"PX_LAST",TEXT($E$2-7,"YYYYMMDD"),TEXT($E$2-7,"YYYYMMDD"),"days=a","fill=p"),"-") -> - | R10: =IF(ISNUMBER($P10-$Q10),$P10-$Q10,"-") -> - | S10: =IF(ISNUMBER(_xll.BDP($F10,S$3)),_xll.BDP($F10,S$3),"-") -> - | T10: =IF(OR(AH10>0, AI10>0, AJ10>0, AK10>0, AL10>0, AM10>0), "Y"," ") -> #NAME? | U10: =IF(OR(_xll.BDP($E10,U$3)="#N/A N/A",_xll.BDP($E10,U$3)="#N/A Invalid Security"), "-", _xll.BDP($E10,U$3)) -> #NAME? | V10: =IF(OR(_xll.BDP($E10,V$2)="#N/A N/A",_xll.BDP($E10,V$2)="#N/A Invalid Security"), "-", _xll.BDP($E10,V$2)) -> #NAME? | W10: =IF(OR(_xll.BDP($E10,W$3)="#N/A N/A",_xll.BDP($E10,W$3)="#N/A Invalid Security"), "-", _xll.BDP($E10,W$3)) -> #NAME? | X10: =IF(OR(_xll.BDP($E10,X$3)="#N/A N/A",_xll.BDP($E10,X$3)="#N/A Invalid Security"), " ", _xll.BDP($E10,X$3)) -> #NAME? | Y10: =IF(OR(_xll.BDP($E10,Y$3)="#N/A N/A",_xll.BDP($E10,Y$3)="#N/A Invalid Security"), " ", _xll.BDP($E10,Y$3)) -> #NAME? | Z10: =IF(OR(_xll.BDP($E10,Z$3)="#N/A N/A",_xll.BDP($E10,Z$3)="#N/A Invalid Security"), " ", _xll.BDP($E10,Z$3)) -> #NAME? | AB10: A | AC10: A1 | AD10: A | AE10: STABLE | AF10: STABLE | AG10: STABLE | AH10: =IF(U10=AB10, 0,1) -> #NAME? | AI10: =IF(V10=AC10, 0,1) -> #NAME? | AJ10: =IF(W10=AD10, 0,1) -> #NAME? | AK10: =IF(X10=AE10, 0,1) -> #NAME? | AL10: =IF(Y10=AF10, 0,1) -> #NAME? | AM10: =IF(Z10=AG10, 0,1) -> #NAME? | AN10: =IF(SUM(AT10:AV10)>0,"Y","") | AO10: {=_xll.BDP($E10,"cur_mkt_cap")} -> #NAME? | AP10: {=_xll.BDP($E10,"crncy")} -> #NAME? | AQ10: {=_xll.BDP("USD"&AP10&" curncy","px_last")} -> #NAME? | AR10: =AO10/AQ10/1000000000 -> #NAME? | AT10: =IF(AND(AW10<=$E$1,AW10>=$F$1),1,"") | AU10: =IF(AND(AX10<=$E$1,AX10>=$F$1),1,"") | AV10: =IF(AND(AY10<=$E$1,AY10>=$F$1),1,"") | AW10: {=IF(ISERROR(DATEVALUE(_xll.BDP($E10,AW$6))),"",DATEVALUE(_xll.BDP($E10,AW$6)))} | AX10: {=IF(ISERROR(DATEVALUE(_xll.BDP($E10,AX$2))),"",DATEVALUE(_xll.BDP($E10,AX$2)))} | AY10: {=IF(ISERROR(DATEVALUE(_xll.BDP($E10,AY$6))),"",DATEVALUE(_xll.BDP($E10,AY$6)))} | AZ10: {=IF(_xll.BQL($E10, "last(matches(px_last(dates=range(-1w,0d)), dayofweek(px_last(dates=range(-1w,0d)).date)==6))")="#N/A","-",_xll.BQL($E10, "last(matches(px_last(dates=range(-1w,0d)), dayofweek(px_last(dates=range(-1w,0d)).date)==6))"))} -> #NAME? | BA10: {=IF(_xll.BQL(E10,"first(last(matches(px_last(dates=range(-1M,0D)),dayofweek(px_last(dates=range(-1M,0D)).date)==6),2),1)")="#N/A","-",_xll.BQL(E10,"first(last(matches(px_last(dates=range(-1M,0D)),dayofweek(px_last(dates=range(-1M,0D)).date)==6),2),1)"))} -> #NAME? | BB10: =IF(ISERROR((AZ10/BA10-1)*100),"-",(AZ10/BA10-1)*100) -> -
E11: bas gr Equity | F11: =_xll.BDP($E11,F$3)&" BEST Curncy" -> #NAME? | G11: =AR11 -> #NAME? | H11: =IF(ISNUMBER(L12),1,0) -> 0 | J11: =_xll.BDP($E11,J$3) -> #NAME? | K11: =_xll.BDP($E11,K$3) -> #NAME? | L11: =IF(ISNUMBER(_xll.BDH($E11,"PX_LAST",TEXT($E$2,"YYYYMMDD"),TEXT($E$2,"YYYYMMDD"),"days=a","fill=p")),_xll.BDH($E11,"PX_LAST",TEXT($E$2,"YYYYMMDD"),TEXT($E$2,"YYYYMMDD"),"days=a","fill=p"),"-") -> - | M11: =IF(ISNUMBER(_xll.BDH($E11,"PX_LAST",TEXT($E$2-7,"YYYYMMDD"),TEXT($E$2-7,"YYYYMMDD"),"days=a","fill=p")),_xll.BDH($E11,"PX_LAST",TEXT($E$2-7,"YYYYMMDD"),TEXT($E$2-7,"YYYYMMDD"),"days=a","fill=p"),"-") -> - | N11: =IF(ISNUMBER(($L11-$M11)/$M11),($L11-$M11)/$M11,"-") -> - | O11: =IF(OR(_xll.BDP($E11,O$3)="#N/A N/A",_xll.BDP($E11,O$3)="#N/A Invalid Security"), "-", _xll.BDP($E11,O$3)) -> #NAME? | P11: =IF(ISNUMBER(_xll.BDH($F11,"PX_LAST",TEXT($E$2,"YYYYMMDD"),TEXT($E$2,"YYYYMMDD"),"days=a","fill=p")),_xll.BDH($F11,"PX_LAST",TEXT($E$2,"YYYYMMDD"),TEXT($E$2,"YYYYMMDD"),"days=a","fill=p"),"-") -> - | Q11: =IF(ISNUMBER(_xll.BDH($F11,"PX_LAST",TEXT($E$2-7,"YYYYMMDD"),TEXT($E$2-7,"YYYYMMDD"),"days=a","fill=p")),_xll.BDH($F11,"PX_LAST",TEXT($E$2-7,"YYYYMMDD"),TEXT($E$2-7,"YYYYMMDD"),"days=a","fill=p"),"-") -> - | R11: =IF(ISNUMBER($P11-$Q11),$P11-$Q11,"-") -> - | S11: =IF(ISNUMBER(_xll.BDP($F11,S$3)),_xll.BDP($F11,S$3),"-") -> - | T11: =IF(OR(AH11>0, AI11>0, AJ11>0, AK11>0, AL11>0, AM11>0), "Y"," ") -> #NAME? | U11: =IF(OR(_xll.BDP($E11,U$3)="#N/A N/A",_xll.BDP($E11,U$3)="#N/A Invalid Security"), "-", _xll.BDP($E11,U$3)) -> #NAME? | V11: =IF(OR(_xll.BDP($E11,V$2)="#N/A N/A",_xll.BDP($E11,V$2)="#N/A Invalid Security"), "-", _xll.BDP($E11,V$2)) -> #NAME? | W11: =IF(OR(_xll.BDP($E11,W$3)="#N/A N/A",_xll.BDP($E11,W$3)="#N/A Invalid Security"), "-", _xll.BDP($E11,W$3)) -> #NAME? | X11: =IF(OR(_xll.BDP($E11,X$3)="#N/A N/A",_xll.BDP($E11,X$3)="#N/A Invalid Security"), " ", _xll.BDP($E11,X$3)) -> #NAME? | Y11: =IF(OR(_xll.BDP($E11,Y$3)="#N/A N/A",_xll.BDP($E11,Y$3)="#N/A Invalid Security"), " ", _xll.BDP($E11,Y$3)) -> #NAME? | Z11: =IF(OR(_xll.BDP($E11,Z$3)="#N/A N/A",_xll.BDP($E11,Z$3)="#N/A Invalid Security"), " ", _xll.BDP($E11,Z$3)) -> #NAME? | AB11: A- | AC11: A3 | AD11: A | AE11: STABLE | AF11: STABLE | AG11: STABLE | AH11: =IF(U11=AB11, 0,1) -> #NAME? | AI11: =IF(V11=AC11, 0,1) -> #NAME? | AJ11: =IF(W11=AD11, 0,1) -> #NAME? | AK11: =IF(X11=AE11, 0,1) -> #NAME? | AL11: =IF(Y11=AF11, 0,1) -> #NAME? | AM11: =IF(Z11=AG11, 0,1) -> #NAME? | AN11: =IF(SUM(AT11:AV11)>0,"Y","") | AO11: {=_xll.BDP($E11,"cur_mkt_cap")} -> #NAME? | AP11: {=_xll.BDP($E11,"crncy")} -> #NAME? | AQ11: {=_xll.BDP("USD"&AP11&" curncy","px_last")} -> #NAME? | AR11: =AO11/AQ11/1000000000 -> #NAME? | AT11: =IF(AND(AW11<=$E$1,AW11>=$F$1),1,"") | AU11: =IF(AND(AX11<=$E$1,AX11>=$F$1),1,"") | AV11: =IF(AND(AY11<=$E$1,AY11>=$F$1),1,"") | AW11: {=IF(ISERROR(DATEVALUE(_xll.BDP($E11,AW$6))),"",DATEVALUE(_xll.BDP($E11,AW$6)))} | AX11: {=IF(ISERROR(DATEVALUE(_xll.BDP($E11,AX$2))),"",DATEVALUE(_xll.BDP($E11,AX$2)))} | AY11: {=IF(ISERROR(DATEVALUE(_xll.BDP($E11,AY$6))),"",DATEVALUE(_xll.BDP($E11,AY$6)))} | AZ11: {=IF(_xll.BQL($E11, "last(matches(px_last(dates=range(-1w,0d)), dayofweek(px_last(dates=range(-1w,0d)).date)==6))")="#N/A","-",_xll.BQL($E11, "last(matches(px_last(dates=range(-1w,0d)), dayofweek(px_last(dates=range(-1w,0d)).date)==6))"))} -> #NAME? | BA11: {=IF(_xll.BQL(E11,"first(last(matches(px_last(dates=range(-1M,0D)),dayofweek(px_last(dates=range(-1M,0D)).date)==6),2),1)")="#N/A","-",_xll.BQL(E11,"first(last(matches(px_last(dates=range(-1M,0D)),dayofweek(px_last(dates=range(-1M,0D)).date)==6),2),1)"))} -> #NAME? | BB11: =IF(ISERROR((AZ11/BA11-1)*100),"-",(AZ11/BA11-1)*100) -> -
E12: 1006z ci Equity | F12: =_xll.BDP($E12,F$3)&" BEST Curncy" -> #NAME? | G12: =AR12 -> #NAME? | J12: =_xll.BDP($E12,J$3) -> #NAME? | K12: =_xll.BDP($E12,K$3) -> #NAME? | L12: =IF(ISNUMBER(_xll.BDH($E12,"PX_LAST",TEXT($E$2,"YYYYMMDD"),TEXT($E$2,"YYYYMMDD"),"days=a","fill=p")),_xll.BDH($E12,"PX_LAST",TEXT($E$2,"YYYYMMDD"),TEXT($E$2,"YYYYMMDD"),"days=a","fill=p"),"-") -> - | M12: =IF(ISNUMBER(_xll.BDH($E12,"PX_LAST",TEXT($E$2-7,"YYYYMMDD"),TEXT($E$2-7,"YYYYMMDD"),"days=a","fill=p")),_xll.BDH($E12,"PX_LAST",TEXT($E$2-7,"YYYYMMDD"),TEXT($E$2-7,"YYYYMMDD"),"days=a","fill=p"),"-") -> - | N12: =IF(ISNUMBER(($L12-$M12)/$M12),($L12-$M12)/$M12,"-") -> - | O12: =IF(OR(_xll.BDP($E12,O$3)="#N/A N/A",_xll.BDP($E12,O$3)="#N/A Invalid Security"), "-", _xll.BDP($E12,O$3)) -> #NAME? | P12: =IF(ISNUMBER(_xll.BDH($F12,"PX_LAST",TEXT($E$2,"YYYYMMDD"),TEXT($E$2,"YYYYMMDD"),"days=a","fill=p")),_xll.BDH($F12,"PX_LAST",TEXT($E$2,"YYYYMMDD"),TEXT($E$2,"YYYYMMDD"),"days=a","fill=p"),"-") -> - | Q12: =IF(ISNUMBER(_xll.BDH($F12,"PX_LAST",TEXT($E$2-7,"YYYYMMDD"),TEXT($E$2-7,"YYYYMMDD"),"days=a","fill=p")),_xll.BDH($F12,"PX_LAST",TEXT($E$2-7,"YYYYMMDD"),TEXT($E$2-7,"YYYYMMDD"),"days=a","fill=p"),"-") -> - | R12: =IF(ISNUMBER($P12-$Q12),$P12-$Q12,"-") -> - | S12: =IF(ISNUMBER(_xll.BDP($F12,S$3)),_xll.BDP($F12,S$3),"-") -> - | T12: =IF(OR(AH12>0, AI12>0, AJ12>0, AK12>0, AL12>0, AM12>0), "Y"," ") -> #NAME? | U12: =IF(OR(_xll.BDP($E12,U$3)="#N/A N/A",_xll.BDP($E12,U$3)="#N/A Invalid Security"), "-", _xll.BDP($E12,U$3)) -> #NAME? | V12: =IF(OR(_xll.BDP($E12,V$2)="#N/A N/A",_xll.BDP($E12,V$2)="#N/A Invalid Security"), "-", _xll.BDP($E12,V$2)) -> #NAME? | W12: =IF(OR(_xll.BDP($E12,W$3)="#N/A N/A",_xll.BDP($E12,W$3)="#N/A Invalid Security"), "-", _xll.BDP($E12,W$3)) -> #NAME? | X12: =IF(OR(_xll.BDP($E12,X$3)="#N/A N/A",_xll.BDP($E12,X$3)="#N/A Invalid Security"), " ", _xll.BDP($E12,X$3)) -> #NAME? | Y12: =IF(OR(_xll.BDP($E12,Y$3)="#N/A N/A",_xll.BDP($E12,Y$3)="#N/A Invalid Security"), " ", _xll.BDP($E12,Y$3)) -> #NAME? | Z12: =IF(OR(_xll.BDP($E12,Z$3)="#N/A N/A",_xll.BDP($E12,Z$3)="#N/A Invalid Security"), " ", _xll.BDP($E12,Z$3)) -> #NAME? | AB12: A- | AC12: A3 | AD12: A | AE12: STABLE | AF12: STABLE | AG12: STABLE | AH12: =IF(U12=AB12, 0,1) -> #NAME? | AI12: =IF(V12=AC12, 0,1) -> #NAME? | AJ12: =IF(W12=AD12, 0,1) -> #NAME? | AK12: =IF(X12=AE12, 0,1) -> #NAME? | AL12: =IF(Y12=AF12, 0,1) -> #NAME? | AM12: =IF(Z12=AG12, 0,1) -> #NAME? | AN12: =IF(SUM(AT12:AV12)>0,"Y","") | AO12: {=_xll.BDP($E12,"cur_mkt_cap")} -> #NAME? | AP12: {=_xll.BDP($E12,"crncy")} -> #NAME? | AQ12: {=_xll.BDP("USD"&AP12&" curncy","px_last")} -> #NAME? | AR12: =AO12/AQ12/1000000000 -> #NAME? | AT12: =IF(AND(AW12<=$E$1,AW12>=$F$1),1,"") | AU12: =IF(AND(AX12<=$E$1,AX12>=$F$1),1,"") | AV12: =IF(AND(AY12<=$E$1,AY12>=$F$1),1,"") | AW12: {=IF(ISERROR(DATEVALUE(_xll.BDP($E12,AW$6))),"",DATEVALUE(_xll.BDP($E12,AW$6)))} | AX12: {=IF(ISERROR(DATEVALUE(_xll.BDP($E12,AX$2))),"",DATEVALUE(_xll.BDP($E12,AX$2)))} | AY12: {=IF(ISERROR(DATEVALUE(_xll.BDP($E12,AY$6))),"",DATEVALUE(_xll.BDP($E12,AY$6)))} | AZ12: {=IF(_xll.BQL($E12, "last(matches(px_last(dates=range(-1w,0d)), dayofweek(px_last(dates=range(-1w,0d)).date)==6))")="#N/A","-",_xll.BQL($E12, "last(matches(px_last(dates=range(-1w,0d)), dayofweek(px_last(dates=range(-1w,0d)).date)==6))"))} -> #NAME? | BA12: {=IF(_xll.BQL(E12,"first(last(matches(px_last(dates=range(-1M,0D)),dayofweek(px_last(dates=range(-1M,0D)).date)==6),2),1)")="#N/A","-",_xll.BQL(E12,"first(last(matches(px_last(dates=range(-1M,0D)),dayofweek(px_last(dates=range(-1M,0D)).date)==6),2),1)"))} -> #NAME? | BB12: =IF(ISERROR((AZ12/BA12-1)*100),"-",(AZ12/BA12-1)*100) -> -
E13: 3091z us Equity | F13: =_xll.BDP($E13,F$3)&" BEST Curncy" -> #NAME? | G13: =AR13 -> #NAME? | J13: =_xll.BDP($E13,J$3) -> #NAME? | K13: =_xll.BDP($E13,K$3) -> #NAME? | L13: =IF(ISNUMBER(_xll.BDH($E13,"PX_LAST",TEXT($E$2,"YYYYMMDD"),TEXT($E$2,"YYYYMMDD"),"days=a","fill=p")),_xll.BDH($E13,"PX_LAST",TEXT($E$2,"YYYYMMDD"),TEXT($E$2,"YYYYMMDD"),"days=a","fill=p"),"-") -> - | M13: =IF(ISNUMBER(_xll.BDH($E13,"PX_LAST",TEXT($E$2-7,"YYYYMMDD"),TEXT($E$2-7,"YYYYMMDD"),"days=a","fill=p")),_xll.BDH($E13,"PX_LAST",TEXT($E$2-7,"YYYYMMDD"),TEXT($E$2-7,"YYYYMMDD"),"days=a","fill=p"),"-") -> - | N13: =IF(ISNUMBER(($L13-$M13)/$M13),($L13-$M13)/$M13,"-") -> - | O13: =IF(OR(_xll.BDP($E13,O$3)="#N/A N/A",_xll.BDP($E13,O$3)="#N/A Invalid Security"), "-", _xll.BDP($E13,O$3)) -> #NAME? | P13: =IF(ISNUMBER(_xll.BDH($F13,"PX_LAST",TEXT($E$2,"YYYYMMDD"),TEXT($E$2,"YYYYMMDD"),"days=a","fill=p")),_xll.BDH($F13,"PX_LAST",TEXT($E$2,"YYYYMMDD"),TEXT($E$2,"YYYYMMDD"),"days=a","fill=p"),"-") -> - | Q13: =IF(ISNUMBER(_xll.BDH($F13,"PX_LAST",TEXT($E$2-7,"YYYYMMDD"),TEXT($E$2-7,"YYYYMMDD"),"days=a","fill=p")),_xll.BDH($F13,"PX_LAST",TEXT($E$2-7,"YYYYMMDD"),TEXT($E$2-7,"YYYYMMDD"),"days=a","fill=p"),"-") -> - | R13: =IF(ISNUMBER($P13-$Q13),$P13-$Q13,"-") -> - | S13: =IF(ISNUMBER(_xll.BDP($F13,S$3)),_xll.BDP($F13,S$3),"-") -> - | T13: =IF(OR(AH13>0, AI13>0, AJ13>0, AK13>0, AL13>0, AM13>0), "Y"," ") -> #NAME? | U13: =IF(OR(_xll.BDP($E13,U$3)="#N/A N/A",_xll.BDP($E13,U$3)="#N/A Invalid Security"), "-", _xll.BDP($E13,U$3)) -> #NAME? | V13: =IF(OR(_xll.BDP($E13,V$2)="#N/A N/A",_xll.BDP($E13,V$2)="#N/A Invalid Security"), "-", _xll.BDP($E13,V$2)) -> #NAME? | W13: =IF(OR(_xll.BDP($E13,W$3)="#N/A N/A",_xll.BDP($E13,W$3)="#N/A Invalid Security"), "-", _xll.BDP($E13,W$3)) -> #NAME? | X13: =IF(OR(_xll.BDP($E13,X$3)="#N/A N/A",_xll.BDP($E13,X$3)="#N/A Invalid Security"), " ", _xll.BDP($E13,X$3)) -> #NAME? | Y13: =IF(OR(_xll.BDP($E13,Y$3)="#N/A N/A",_xll.BDP($E13,Y$3)="#N/A Invalid Security"), " ", _xll.BDP($E13,Y$3)) -> #NAME? | Z13: =IF(OR(_xll.BDP($E13,Z$3)="#N/A N/A",_xll.BDP($E13,Z$3)="#N/A Invalid Security"), " ", _xll.BDP($E13,Z$3)) -> #NAME? | AB13: A | AC13: A2 | AD13: A | AE13: STABLE | AF13: STABLE | AG13: STABLE | AH13: =IF(U13=AB13, 0,1) -> #NAME? | AI13: =IF(V13=AC13, 0,1) -> #NAME? | AJ13: =IF(W13=AD13, 0,1) -> #NAME? | AK13: =IF(X13=AE13, 0,1) -> #NAME? | AL13: =IF(Y13=AF13, 0,1) -> #NAME? | AM13: =IF(Z13=AG13, 0,1) -> #NAME? | AN13: =IF(SUM(AT13:AV13)>0,"Y","") | AO13: {=_xll.BDP($E13,"cur_mkt_cap")} -> #NAME? | AP13: {=_xll.BDP($E13,"crncy")} -> #NAME? | AQ13: {=_xll.BDP("USD"&AP13&" curncy","px_last")} -> #NAME? | AR13: =AO13/AQ13/1000000000 -> #NAME? | AT13: =IF(AND(AW13<=$E$1,AW13>=$F$1),1,"") | AU13: =IF(AND(AX13<=$E$1,AX13>=$F$1),1,"") | AV13: =IF(AND(AY13<=$E$1,AY13>=$F$1),1,"") | AW13: {=IF(ISERROR(DATEVALUE(_xll.BDP($E13,AW$6))),"",DATEVALUE(_xll.BDP($E13,AW$6)))} | AX13: {=IF(ISERROR(DATEVALUE(_xll.BDP($E13,AX$2))),"",DATEVALUE(_xll.BDP($E13,AX$2)))} | AY13: {=IF(ISERROR(DATEVALUE(_xll.BDP($E13,AY$6))),"",DATEVALUE(_xll.BDP($E13,AY$6)))} | AZ13: {=IF(_xll.BQL($E13, "last(matches(px_last(dates=range(-1w,0d)), dayofweek(px_last(dates=range(-1w,0d)).date)==6))")="#N/A","-",_xll.BQL($E13, "last(matches(px_last(dates=range(-1w,0d)), dayofweek(px_last(dates=range(-1w,0d)).date)==6))"))} -> #NAME? | BA13: {=IF(_xll.BQL(E13,"first(last(matches(px_last(dates=range(-1M,0D)),dayofweek(px_last(dates=range(-1M,0D)).date)==6),2),1)")="#N/A","-",_xll.BQL(E13,"first(last(matches(px_last(dates=range(-1M,0D)),dayofweek(px_last(dates=range(-1M,0D)).date)==6),2),1)"))} -> #NAME? | BB13: =IF(ISERROR((AZ13/BA13-1)*100),"-",(AZ13/BA13-1)*100) -> -
E14: vale3 bz Equity | F14: =_xll.BDP($E14,F$3)&" BEST Curncy" -> #NAME? | G14: =AR14 -> #NAME? | J14: =_xll.BDP($E14,J$3) -> #NAME? | K14: =_xll.BDP($E14,K$3) -> #NAME? | L14: =IF(ISNUMBER(_xll.BDH($E14,"PX_LAST",TEXT($E$2,"YYYYMMDD"),TEXT($E$2,"YYYYMMDD"),"days=a","fill=p")),_xll.BDH($E14,"PX_LAST",TEXT($E$2,"YYYYMMDD"),TEXT($E$2,"YYYYMMDD"),"days=a","fill=p"),"-") -> - | M14: =IF(ISNUMBER(_xll.BDH($E14,"PX_LAST",TEXT($E$2-7,"YYYYMMDD"),TEXT($E$2-7,"YYYYMMDD"),"days=a","fill=p")),_xll.BDH($E14,"PX_LAST",TEXT($E$2-7,"YYYYMMDD"),TEXT($E$2-7,"YYYYMMDD"),"days=a","fill=p"),"-") -> - | N14: =IF(ISNUMBER(($L14-$M14)/$M14),($L14-$M14)/$M14,"-") -> - | O14: =IF(OR(_xll.BDP($E14,O$3)="#N/A N/A",_xll.BDP($E14,O$3)="#N/A Invalid Security"), "-", _xll.BDP($E14,O$3)) -> #NAME? | P14: =IF(ISNUMBER(_xll.BDH($F14,"PX_LAST",TEXT($E$2,"YYYYMMDD"),TEXT($E$2,"YYYYMMDD"),"days=a","fill=p")),_xll.BDH($F14,"PX_LAST",TEXT($E$2,"YYYYMMDD"),TEXT($E$2,"YYYYMMDD"),"days=a","fill=p"),"-") -> - | Q14: =IF(ISNUMBER(_xll.BDH($F14,"PX_LAST",TEXT($E$2-7,"YYYYMMDD"),TEXT($E$2-7,"YYYYMMDD"),"days=a","fill=p")),_xll.BDH($F14,"PX_LAST",TEXT($E$2-7,"YYYYMMDD"),TEXT($E$2-7,"YYYYMMDD"),"days=a","fill=p"),"-") -> - | R14: =IF(ISNUMBER($P14-$Q14),$P14-$Q14,"-") -> - | S14: =IF(ISNUMBER(_xll.BDP($F14,S$3)),_xll.BDP($F14,S$3),"-") -> - | T14: =IF(OR(AH14>0, AI14>0, AJ14>0, AK14>0, AL14>0, AM14>0), "Y"," ") -> #NAME? | U14: =IF(OR(_xll.BDP($E14,U$3)="#N/A N/A",_xll.BDP($E14,U$3)="#N/A Invalid Security"), "-", _xll.BDP($E14,U$3)) -> #NAME? | V14: =IF(OR(_xll.BDP($E14,V$2)="#N/A N/A",_xll.BDP($E14,V$2)="#N/A Invalid Security"), "-", _xll.BDP($E14,V$2)) -> #NAME? | W14: =IF(OR(_xll.BDP($E14,W$3)="#N/A N/A",_xll.BDP($E14,W$3)="#N/A Invalid Security"), "-", _xll.BDP($E14,W$3)) -> #NAME? | X14: =IF(OR(_xll.BDP($E14,X$3)="#N/A N/A",_xll.BDP($E14,X$3)="#N/A Invalid Security"), " ", _xll.BDP($E14,X$3)) -> #NAME? | Y14: =IF(OR(_xll.BDP($E14,Y$3)="#N/A N/A",_xll.BDP($E14,Y$3)="#N/A Invalid Security"), " ", _xll.BDP($E14,Y$3)) -> #NAME? | Z14: =IF(OR(_xll.BDP($E14,Z$3)="#N/A N/A",_xll.BDP($E14,Z$3)="#N/A Invalid Security"), " ", _xll.BDP($E14,Z$3)) -> #NAME? | AB14: BBB- | AC14: Baa2 | AD14: BBB | AE14: STABLE | AF14: STABLE | AG14: POS | AH14: =IF(U14=AB14, 0,1) -> #NAME? | AI14: =IF(V14=AC14, 0,1) -> #NAME? | AJ14: =IF(W14=AD14, 0,1) -> #NAME? | AK14: =IF(X14=AE14, 0,1) -> #NAME? | AL14: =IF(Y14=AF14, 0,1) -> #NAME? | AM14: =IF(Z14=AG14, 0,1) -> #NAME? | AN14: =IF(SUM(AT14:AV14)>0,"Y","") | AO14: {=_xll.BDP($E14,"cur_mkt_cap")} -> #NAME? | AP14: {=_xll.BDP($E14,"crncy")} -> #NAME? | AQ14: {=_xll.BDP("USD"&AP14&" curncy","px_last")} -> #NAME? | AR14: =AO14/AQ14/1000000000 -> #NAME? | AT14: =IF(AND(AW14<=$E$1,AW14>=$F$1),1,"") | AU14: =IF(AND(AX14<=$E$1,AX14>=$F$1),1,"") | AV14: =IF(AND(AY14<=$E$1,AY14>=$F$1),1,"") | AW14: {=IF(ISERROR(DATEVALUE(_xll.BDP($E14,AW$6))),"",DATEVALUE(_xll.BDP($E14,AW$6)))} | AX14: {=IF(ISERROR(DATEVALUE(_xll.BDP($E14,AX$2))),"",DATEVALUE(_xll.BDP($E14,AX$2)))} | AY14: {=IF(ISERROR(DATEVALUE(_xll.BDP($E14,AY$6))),"",DATEVALUE(_xll.BDP($E14,AY$6)))} | AZ14: {=IF(_xll.BQL($E14, "last(matches(px_last(dates=range(-1w,0d)), dayofweek(px_last(dates=range(-1w,0d)).date)==6))")="#N/A","-",_xll.BQL($E14, "last(matches(px_last(dates=range(-1w,0d)), dayofweek(px_last(dates=range(-1w,0d)).date)==6))"))} -> #NAME? | BA14: {=IF(_xll.BQL(E14,"first(last(matches(px_last(dates=range(-1M,0D)),dayofweek(px_last(dates=range(-1M,0D)).date)==6),2),1)")="#N/A","-",_xll.BQL(E14,"first(last(matches(px_last(dates=range(-1M,0D)),dayofweek(px_last(dates=range(-1M,0D)).date)==6),2),1)"))} -> #NAME? | BB14: =IF(ISERROR((AZ14/BA14-1)*100),"-",(AZ14/BA14-1)*100) -> -
E15: 1006Z CI Equity | F15: =_xll.BDP($E15,F$3)&" BEST Curncy" -> #NAME? | G15: =AR15 -> #NAME? | J15: =_xll.BDP($E15,J$3) -> #NAME? | K15: =_xll.BDP($E15,K$3) -> #NAME? | L15: =IF(ISNUMBER(_xll.BDH($E15,"PX_LAST",TEXT($E$2,"YYYYMMDD"),TEXT($E$2,"YYYYMMDD"),"days=a","fill=p")),_xll.BDH($E15,"PX_LAST",TEXT($E$2,"YYYYMMDD"),TEXT($E$2,"YYYYMMDD"),"days=a","fill=p"),"-") -> - | M15: =IF(ISNUMBER(_xll.BDH($E15,"PX_LAST",TEXT($E$2-7,"YYYYMMDD"),TEXT($E$2-7,"YYYYMMDD"),"days=a","fill=p")),_xll.BDH($E15,"PX_LAST",TEXT($E$2-7,"YYYYMMDD"),TEXT($E$2-7,"YYYYMMDD"),"days=a","fill=p"),"-") -> - | N15: =IF(ISNUMBER(($L15-$M15)/$M15),($L15-$M15)/$M15,"-") -> - | O15: =IF(OR(_xll.BDP($E15,O$3)="#N/A N/A",_xll.BDP($E15,O$3)="#N/A Invalid Security"), "-", _xll.BDP($E15,O$3)) -> #NAME? | P15: =IF(ISNUMBER(_xll.BDH($F15,"PX_LAST",TEXT($E$2,"YYYYMMDD"),TEXT($E$2,"YYYYMMDD"),"days=a","fill=p")),_xll.BDH($F15,"PX_LAST",TEXT($E$2,"YYYYMMDD"),TEXT($E$2,"YYYYMMDD"),"days=a","fill=p"),"-") -> - | Q15: =IF(ISNUMBER(_xll.BDH($F15,"PX_LAST",TEXT($E$2-7,"YYYYMMDD"),TEXT($E$2-7,"YYYYMMDD"),"days=a","fill=p")),_xll.BDH($F15,"PX_LAST",TEXT($E$2-7,"YYYYMMDD"),TEXT($E$2-7,"YYYYMMDD"),"days=a","fill=p"),"-") -> - | R15: =IF(ISNUMBER($P15-$Q15),$P15-$Q15,"-") -> - | S15: =IF(ISNUMBER(_xll.BDP($F15,S$3)),_xll.BDP($F15,S$3),"-") -> - | T15: =IF(OR(AH15>0, AI15>0, AJ15>0, AK15>0, AL15>0, AM15>0), "Y"," ") -> #NAME? | U15: =IF(OR(_xll.BDP($E15,U$3)="#N/A N/A",_xll.BDP($E15,U$3)="#N/A Invalid Security"), "-", _xll.BDP($E15,U$3)) -> #NAME? | V15: =IF(OR(_xll.BDP($E15,V$2)="#N/A N/A",_xll.BDP($E15,V$2)="#N/A Invalid Security"), "-", _xll.BDP($E15,V$2)) -> #NAME? | W15: =IF(OR(_xll.BDP($E15,W$3)="#N/A N/A",_xll.BDP($E15,W$3)="#N/A Invalid Security"), "-", _xll.BDP($E15,W$3)) -> #NAME? | X15: =IF(OR(_xll.BDP($E15,X$3)="#N/A N/A",_xll.BDP($E15,X$3)="#N/A Invalid Security"), " ", _xll.BDP($E15,X$3)) -> #NAME? | Y15: =IF(OR(_xll.BDP($E15,Y$3)="#N/A N/A",_xll.BDP($E15,Y$3)="#N/A Invalid Security"), " ", _xll.BDP($E15,Y$3)) -> #NAME? | Z15: =IF(OR(_xll.BDP($E15,Z$3)="#N/A N/A",_xll.BDP($E15,Z$3)="#N/A Invalid Security"), " ", _xll.BDP($E15,Z$3)) -> #NAME? | AB15: BBB+ | AC15: Baa2 | AD15: BBB+ | AE15: STABLE | AF15: STABLE | AG15: STABLE | AH15: =IF(U15=AB15, 0,1) -> #NAME? | AI15: =IF(V15=AC15, 0,1) -> #NAME? | AJ15: =IF(W15=AD15, 0,1) -> #NAME? | AK15: =IF(X15=AE15, 0,1) -> #NAME? | AL15: =IF(Y15=AF15, 0,1) -> #NAME? | AM15: =IF(Z15=AG15, 0,1) -> #NAME? | AN15: =IF(SUM(AT15:AV15)>0,"Y","") | AO15: {=_xll.BDP($E15,"cur_mkt_cap")} -> #NAME? | AP15: {=_xll.BDP($E15,"crncy")} -> #NAME? | AQ15: {=_xll.BDP("USD"&AP15&" curncy","px_last")} -> #NAME? | AR15: =AO15/AQ15/1000000000 -> #NAME? | AT15: =IF(AND(AW15<=$E$1,AW15>=$F$1),1,"") | AU15: =IF(AND(AX15<=$E$1,AX15>=$F$1),1,"") | AV15: =IF(AND(AY15<=$E$1,AY15>=$F$1),1,"") | AW15: {=IF(ISERROR(DATEVALUE(_xll.BDP($E15,AW$6))),"",DATEVALUE(_xll.BDP($E15,AW$6)))} | AX15: {=IF(ISERROR(DATEVALUE(_xll.BDP($E15,AX$2))),"",DATEVALUE(_xll.BDP($E15,AX$2)))} | AY15: {=IF(ISERROR(DATEVALUE(_xll.BDP($E15,AY$6))),"",DATEVALUE(_xll.BDP($E15,AY$6)))} | AZ15: {=IF(_xll.BQL($E15, "last(matches(px_last(dates=range(-1w,0d)), dayofweek(px_last(dates=range(-1w,0d)).date)==6))")="#N/A","-",_xll.BQL($E15, "last(matches(px_last(dates=range(-1w,0d)), dayofweek(px_last(dates=range(-1w,0d)).date)==6))"))} -> #NAME? | BA15: {=IF(_xll.BQL(E15,"first(last(matches(px_last(dates=range(-1M,0D)),dayofweek(px_last(dates=range(-1M,0D)).date)==6),2),1)")="#N/A","-",_xll.BQL(E15,"first(last(matches(px_last(dates=range(-1M,0D)),dayofweek(px_last(dates=range(-1M,0D)).date)==6),2),1)"))} -> #NAME? | BB15: =IF(ISERROR((AZ15/BA15-1)*100),"-",(AZ15/BA15-1)*100) -> -
E16: 700 HK Equity | F16: =_xll.BDP($E16,F$3)&" best Curncy" -> #NAME? | G16: =AR16 -> #NAME? | I16: 通訊 | J16: =_xll.BDP($E16,J$3) -> #NAME? | K16: =_xll.BDP($E16,K$3) -> #NAME? | L16: =IF(ISNUMBER(_xll.BDH($E16,"PX_LAST",TEXT($E$2,"YYYYMMDD"),TEXT($E$2,"YYYYMMDD"),"days=a","fill=p")),_xll.BDH($E16,"PX_LAST",TEXT($E$2,"YYYYMMDD"),TEXT($E$2,"YYYYMMDD"),"days=a","fill=p"),"-") -> - | M16: =IF(ISNUMBER(_xll.BDH($E16,"PX_LAST",TEXT($E$2-7,"YYYYMMDD"),TEXT($E$2-7,"YYYYMMDD"),"days=a","fill=p")),_xll.BDH($E16,"PX_LAST",TEXT($E$2-7,"YYYYMMDD"),TEXT($E$2-7,"YYYYMMDD"),"days=a","fill=p"),"-") -> - | N16: =IF(ISNUMBER(($L16-$M16)/$M16),($L16-$M16)/$M16,"-") -> - | O16: =IF(OR(_xll.BDP($E16,O$3)="#N/A N/A",_xll.BDP($E16,O$3)="#N/A Invalid Security"), "-", _xll.BDP($E16,O$3)) -> #NAME? | P16: =IF(ISNUMBER(_xll.BDH($F16,"PX_LAST",TEXT($E$2,"YYYYMMDD"),TEXT($E$2,"YYYYMMDD"),"days=a","fill=p")),_xll.BDH($F16,"PX_LAST",TEXT($E$2,"YYYYMMDD"),TEXT($E$2,"YYYYMMDD"),"days=a","fill=p"),"-") -> - | Q16: =IF(ISNUMBER(_xll.BDH($F16,"PX_LAST",TEXT($E$2-7,"YYYYMMDD"),TEXT($E$2-7,"YYYYMMDD"),"days=a","fill=p")),_xll.BDH($F16,"PX_LAST",TEXT($E$2-7,"YYYYMMDD"),TEXT($E$2-7,"YYYYMMDD"),"days=a","fill=p"),"-") -> - | R16: =IF(ISNUMBER($P16-$Q16),$P16-$Q16,"-") -> - | S16: =IF(ISNUMBER(_xll.BDP($F16,S$3)),_xll.BDP($F16,S$3),"-") -> - | T16: =IF(OR(AH16>0, AI16>0, AJ16>0, AK16>0, AL16>0, AM16>0), "Y"," ") -> #NAME? | U16: =IF(OR(_xll.BDP($E16,U$3)="#N/A N/A",_xll.BDP($E16,U$3)="#N/A Invalid Security"), "-", _xll.BDP($E16,U$3)) -> #NAME? | V16: =IF(OR(_xll.BDP($E16,V$2)="#N/A N/A",_xll.BDP($E16,V$2)="#N/A Invalid Security"), "-", _xll.BDP($E16,V$2)) -> #NAME? | W16: =IF(OR(_xll.BDP($E16,W$3)="#N/A N/A",_xll.BDP($E16,W$3)="#N/A Invalid Security"), "-", _xll.BDP($E16,W$3)) -> #NAME? | X16: =IF(OR(_xll.BDP($E16,X$3)="#N/A N/A",_xll.BDP($E16,X$3)="#N/A Invalid Security"), " ", _xll.BDP($E16,X$3)) -> #NAME? | Y16: =IF(OR(_xll.BDP($E16,Y$3)="#N/A N/A",_xll.BDP($E16,Y$3)="#N/A Invalid Security"), " ", _xll.BDP($E16,Y$3)) -> #NAME? | Z16: =IF(OR(_xll.BDP($E16,Z$3)="#N/A N/A",_xll.BDP($E16,Z$3)="#N/A Invalid Security"), " ", _xll.BDP($E16,Z$3)) -> #NAME? | AB16: A+ | AC16: A1 | AD16: A | AE16: STABLE | AF16: NEG | AG16: STABLE | AH16: =IF(U16=AB16, 0,1) -> #NAME? | AI16: =IF(V16=AC16, 0,1) -> #NAME? | AJ16: =IF(W16=AD16, 0,1) -> #NAME? | AK16: =IF(X16=AE16, 0,1) -> #NAME? | AL16: =IF(Y16=AF16, 0,1) -> #NAME? | AM16: =IF(Z16=AG16, 0,1) -> #NAME? | AN16: =IF(SUM(AT16:AV16)>0,"Y","") | AO16: {=_xll.BDP($E16,"cur_mkt_cap")} -> #NAME? | AP16: {=_xll.BDP($E16,"crncy")} -> #NAME? | AQ16: {=_xll.BDP("USD"&AP16&" curncy","px_last")} -> #NAME? | AR16: =AO16/AQ16/1000000000 -> #NAME? | AT16: =IF(AND(AW16<=$E$1,AW16>=$F$1),1,"") | AU16: =IF(AND(AX16<=$E$1,AX16>=$F$1),1,"") | AV16: =IF(AND(AY16<=$E$1,AY16>=$F$1),1,"") | AW16: {=IF(ISERROR(DATEVALUE(_xll.BDP($E16,AW$6))),"",DATEVALUE(_xll.BDP($E16,AW$6)))} | AX16: {=IF(ISERROR(DATEVALUE(_xll.BDP($E16,AX$2))),"",DATEVALUE(_xll.BDP($E16,AX$2)))} | AY16: {=IF(ISERROR(DATEVALUE(_xll.BDP($E16,AY$6))),"",DATEVALUE(_xll.BDP($E16,AY$6)))} | AZ16: {=IF(_xll.BQL($E16, "last(matches(px_last(dates=range(-1w,0d)), dayofweek(px_last(dates=range(-1w,0d)).date)==6))")="#N/A","-",_xll.BQL($E16, "last(matches(px_last(dates=range(-1w,0d)), dayofweek(px_last(dates=range(-1w,0d)).date)==6))"))} -> #NAME? | BA16: {=IF(_xll.BQL(E16,"first(last(matches(px_last(dates=range(-1M,0D)),dayofweek(px_last(dates=range(-1M,0D)).date)==6),2),1)")="#N/A","-",_xll.BQL(E16,"first(last(matches(px_last(dates=range(-1M,0D)),dayofweek(px_last(dates=range(-1M,0D)).date)==6),2),1)"))} -> #NAME? | BB16: =IF(ISERROR((AZ16/BA16-1)*100),"-",(AZ16/BA16-1)*100) -> -
E17: 9984 JP Equity | F17: ="SOFTB CDS JPY SR 5Y D14"&" BEST Curncy" -> SOFTB CDS JPY SR 5Y D14 BEST Curncy | G17: =AR17 -> #NAME? | J17: =_xll.BDP($E17,J$3) -> #NAME? | K17: =_xll.BDP($E17,K$3) -> #NAME? | L17: =IF(ISNUMBER(_xll.BDH($E17,"PX_LAST",TEXT($E$2,"YYYYMMDD"),TEXT($E$2,"YYYYMMDD"),"days=a","fill=p")),_xll.BDH($E17,"PX_LAST",TEXT($E$2,"YYYYMMDD"),TEXT($E$2,"YYYYMMDD"),"days=a","fill=p"),"-") -> - | M17: =IF(ISNUMBER(_xll.BDH($E17,"PX_LAST",TEXT($E$2-7,"YYYYMMDD"),TEXT($E$2-7,"YYYYMMDD"),"days=a","fill=p")),_xll.BDH($E17,"PX_LAST",TEXT($E$2-7,"YYYYMMDD"),TEXT($E$2-7,"YYYYMMDD"),"days=a","fill=p"),"-") -> - | N17: =IF(ISNUMBER(($L17-$M17)/$M17),($L17-$M17)/$M17,"-") -> - | O17: =IF(OR(_xll.BDP($E17,O$3)="#N/A N/A",_xll.BDP($E17,O$3)="#N/A Invalid Security"), "-", _xll.BDP($E17,O$3)) -> #NAME? | P17: =IF(ISNUMBER(_xll.BDH($F17,"PX_LAST",TEXT($E$2,"YYYYMMDD"),TEXT($E$2,"YYYYMMDD"),"days=a","fill=p")),_xll.BDH($F17,"PX_LAST",TEXT($E$2,"YYYYMMDD"),TEXT($E$2,"YYYYMMDD"),"days=a","fill=p"),"-") -> - | Q17: =IF(ISNUMBER(_xll.BDH($F17,"PX_LAST",TEXT($E$2-7,"YYYYMMDD"),TEXT($E$2-7,"YYYYMMDD"),"days=a","fill=p")),_xll.BDH($F17,"PX_LAST",TEXT($E$2-7,"YYYYMMDD"),TEXT($E$2-7,"YYYYMMDD"),"days=a","fill=p"),"-") -> - | R17: =IF(ISNUMBER($P17-$Q17),$P17-$Q17,"-") -> - | S17: =IF(ISNUMBER(_xll.BDP($F17,S$3)),_xll.BDP($F17,S$3),"-") -> - | T17: =IF(OR(AH17>0, AI17>0, AJ17>0, AK17>0, AL17>0, AM17>0), "Y"," ") -> #NAME? | U17: =IF(OR(_xll.BDP($E17,U$3)="#N/A N/A",_xll.BDP($E17,U$3)="#N/A Invalid Security"), "-", _xll.BDP($E17,U$3)) -> #NAME? | V17: =IF(OR(_xll.BDP($E17,V$2)="#N/A N/A",_xll.BDP($E17,V$2)="#N/A Invalid Security"), "-", _xll.BDP($E17,V$2)) -> #NAME? | W17: =IF(OR(_xll.BDP($E17,W$3)="#N/A N/A",_xll.BDP($E17,W$3)="#N/A Invalid Security"), "-", _xll.BDP($E17,W$3)) -> #NAME? | X17: =IF(OR(_xll.BDP($E17,X$3)="#N/A N/A",_xll.BDP($E17,X$3)="#N/A Invalid Security"), " ", _xll.BDP($E17,X$3)) -> #NAME? | Y17: =IF(OR(_xll.BDP($E17,Y$3)="#N/A N/A",_xll.BDP($E17,Y$3)="#N/A Invalid Security"), " ", _xll.BDP($E17,Y$3)) -> #NAME? | Z17: =IF(OR(_xll.BDP($E17,Z$3)="#N/A N/A",_xll.BDP($E17,Z$3)="#N/A Invalid Security"), " ", _xll.BDP($E17,Z$3)) -> #NAME? | AB17: BB+ | AC17: Ba3u | AD17: - | AE17: STABLE | AF17: POS | AH17: =IF(U17=AB17, 0,1) -> #NAME? | AI17: =IF(V17=AC17, 0,1) -> #NAME? | AJ17: =IF(W17=AD17, 0,1) -> #NAME? | AK17: =IF(X17=AE17, 0,1) -> #NAME? | AL17: =IF(Y17=AF17, 0,1) -> #NAME? | AM17: =IF(Z17=AG17, 0,1) -> #NAME? | AN17: =IF(SUM(AT17:AV17)>0,"Y","") | AO17: {=_xll.BDP($E17,"cur_mkt_cap")} -> #NAME? | AP17: {=_xll.BDP($E17,"crncy")} -> #NAME? | AQ17: {=_xll.BDP("USD"&AP17&" curncy","px_last")} -> #NAME? | AR17: =AO17/AQ17/1000000000 -> #NAME? | AT17: =IF(AND(AW17<=$E$1,AW17>=$F$1),1,"") | AU17: =IF(AND(AX17<=$E$1,AX17>=$F$1),1,"") | AV17: =IF(AND(AY17<=$E$1,AY17>=$F$1),1,"") | AW17: {=IF(ISERROR(DATEVALUE(_xll.BDP($E17,AW$6))),"",DATEVALUE(_xll.BDP($E17,AW$6)))} | AX17: {=IF(ISERROR(DATEVALUE(_xll.BDP($E17,AX$2))),"",DATEVALUE(_xll.BDP($E17,AX$2)))} | AY17: {=IF(ISERROR(DATEVALUE(_xll.BDP($E17,AY$6))),"",DATEVALUE(_xll.BDP($E17,AY$6)))} | AZ17: {=IF(_xll.BQL($E17, "last(matches(px_last(dates=range(-1w,0d)), dayofweek(px_last(dates=range(-1w,0d)).date)==6))")="#N/A","-",_xll.BQL($E17, "last(matches(px_last(dates=range(-1w,0d)), dayofweek(px_last(dates=range(-1w,0d)).date)==6))"))} -> #NAME? | BA17: {=IF(_xll.BQL(E17,"first(last(matches(px_last(dates=range(-1M,0D)),dayofweek(px_last(dates=range(-1M,0D)).date)==6),2),1)")="#N/A","-",_xll.BQL(E17,"first(last(matches(px_last(dates=range(-1M,0D)),dayofweek(px_last(dates=range(-1M,0D)).date)==6),2),1)"))} -> #NAME? | BB17: =IF(ISERROR((AZ17/BA17-1)*100),"-",(AZ17/BA17-1)*100) -> -
E18: CTL US Equity | F18: =_xll.BDP($E18,F$3)&" BEST Curncy" -> #NAME? | G18: =AR18 -> #NAME? | J18: =_xll.BDP($E18,J$3) -> #NAME? | K18: =_xll.BDP($E18,K$3) -> #NAME? | L18: =IF(ISNUMBER(_xll.BDH($E18,"PX_LAST",TEXT($E$2,"YYYYMMDD"),TEXT($E$2,"YYYYMMDD"),"days=a","fill=p")),_xll.BDH($E18,"PX_LAST",TEXT($E$2,"YYYYMMDD"),TEXT($E$2,"YYYYMMDD"),"days=a","fill=p"),"-") -> - | M18: =IF(ISNUMBER(_xll.BDH($E18,"PX_LAST",TEXT($E$2-7,"YYYYMMDD"),TEXT($E$2-7,"YYYYMMDD"),"days=a","fill=p")),_xll.BDH($E18,"PX_LAST",TEXT($E$2-7,"YYYYMMDD"),TEXT($E$2-7,"YYYYMMDD"),"days=a","fill=p"),"-") -> - | N18: =IF(ISNUMBER(($L18-$M18)/$M18),($L18-$M18)/$M18,"-") -> - | O18: =IF(OR(_xll.BDP($E18,O$3)="#N/A N/A",_xll.BDP($E18,O$3)="#N/A Invalid Security"), "-", _xll.BDP($E18,O$3)) -> #NAME? | P18: =IF(ISNUMBER(_xll.BDH($F18,"PX_LAST",TEXT($E$2,"YYYYMMDD"),TEXT($E$2,"YYYYMMDD"),"days=a","fill=p")),_xll.BDH($F18,"PX_LAST",TEXT($E$2,"YYYYMMDD"),TEXT($E$2,"YYYYMMDD"),"days=a","fill=p"),"-") -> - | Q18: =IF(ISNUMBER(_xll.BDH($F18,"PX_LAST",TEXT($E$2-7,"YYYYMMDD"),TEXT($E$2-7,"YYYYMMDD"),"days=a","fill=p")),_xll.BDH($F18,"PX_LAST",TEXT($E$2-7,"YYYYMMDD"),TEXT($E$2-7,"YYYYMMDD"),"days=a","fill=p"),"-") -> - | R18: =IF(ISNUMBER($P18-$Q18),$P18-$Q18,"-") -> - | S18: =IF(ISNUMBER(_xll.BDP($F18,S$3)),_xll.BDP($F18,S$3),"-") -> - | T18: =IF(OR(AH18>0, AI18>0, AJ18>0, AK18>0, AL18>0, AM18>0), "Y"," ") -> #NAME? | U18: =IF(OR(_xll.BDP($E18,U$3)="#N/A N/A",_xll.BDP($E18,U$3)="#N/A Invalid Security"), "-", _xll.BDP($E18,U$3)) -> #NAME? | V18: =IF(OR(_xll.BDP($E18,V$2)="#N/A N/A",_xll.BDP($E18,V$2)="#N/A Invalid Security"), "-", _xll.BDP($E18,V$2)) -> #NAME? | W18: =IF(OR(_xll.BDP($E18,W$3)="#N/A N/A",_xll.BDP($E18,W$3)="#N/A Invalid Security"), "-", _xll.BDP($E18,W$3)) -> #NAME? | X18: =IF(OR(_xll.BDP($E18,X$3)="#N/A N/A",_xll.BDP($E18,X$3)="#N/A Invalid Security"), " ", _xll.BDP($E18,X$3)) -> #NAME? | Y18: =IF(OR(_xll.BDP($E18,Y$3)="#N/A N/A",_xll.BDP($E18,Y$3)="#N/A Invalid Security"), " ", _xll.BDP($E18,Y$3)) -> #NAME? | Z18: =IF(OR(_xll.BDP($E18,Z$3)="#N/A N/A",_xll.BDP($E18,Z$3)="#N/A Invalid Security"), " ", _xll.BDP($E18,Z$3)) -> #NAME? | AB18: B- | AC18: B3 *+ | AD18: CCC+ *+ | AE18: STABLE | AH18: =IF(U18=AB18, 0,1) -> #NAME? | AI18: =IF(V18=AC18, 0,1) -> #NAME? | AJ18: =IF(W18=AD18, 0,1) -> #NAME? | AK18: =IF(X18=AE18, 0,1) -> #NAME? | AL18: =IF(Y18=AF18, 0,1) -> #NAME? | AM18: =IF(Z18=AG18, 0,1) -> #NAME? | AN18: =IF(SUM(AT18:AV18)>0,"Y","") | AO18: {=_xll.BDP($E18,"cur_mkt_cap")} -> #NAME? | AP18: {=_xll.BDP($E18,"crncy")} -> #NAME? | AQ18: {=_xll.BDP("USD"&AP18&" curncy","px_last")} -> #NAME? | AR18: =AO18/AQ18/1000000000 -> #NAME? | AT18: =IF(AND(AW18<=$E$1,AW18>=$F$1),1,"") | AU18: =IF(AND(AX18<=$E$1,AX18>=$F$1),1,"") | AV18: =IF(AND(AY18<=$E$1,AY18>=$F$1),1,"") | AW18: {=IF(ISERROR(DATEVALUE(_xll.BDP($E18,AW$6))),"",DATEVALUE(_xll.BDP($E18,AW$6)))} | AX18: {=IF(ISERROR(DATEVALUE(_xll.BDP($E18,AX$2))),"",DATEVALUE(_xll.BDP($E18,AX$2)))} | AY18: {=IF(ISERROR(DATEVALUE(_xll.BDP($E18,AY$6))),"",DATEVALUE(_xll.BDP($E18,AY$6)))} | AZ18: {=IF(_xll.BQL($E18, "last(matches(px_last(dates=range(-1w,0d)), dayofweek(px_last(dates=range(-1w,0d)).date)==6))")="#N/A","-",_xll.BQL($E18, "last(matches(px_last(dates=range(-1w,0d)), dayofweek(px_last(dates=range(-1w,0d)).date)==6))"))} -> #NAME? | BA18: {=IF(_xll.BQL(E18,"first(last(matches(px_last(dates=range(-1M,0D)),dayofweek(px_last(dates=range(-1M,0D)).date)==6),2),1)")="#N/A","-",_xll.BQL(E18,"first(last(matches(px_last(dates=range(-1M,0D)),dayofweek(px_last(dates=range(-1M,0D)).date)==6),2),1)"))} -> #NAME? | BB18: =IF(ISERROR((AZ18/BA18-1)*100),"-",(AZ18/BA18-1)*100) -> -
E19: T US Equity | F19: =_xll.BDP($E19,F$3)&" BEST Curncy" -> #NAME? | G19: =AR19 -> #NAME? | J19: =_xll.BDP($E19,J$3) -> #NAME? | K19: =_xll.BDP($E19,K$3) -> #NAME? | L19: =IF(ISNUMBER(_xll.BDH($E19,"PX_LAST",TEXT($E$2,"YYYYMMDD"),TEXT($E$2,"YYYYMMDD"),"days=a","fill=p")),_xll.BDH($E19,"PX_LAST",TEXT($E$2,"YYYYMMDD"),TEXT($E$2,"YYYYMMDD"),"days=a","fill=p"),"-") -> - | M19: =IF(ISNUMBER(_xll.BDH($E19,"PX_LAST",TEXT($E$2-7,"YYYYMMDD"),TEXT($E$2-7,"YYYYMMDD"),"days=a","fill=p")),_xll.BDH($E19,"PX_LAST",TEXT($E$2-7,"YYYYMMDD"),TEXT($E$2-7,"YYYYMMDD"),"days=a","fill=p"),"-") -> - | N19: =IF(ISNUMBER(($L19-$M19)/$M19),($L19-$M19)/$M19,"-") -> - | O19: =IF(OR(_xll.BDP($E19,O$3)="#N/A N/A",_xll.BDP($E19,O$3)="#N/A Invalid Security"), "-", _xll.BDP($E19,O$3)) -> #NAME? | P19: =IF(ISNUMBER(_xll.BDH($F19,"PX_LAST",TEXT($E$2,"YYYYMMDD"),TEXT($E$2,"YYYYMMDD"),"days=a","fill=p")),_xll.BDH($F19,"PX_LAST",TEXT($E$2,"YYYYMMDD"),TEXT($E$2,"YYYYMMDD"),"days=a","fill=p"),"-") -> - | Q19: =IF(ISNUMBER(_xll.BDH($F19,"PX_LAST",TEXT($E$2-7,"YYYYMMDD"),TEXT($E$2-7,"YYYYMMDD"),"days=a","fill=p")),_xll.BDH($F19,"PX_LAST",TEXT($E$2-7,"YYYYMMDD"),TEXT($E$2-7,"YYYYMMDD"),"days=a","fill=p"),"-") -> - | R19: =IF(ISNUMBER($P19-$Q19),$P19-$Q19,"-") -> - | S19: =IF(ISNUMBER(_xll.BDP($F19,S$3)),_xll.BDP($F19,S$3),"-") -> - | T19: =IF(OR(AH19>0, AI19>0, AJ19>0, AK19>0, AL19>0, AM19>0), "Y"," ") -> #NAME? | U19: =IF(OR(_xll.BDP($E19,U$3)="#N/A N/A",_xll.BDP($E19,U$3)="#N/A Invalid Security"), "-", _xll.BDP($E19,U$3)) -> #NAME? | V19: =IF(OR(_xll.BDP($E19,V$2)="#N/A N/A",_xll.BDP($E19,V$2)="#N/A Invalid Security"), "-", _xll.BDP($E19,V$2)) -> #NAME? | W19: =IF(OR(_xll.BDP($E19,W$3)="#N/A N/A",_xll.BDP($E19,W$3)="#N/A Invalid Security"), "-", _xll.BDP($E19,W$3)) -> #NAME? | X19: =IF(OR(_xll.BDP($E19,X$3)="#N/A N/A",_xll.BDP($E19,X$3)="#N/A Invalid Security"), " ", _xll.BDP($E19,X$3)) -> #NAME? | Y19: =IF(OR(_xll.BDP($E19,Y$3)="#N/A N/A",_xll.BDP($E19,Y$3)="#N/A Invalid Security"), " ", _xll.BDP($E19,Y$3)) -> #NAME? | Z19: =IF(OR(_xll.BDP($E19,Z$3)="#N/A N/A",_xll.BDP($E19,Z$3)="#N/A Invalid Security"), " ", _xll.BDP($E19,Z$3)) -> #NAME? | AB19: BBB | AC19: Baa2 | AD19: BBB+ | AE19: POS | AF19: STABLE | AG19: STABLE | AH19: =IF(U19=AB19, 0,1) -> #NAME? | AI19: =IF(V19=AC19, 0,1) -> #NAME? | AJ19: =IF(W19=AD19, 0,1) -> #NAME? | AK19: =IF(X19=AE19, 0,1) -> #NAME? | AL19: =IF(Y19=AF19, 0,1) -> #NAME? | AM19: =IF(Z19=AG19, 0,1) -> #NAME? | AN19: =IF(SUM(AT19:AV19)>0,"Y","") | AO19: {=_xll.BDP($E19,"cur_mkt_cap")} -> #NAME? | AP19: {=_xll.BDP($E19,"crncy")} -> #NAME? | AQ19: {=_xll.BDP("USD"&AP19&" curncy","px_last")} -> #NAME? | AR19: =AO19/AQ19/1000000000 -> #NAME? | AT19: =IF(AND(AW19<=$E$1,AW19>=$F$1),1,"") | AU19: =IF(AND(AX19<=$E$1,AX19>=$F$1),1,"") | AV19: =IF(AND(AY19<=$E$1,AY19>=$F$1),1,"") | AW19: {=IF(ISERROR(DATEVALUE(_xll.BDP($E19,AW$6))),"",DATEVALUE(_xll.BDP($E19,AW$6)))} | AX19: {=IF(ISERROR(DATEVALUE(_xll.BDP($E19,AX$2))),"",DATEVALUE(_xll.BDP($E19,AX$2)))} | AY19: {=IF(ISERROR(DATEVALUE(_xll.BDP($E19,AY$6))),"",DATEVALUE(_xll.BDP($E19,AY$6)))} | AZ19: {=IF(_xll.BQL($E19, "last(matches(px_last(dates=range(-1w,0d)), dayofweek(px_last(dates=range(-1w,0d)).date)==6))")="#N/A","-",_xll.BQL($E19, "last(matches(px_last(dates=range(-1w,0d)), dayofweek(px_last(dates=range(-1w,0d)).date)==6))"))} -> #NAME? | BA19: {=IF(_xll.BQL(E19,"first(last(matches(px_last(dates=range(-1M,0D)),dayofweek(px_last(dates=range(-1M,0D)).date)==6),2),1)")="#N/A","-",_xll.BQL(E19,"first(last(matches(px_last(dates=range(-1M,0D)),dayofweek(px_last(dates=range(-1M,0D)).date)==6),2),1)"))} -> #NAME? | BB19: =IF(ISERROR((AZ19/BA19-1)*100),"-",(AZ19/BA19-1)*100) -> -
